Workbook
Name SegmentaçãodeDados_Ano: #N/A
Name SegmentaçãodeDados_Ano1: #N/A
Name SegmentaçãodeDados_ano2: #N/A
Name SegmentaçãodeDados_Mês: #N/A
Name SegmentaçãodeDados_mes_nome: #N/A
Name SegmentaçãodeDados_Mês1: #N/A
Name SegmentaçãodeDados_tipo_atividade: #N/A
Name SegmentaçãodeDados_Tipo_de_Projeto: #N/A
Name SegmentaçãodeDados_Tipo_de_Projeto1: #N/A

Sheet PROJETOS
A4: ID | B4: Projeto | C4: Descrição | D4: Prioridade | E4: Responsável | F4: FTEs | G4: Valor previsto | H4: Valor gasto | I4: Data Início Planej. | J4: Data Fim Planej. | K4: Data de início | L4: Data Fim Real | M4: Total de tarefas | N4: Tarefas Concluídas | O4: Tarefas em andamento | P4: Tarefas atrasadas | Q4: Tarefas não iniciadas | R4: Status | S4: % de Conclusão
A5: 1 | B5: GAB TUBO SUPERIOR 21, 27 E 35 (980102670500) | C5: Projeto Gabarito Tubo Superior 21,27 e 35 | D5: 3- Alta | E5: Evandro | F5: 1 | G5: 0 | H5: 0 | I5: 45355 | J5: 45381 | K5: =IF(Base_Projetos[[#This Row],[Total de tarefas]]=Base_Projetos[[#This Row],[Tarefas não iniciadas]],"Não iniciado",_xlfn.MINIFS(TAREFAS!H:H,TAREFAS!B:B,Base_Projetos[[#This Row],[Projeto]])) -> 45381 | L5: 45382 | M5: =SUM(Base_Projetos[[#This Row],[Tarefas Concluídas]:[Tarefas não iniciadas]]) -> 3 | N5: =COUNTIFS(tbl_PlanilhaB[Projeto],Base_Projetos[[#This Row],[Projeto]],tbl_PlanilhaB[Status],"Concluído") -> 3 | O5: =COUNTIFS(tbl_PlanilhaB[Projeto],Base_Projetos[[#This Row],[Projeto]],tbl_PlanilhaB[Status],"Em andamento") -> 0 | P5: =COUNTIFS(tbl_PlanilhaB[Projeto],Base_Projetos[[#This Row],[Projeto]],tbl_PlanilhaB[Status],"Atrasado") -> 0 | Q5: =COUNTIFS(tbl_PlanilhaB[Projeto],Base_Projetos[[#This Row],[Projeto]],tbl_PlanilhaB[Status],"Não iniciado") -> 0 | R5: =IF(Base_Projetos[[#This Row],[Total de tarefas]]=Base_Projetos[[#This Row],[Tarefas Concluídas]],"Concluído",IF(Base_Projetos[[#This Row],[Tarefas não iniciadas]]=Base_Projetos[[#This Row],[Total de tarefas]],"Não iniciado",IF(Base_Projetos[[#This Row],[Tarefas atrasadas]]>0,"Atrasado","Em andamento"))) -> Concluído | S5: =Base_Projetos[[#This Row],[Tarefas Concluídas]]/Base_Projetos[[#This Row],[Total de tarefas]] -> 1
A6: =A5+1 -> 2 | B6: GAB ESCADA MAIOR 13, 16, 21, 25T, 32 E 35 (980102640200) | C6: Projeto Gabarito Tubo Superior 13, 16, 21, 25T, 32 E 35 | D6: 3- Alta | E6: Evandro | F6: 1 | G6: =SUMIF(tbl_PlanilhaB[Projeto],Base_Projetos[[#This Row],[Projeto]],tbl_PlanilhaB[Valor previsto]) -> 0 | H6: =SUMIF(tbl_PlanilhaB[Projeto],Base_Projetos[[#This Row],[Projeto]],tbl_PlanilhaB[Valor gasto]) -> 0 | I6: 45355 | J6: 45381 | K6: =IF(Base_Projetos[[#This Row],[Total de tarefas]]=Base_Projetos[[#This Row],[Tarefas não iniciadas]],"Não iniciado",_xlfn.MINIFS(TAREFAS!H:H,TAREFAS!B:B,Base_Projetos[[#This Row],[Projeto]])) -> 45381 | L6: 45382 | M6: =SUM(Base_Projetos[[#This Row],[Tarefas Concluídas]:[Tarefas não iniciadas]]) -> 3 | N6: =COUNTIFS(tbl_PlanilhaB[Projeto],Base_Projetos[[#This Row],[Projeto]],tbl_PlanilhaB[Status],"Concluído") -> 2 | O6: =COUNTIFS(tbl_PlanilhaB[Projeto],Base_Projetos[[#This Row],[Projeto]],tbl_PlanilhaB[Status],"Em andamento") -> 0 | P6: =COUNTIFS(tbl_PlanilhaB[Projeto],Base_Projetos[[#This Row],[Projeto]],tbl_PlanilhaB[Status],"Atrasado") -> 0 | Q6: =COUNTIFS(tbl_PlanilhaB[Projeto],Base_Projetos[[#This Row],[Projeto]],tbl_PlanilhaB[Status],"Não iniciado") -> 1 | R6: =IF(Base_Projetos[[#This Row],[Total de tarefas]]=Base_Projetos[[#This Row],[Tarefas Concluídas]],"Concluído",IF(Base_Projetos[[#This Row],[Tarefas não iniciadas]]=Base_Projetos[[#This Row],[Total de tarefas]],"Não iniciado",IF(Base_Projetos[[#This Row],[Tarefas atrasadas]]>0,"Atrasado","Em andamento"))) -> Em andamento | S6: =Base_Projetos[[#This Row],[Tarefas Concluídas]]/Base_Projetos[[#This Row],[Total de tarefas]] -> 0.66666667
A7: =A6+1 -> 3 | B7: Gabarito Chassi 21000 | C7: Projeto Gabarito Chassi 21000 | D7: 3- Alta | E7: Evandro | F7: 1 | G7: =SUMIF(tbl_PlanilhaB[Projeto],Base_Projetos[[#This Row],[Projeto]],tbl_PlanilhaB[Valor previsto]) -> 0 | H7: =SUMIF(tbl_PlanilhaB[Projeto],Base_Projetos[[#This Row],[Projeto]],tbl_PlanilhaB[Valor gasto]) -> 0 | I7: 45231 | J7: 45245 | K7: =IF(Base_Projetos[[#This Row],[Total de tarefas]]=Base_Projetos[[#This Row],[Tarefas não iniciadas]],"Não iniciado",_xlfn.MINIFS(TAREFAS!H:H,TAREFAS!B:B,Base_Projetos[[#This Row],[Projeto]])) -> 45231 | L7: 45245 | M7: =SUM(Base_Projetos[[#This Row],[Tarefas Concluídas]:[Tarefas não iniciadas]]) -> 3 | N7: =COUNTIFS(tbl_PlanilhaB[Projeto],Base_Projetos[[#This Row],[Projeto]],tbl_PlanilhaB[Status],"Concluído") -> 3 | O7: =COUNTIFS(tbl_PlanilhaB[Projeto],Base_Projetos[[#This Row],[Projeto]],tbl_PlanilhaB[Status],"Em andamento") -> 0 | P7: =COUNTIFS(tbl_PlanilhaB[Projeto],Base_Projetos[[#This Row],[Projeto]],tbl_PlanilhaB[Status],"Atrasado") -> 0 | Q7: =COUNTIFS(tbl_PlanilhaB[Projeto],Base_Projetos[[#This Row],[Projeto]],tbl_PlanilhaB[Status],"Não iniciado") -> 0 | R7: =IF(Base_Projetos[[#This Row],[Total de tarefas]]=Base_Projetos[[#This Row],[Tarefas Concluídas]],"Concluído",IF(Base_Projetos[[#This Row],[Tarefas não iniciadas]]=Base_Projetos[[#This Row],[Total de tarefas]],"Não iniciado",IF(Base_Projetos[[#This Row],[Tarefas atrasadas]]>0,"Atrasado","Em andamento"))) -> Concluído | S7: =Base_Projetos[[#This Row],[Tarefas Concluídas]]/Base_Projetos[[#This Row],[Total de tarefas]] -> 1
A8: =A7+1 -> 4 | B8: Gabarito Caixa Coletora 27000 | C8: Projetar Gabarito Caixa coletora 27000 | D8: 3- Alta | E8: Evandro | F8: 1 | G8: =SUMIF(tbl_PlanilhaB[Projeto],Base_Projetos[[#This Row],[Projeto]],tbl_PlanilhaB[Valor previsto]) -> 0 | H8: =SUMIF(tbl_PlanilhaB[Projeto],Base_Projetos[[#This Row],[Projeto]],tbl_PlanilhaB[Valor gasto]) -> 0 | I8: =_xlfn.MINIFS(TAREFAS!E:E,TAREFAS!B:B,Base_Projetos[[#This Row],[Projeto]]) -> 45232 | J8: =_xlfn.MAXIFS(TAREFAS!G:G,TAREFAS!B:B,Base_Projetos[[#This Row],[Projeto]]) -> 45246 | K8: =IF(Base_Projetos[[#This Row],[Total de tarefas]]=Base_Projetos[[#This Row],[Tarefas não iniciadas]],"Não iniciado",_xlfn.MINIFS(TAREFAS!H:H,TAREFAS!B:B,Base_Projetos[[#This Row],[Projeto]])) -> 45232 | L8: =IF(Base_Projetos[[#This Row],[Total de tarefas]]=Base_Projetos[[#This Row],[Tarefas Concluídas]],_xlfn.MAXIFS(TAREFAS!H:H,TAREFAS!B:B,Base_Projetos[[#This Row],[Projeto]]),IF(Base_Projetos[[#This Row],[Total de tarefas]]=Base_Projetos[[#This Row],[Tarefas não iniciadas]],"Não iniciado","Em andamento")) -> 45232 | M8: =SUM(Base_Projetos[[#This Row],[Tarefas Concluídas]:[Tarefas não iniciadas]]) -> 1 | N8: =COUNTIFS(tbl_PlanilhaB[Projeto],Base_Projetos[[#This Row],[Projeto]],tbl_PlanilhaB[Status],"Concluído") -> 1 | O8: =COUNTIFS(tbl_PlanilhaB[Projeto],Base_Projetos[[#This Row],[Projeto]],tbl_PlanilhaB[Status],"Em andamento") -> 0 | P8: =COUNTIFS(tbl_PlanilhaB[Projeto],Base_Projetos[[#This Row],[Projeto]],tbl_PlanilhaB[Status],"Atrasado") -> 0 | Q8: =COUNTIFS(tbl_PlanilhaB[Projeto],Base_Projetos[[#This Row],[Projeto]],tbl_PlanilhaB[Status],"Não iniciado") -> 0 | R8: =IF(Base_Projetos[[#This Row],[Total de tarefas]]=Base_Projetos[[#This Row],[Tarefas Concluídas]],"Concluído",IF(Base_Projetos[[#This Row],[Tarefas não iniciadas]]=Base_Projetos[[#This Row],[Total de tarefas]],"Não iniciado",IF(Base_Projetos[[#This Row],[Tarefas atrasadas]]>0,"Atrasado","Em andamento"))) -> Concluído | S8: =Base_Projetos[[#This Row],[Tarefas Concluídas]]/Base_Projetos[[#This Row],[Total de tarefas]] -> 1
A9: =A8+1 -> 5 | B9: Gabarito Chassi 27000 | C9: Projetar Gabarito Chassi 27000 | D9: 3- Alta | E9: Evandro | F9: 1 | G9: =SUMIF(tbl_PlanilhaB[Projeto],Base_Projetos[[#This Row],[Projeto]],tbl_PlanilhaB[Valor previsto]) -> 0 | H9: =SUMIF(tbl_PlanilhaB[Projeto],Base_Projetos[[#This Row],[Projeto]],tbl_PlanilhaB[Valor gasto]) -> 0 | I9: =_xlfn.MINIFS(TAREFAS!E:E,TAREFAS!B:B,Base_Projetos[[#This Row],[Projeto]]) -> 45243 | J9: =_xlfn.MAXIFS(TAREFAS!G:G,TAREFAS!B:B,Base_Projetos[[#This Row],[Projeto]]) -> 45257 | K9: =IF(Base_Projetos[[#This Row],[Total de tarefas]]=Base_Projetos[[#This Row],[Tarefas não iniciadas]],"Não iniciado",_xlfn.MINIFS(TAREFAS!H:H,TAREFAS!B:B,Base_Projetos[[#This Row],[Projeto]])) -> 45243 | L9: =IF(Base_Projetos[[#This Row],[Total de tarefas]]=Base_Projetos[[#This Row],[Tarefas Concluídas]],_xlfn.MAXIFS(TAREFAS!H:H,TAREFAS!B:B,Base_Projetos[[#This Row],[Projeto]]),IF(Base_Projetos[[#This Row],[Total de tarefas]]=Base_Projetos[[#This Row],[Tarefas não iniciadas]],"Não iniciado","Em andamento")) -> 45243 | M9: =SUM(Base_Projetos[[#This Row],[Tarefas Concluídas]:[Tarefas não iniciadas]]) -> 1 | N9: =COUNTIFS(tbl_PlanilhaB[Projeto],Base_Projetos[[#This Row],[Projeto]],tbl_PlanilhaB[Status],"Concluído") -> 1 | O9: =COUNTIFS(tbl_PlanilhaB[Projeto],Base_Projetos[[#This Row],[Projeto]],tbl_PlanilhaB[Status],"Em andamento") -> 0 | P9: =COUNTIFS(tbl_PlanilhaB[Projeto],Base_Projetos[[#This Row],[Projeto]],tbl_PlanilhaB[Status],"Atrasado") -> 0 | Q9: =COUNTIFS(tbl_PlanilhaB[Projeto],Base_Projetos[[#This Row],[Projeto]],tbl_PlanilhaB[Status],"Não iniciado") -> 0 | R9: =IF(Base_Projetos[[#This Row],[Total de tarefas]]=Base_Projetos[[#This Row],[Tarefas Concluídas]],"Concluído",IF(Base_Projetos[[#This Row],[Tarefas não iniciadas]]=Base_Projetos[[#This Row],[Total de tarefas]],"Não iniciado",IF(Base_Projetos[[#This Row],[Tarefas atrasadas]]>0,"Atrasado","Em andamento"))) -> Concluído | S9: =Base_Projetos[[#This Row],[Tarefas Concluídas]]/Base_Projetos[[#This Row],[Total de tarefas]] -> 1
A10: =A9+1 -> 6 | B10: Gabarito Reforço Frontal 27000 | C10: Projetar Gabarito Reforço Frontal 27000 | D10: 3- Alta | E10: Fabricio | F10: 1 | G10: =SUMIF(tbl_PlanilhaB[Projeto],Base_Projetos[[#This Row],[Projeto]],tbl_PlanilhaB[Valor previsto]) -> 0 | H10: =SUMIF(tbl_PlanilhaB[Projeto],Base_Projetos[[#This Row],[Projeto]],tbl_PlanilhaB[Valor gasto]) -> 0 | I10: =_xlfn.MINIFS(TAREFAS!E:E,TAREFAS!B:B,Base_Projetos[[#This Row],[Projeto]]) -> 45237 | J10: =_xlfn.MAXIFS(TAREFAS!G:G,TAREFAS!B:B,Base_Projetos[[#This Row],[Projeto]]) -> 45258 | K10: =IF(Base_Projetos[[#This Row],[Total de tarefas]]=Base_Projetos[[#This Row],[Tarefas não iniciadas]],"Não iniciado",_xlfn.MINIFS(TAREFAS!H:H,TAREFAS!B:B,Base_Projetos[[#This Row],[Projeto]])) -> 45237 | L10: =IF(Base_Projetos[[#This Row],[Total de tarefas]]=Base_Projetos[[#This Row],[Tarefas Concluídas]],_xlfn.MAXIFS(TAREFAS!H:H,TAREFAS!B:B,Base_Projetos[[#This Row],[Projeto]]),IF(Base_Projetos[[#This Row],[Total de tarefas]]=Base_Projetos[[#This Row],[Tarefas não iniciadas]],"Não iniciado","Em andamento")) -> 45237 | M10: =SUM(Base_Projetos[[#This Row],[Tarefas Concluídas]:[Tarefas não iniciadas]]) -> 1 | N10: =COUNTIFS(tbl_PlanilhaB[Projeto],Base_Projetos[[#This Row],[Projeto]],tbl_PlanilhaB[Status],"Concluído") -> 1 | O10: =COUNTIFS(tbl_PlanilhaB[Projeto],Base_Projetos[[#This Row],[Projeto]],tbl_PlanilhaB[Status],"Em andamento") -> 0 | P10: =COUNTIFS(tbl_PlanilhaB[Projeto],Base_Projetos[[#This Row],[Projeto]],tbl_PlanilhaB[Status],"Atrasado") -> 0 | Q10: =COUNTIFS(tbl_PlanilhaB[Projeto],Base_Projetos[[#This Row],[Projeto]],tbl_PlanilhaB[Status],"Não iniciado") -> 0 | R10: =IF(Base_Projetos[[#This Row],[Total de tarefas]]=Base_Projetos[[#This Row],[Tarefas Concluídas]],"Concluído",IF(Base_Projetos[[#This Row],[Tarefas não iniciadas]]=Base_Projetos[[#This Row],[Total de tarefas]],"Não iniciado",IF(Base_Projetos[[#This Row],[Tarefas atrasadas]]>0,"Atrasado","Em andamento"))) -> Concluído | S10: =Base_Projetos[[#This Row],[Tarefas Concluídas]]/Base_Projetos[[#This Row],[Total de tarefas]] -> 1
A11: =A10+1 -> 7 | B11: Gabarito Reforço traseiro 27000 | C11: Projetar Gabarito Reforço Traseiro 27000 | D11: 3- Alta | E11: Fabricio | F11: 1 | G11: =SUMIF(tbl_PlanilhaB[Projeto],Base_Projetos[[#This Row],[Projeto]],tbl_PlanilhaB[Valor previsto]) -> 0 | H11: =SUMIF(tbl_PlanilhaB[Projeto],Base_Projetos[[#This Row],[Projeto]],tbl_PlanilhaB[Valor gasto]) -> 0 | I11: =_xlfn.MINIFS(TAREFAS!E:E,TAREFAS!B:B,Base_Projetos[[#This Row],[Projeto]]) -> 45247 | J11: =_xlfn.MAXIFS(TAREFAS!G:G,TAREFAS!B:B,Base_Projetos[[#This Row],[Projeto]]) -> 45268 | K11: =IF(Base_Projetos[[#This Row],[Total de tarefas]]=Base_Projetos[[#This Row],[Tarefas não iniciadas]],"Não iniciado",_xlfn.MINIFS(TAREFAS!H:H,TAREFAS!B:B,Base_Projetos[[#This Row],[Projeto]])) -> 45247 | L11: =IF(Base_Projetos[[#This Row],[Total de tarefas]]=Base_Projetos[[#This Row],[Tarefas Concluídas]],_xlfn.MAXIFS(TAREFAS!H:H,TAREFAS!B:B,Base_Projetos[[#This Row],[Projeto]]),IF(Base_Projetos[[#This Row],[Total de tarefas]]=Base_Projetos[[#This Row],[Tarefas não iniciadas]],"Não iniciado","Em andamento")) -> 45247 | M11: =SUM(Base_Projetos[[#This Row],[Tarefas Concluídas]:[Tarefas não iniciadas]]) -> 1 | N11: =COUNTIFS(tbl_PlanilhaB[Projeto],Base_Projetos[[#This Row],[Projeto]],tbl_PlanilhaB[Status],"Concluído") -> 1 | O11: =COUNTIFS(tbl_PlanilhaB[Projeto],Base_Projetos[[#This Row],[Projeto]],tbl_PlanilhaB[Status],"Em andamento") -> 0 | P11: =COUNTIFS(tbl_PlanilhaB[Projeto],Base_Projetos[[#This Row],[Projeto]],tbl_PlanilhaB[Status],"Atrasado") -> 0 | Q11: =COUNTIFS(tbl_PlanilhaB[Projeto],Base_Projetos[[#This Row],[Projeto]],tbl_PlanilhaB[Status],"Não iniciado") -> 0 | R11: =IF(Base_Projetos[[#This Row],[Total de tarefas]]=Base_Projetos[[#This Row],[Tarefas Concluídas]],"Concluído",IF(Base_Projetos[[#This Row],[Tarefas não iniciadas]]=Base_Projetos[[#This Row],[Total de tarefas]],"Não iniciado",IF(Base_Projetos[[#This Row],[Tarefas atrasadas]]>0,"Atrasado","Em andamento"))) -> Concluído | S11: =Base_Projetos[[#This Row],[Tarefas Concluídas]]/Base_Projetos[[#This Row],[Total de tarefas]] -> 1
A12: =A11+1 -> 8 | B12: Gabarito Reforço Lateral 27000 | C12: Projetar Gabarito Reforço Lateral 27000 | D12: 3- Alta | E12: Fabricio | F12: 1 | G12: =SUMIF(tbl_PlanilhaB[Projeto],Base_Projetos[[#This Row],[Projeto]],tbl_PlanilhaB[Valor previsto]) -> 0 | H12: =SUMIF(tbl_PlanilhaB[Projeto],Base_Projetos[[#This Row],[Projeto]],tbl_PlanilhaB[Valor gasto]) -> 0 | I12: =_xlfn.MINIFS(TAREFAS!E:E,TAREFAS!B:B,Base_Projetos[[#This Row],[Projeto]]) -> 45254 | J12: =_xlfn.MAXIFS(TAREFAS!G:G,TAREFAS!B:B,Base_Projetos[[#This Row],[Projeto]]) -> 45268 | K12: =IF(Base_Projetos[[#This Row],[Total de tarefas]]=Base_Projetos[[#This Row],[Tarefas não iniciadas]],"Não iniciado",_xlfn.MINIFS(TAREFAS!H:H,TAREFAS!B:B,Base_Projetos[[#This Row],[Projeto]])) -> 45254 | L12: =IF(Base_Projetos[[#This Row],[Total de tarefas]]=Base_Projetos[[#This Row],[Tarefas Concluídas]],_xlfn.MAXIFS(TAREFAS!H:H,TAREFAS!B:B,Base_Projetos[[#This Row],[Projeto]]),IF(Base_Projetos[[#This Row],[Total de tarefas]]=Base_Projetos[[#This Row],[Tarefas não iniciadas]],"Não iniciado","Em andamento")) -> 45254 | M12: =SUM(Base_Projetos[[#This Row],[Tarefas Concluídas]:[Tarefas não iniciadas]]) -> 1 | N12: =COUNTIFS(tbl_PlanilhaB[Projeto],Base_Projetos[[#This Row],[Projeto]],tbl_PlanilhaB[Status],"Concluído") -> 1 | O12: =COUNTIFS(tbl_PlanilhaB[Projeto],Base_Projetos[[#This Row],[Projeto]],tbl_PlanilhaB[Status],"Em andamento") -> 0 | P12: =COUNTIFS(tbl_PlanilhaB[Projeto],Base_Projetos[[#This Row],[Projeto]],tbl_PlanilhaB[Status],"Atrasado") -> 0 | Q12: =COUNTIFS(tbl_PlanilhaB[Projeto],Base_Projetos[[#This Row],[Projeto]],tbl_PlanilhaB[Status],"Não iniciado") -> 0 | R12: =IF(Base_Projetos[[#This Row],[Total de tarefas]]=Base_Projetos[[#This Row],[Tarefas Concluídas]],"Concluído",IF(Base_Projetos[[#This Row],[Tarefas não iniciadas]]=Base_Projetos[[#This Row],[Total de tarefas]],"Não iniciado",IF(Base_Projetos[[#This Row],[Tarefas atrasadas]]>0,"Atrasado","Em andamento"))) -> Concluído | S12: =Base_Projetos[[#This Row],[Tarefas Concluídas]]/Base_Projetos[[#This Row],[Total de tarefas]] -> 1
A13: =A12+1 -> 9 | B13: Gabarito Caixa Coletora 21000 | C13: Projetar Gabarito Caixa Coletora 21000 | D13: 3- Alta | E13: Evandro | F13: 1 | G13: =SUMIF(tbl_PlanilhaB[Projeto],Base_Projetos[[#This Row],[Projeto]],tbl_PlanilhaB[Valor previsto]) -> 0 | H13: =SUMIF(tbl_PlanilhaB[Projeto],Base_Projetos[[#This Row],[Projeto]],tbl_PlanilhaB[Valor gasto]) -> 0 | I13: =_xlfn.MINIFS(TAREFAS!E:E,TAREFAS!B:B,Base_Projetos[[#This Row],[Projeto]]) -> 45020 | J13: =_xlfn.MAXIFS(TAREFAS!G:G,TAREFAS!B:B,Base_Projetos[[#This Row],[Projeto]]) -> 45275 | K13: =IF(Base_Projetos[[#This Row],[Total de tarefas]]=Base_Projetos[[#This Row],[Tarefas não iniciadas]],"Não iniciado",_xlfn.MINIFS(TAREFAS!H:H,TAREFAS!B:B,Base_Projetos[[#This Row],[Projeto]])) -> 45020 | L13: =IF(Base_Projetos[[#This Row],[Total de tarefas]]=Base_Projetos[[#This Row],[Tarefas Concluídas]],_xlfn.MAXIFS(TAREFAS!H:H,TAREFAS!B:B,Base_Projetos[[#This Row],[Projeto]]),IF(Base_Projetos[[#This Row],[Total de tarefas]]=Base_Projetos[[#This Row],[Tarefas não iniciadas]],"Não iniciado","Em andamento")) -> 45261 | M13: =SUM(Base_Projetos[[#This Row],[Tarefas Concluídas]:[Tarefas não iniciadas]]) -> 2 | N13: =COUNTIFS(tbl_PlanilhaB[Projeto],Base_Projetos[[#This Row],[Projeto]],tbl_PlanilhaB[Status],"Concluído") -> 2 | O13: =COUNTIFS(tbl_PlanilhaB[Projeto],Base_Projetos[[#This Row],[Projeto]],tbl_PlanilhaB[Status],"Em andamento") -> 0 | P13: =COUNTIFS(tbl_PlanilhaB[Projeto],Base_Projetos[[#This Row],[Projeto]],tbl_PlanilhaB[Status],"Atrasado") -> 0 | Q13: =COUNTIFS(tbl_PlanilhaB[Projeto],Base_Projetos[[#This Row],[Projeto]],tbl_PlanilhaB[Status],"Não iniciado") -> 0 | R13: =IF(Base_Projetos[[#This Row],[Total de tarefas]]=Base_Projetos[[#This Row],[Tarefas Concluídas]],"Concluído",IF(Base_Projetos[[#This Row],[Tarefas não iniciadas]]=Base_Projetos[[#This Row],[Total de tarefas]],"Não iniciado",IF(Base_Projetos[[#This Row],[Tarefas atrasadas]]>0,"Atrasado","Em andamento"))) -> Concluído | S13: =Base_Projetos[[#This Row],[Tarefas Concluídas]]/Base_Projetos[[#This Row],[Total de tarefas]] -> 1
A14: =A13+1 -> 10 | B14: Gabarito Funil 27000 | C14: Projetar Gabarito Funil 27000 | D14: 3- Alta | E14: Fabricio | F14: 1 | G14: =SUMIF(tbl_PlanilhaB[Projeto],Base_Projetos[[#This Row],[Projeto]],tbl_PlanilhaB[Valor previsto]) -> 0 | H14: =SUMIF(tbl_PlanilhaB[Projeto],Base_Projetos[[#This Row],[Projeto]],tbl_PlanilhaB[Valor gasto]) -> 0 | I14: =_xlfn.MINIFS(TAREFAS!E:E,TAREFAS!B:B,Base_Projetos[[#This Row],[Projeto]]) -> 45264 | J14: =_xlfn.MAXIFS(TAREFAS!G:G,TAREFAS!B:B,Base_Projetos[[#This Row],[Projeto]]) -> 45285 | K14: =IF(Base_Projetos[[#This Row],[Total de tarefas]]=Base_Projetos[[#This Row],[Tarefas não iniciadas]],"Não iniciado",_xlfn.MINIFS(TAREFAS!H:H,TAREFAS!B:B,Base_Projetos[[#This Row],[Projeto]])) -> 45264 | L14: =IF(Base_Projetos[[#This Row],[Total de tarefas]]=Base_Projetos[[#This Row],[Tarefas Concluídas]],_xlfn.MAXIFS(TAREFAS!H:H,TAREFAS!B:B,Base_Projetos[[#This Row],[Projeto]]),IF(Base_Projetos[[#This Row],[Total de tarefas]]=Base_Projetos[[#This Row],[Tarefas não iniciadas]],"Não iniciado","Em andamento")) -> 45264 | M14: =SUM(Base_Projetos[[#This Row],[Tarefas Concluídas]:[Tarefas não iniciadas]]) -> 1 | N14: =COUNTIFS(tbl_PlanilhaB[Projeto],Base_Projetos[[#This Row],[Projeto]],tbl_PlanilhaB[Status],"Concluído") -> 1 | O14: =COUNTIFS(tbl_PlanilhaB[Projeto],Base_Projetos[[#This Row],[Projeto]],tbl_PlanilhaB[Status],"Em andamento") -> 0 | P14: =COUNTIFS(tbl_PlanilhaB[Projeto],Base_Projetos[[#This Row],[Projeto]],tbl_PlanilhaB[Status],"Atrasado") -> 0 | Q14: =COUNTIFS(tbl_PlanilhaB[Projeto],Base_Projetos[[#This Row],[Projeto]],tbl_PlanilhaB[Status],"Não iniciado") -> 0 | R14: =IF(Base_Projetos[[#This Row],[Total de tarefas]]=Base_Projetos[[#This Row],[Tarefas Concluídas]],"Concluído",IF(Base_Projetos[[#This Row],[Tarefas não iniciadas]]=Base_Projetos[[#This Row],[Total de tarefas]],"Não iniciado",IF(Base_Projetos[[#This Row],[Tarefas atrasadas]]>0,"Atrasado","Em andamento"))) -> Concluído | S14: =Base_Projetos[[#This Row],[Tarefas Concluídas]]/Base_Projetos[[#This Row],[Total de tarefas]] -> 1
A15: =A14+1 -> 11 | B15: Gabarito Chassi Rob 440/480 | C15: Projetar Gabarito Chassi Rob 440/480 | D15: 3- Alta | E15: Fabricio | F15: 1 | G15: =SUMIF(tbl_PlanilhaB[Projeto],Base_Projetos[[#This Row],[Projeto]],tbl_PlanilhaB[Valor previsto]) -> 0 | H15: =SUMIF(tbl_PlanilhaB[Projeto],Base_Projetos[[#This Row],[Projeto]],tbl_PlanilhaB[Valor gasto]) -> 0 | I15: =_xlfn.MINIFS(TAREFAS!E:E,TAREFAS!B:B,Base_Projetos[[#This Row],[Projeto]]) -> 45267 | J15: =_xlfn.MAXIFS(TAREFAS!G:G,TAREFAS!B:B,Base_Projetos[[#This Row],[Projeto]]) -> 45407 | K15: =IF(Base_Projetos[[#This Row],[Total de tarefas]]=Base_Projetos[[#This Row],[Tarefas não iniciadas]],"Não iniciado",_xlfn.MINIFS(TAREFAS!H:H,TAREFAS!B:B,Base_Projetos[[#This Row],[Projeto]])) -> 45267 | L15: =IF(Base_Projetos[[#This Row],[Total de tarefas]]=Base_Projetos[[#This Row],[Tarefas Concluídas]],_xlfn.MAXIFS(TAREFAS!H:H,TAREFAS!B:B,Base_Projetos[[#This Row],[Projeto]]),IF(Base_Projetos[[#This Row],[Total de tarefas]]=Base_Projetos[[#This Row],[Tarefas não iniciadas]],"Não iniciado","Em andamento")) -> 45406 | M15: =SUM(Base_Projetos[[#This Row],[Tarefas Concluídas]:[Tarefas não iniciadas]]) -> 2 | N15: =COUNTIFS(tbl_PlanilhaB[Projeto],Base_Projetos[[#This Row],[Projeto]],tbl_PlanilhaB[Status],"Concluído") -> 2 | O15: =COUNTIFS(tbl_PlanilhaB[Projeto],Base_Projetos[[#This Row],[Projeto]],tbl_PlanilhaB[Status],"Em andamento") -> 0 | P15: =COUNTIFS(tbl_PlanilhaB[Projeto],Base_Projetos[[#This Row],[Projeto]],tbl_PlanilhaB[Status],"Atrasado") -> 0 | Q15: =COUNTIFS(tbl_PlanilhaB[Projeto],Base_Projetos[[#This Row],[Projeto]],tbl_PlanilhaB[Status],"Não iniciado") -> 0 | R15: =IF(Base_Projetos[[#This Row],[Total de tarefas]]=Base_Projetos[[#This Row],[Tarefas Concluídas]],"Concluído",IF(Base_Projetos[[#This Row],[Tarefas não iniciadas]]=Base_Projetos[[#This Row],[Total de tarefas]],"Não iniciado",IF(Base_Projetos[[#This Row],[Tarefas atrasadas]]>0,"Atrasado","Em andamento"))) -> Concluído | S15: =Base_Projetos[[#This Row],[Tarefas Concluídas]]/Base_Projetos[[#This Row],[Total de tarefas]] -> 1
A16: =A15+1 -> 12 | B16: Gabarito Tubo Intermediário 21, 25T e 27 Complemento | C16: Projetar Gabarito Tubo Intermediário 21,25T e 27 Complemento | D16: 3- Alta | E16: Evandro | F16: 1 | G16: =SUMIF(tbl_PlanilhaB[Projeto],Base_Projetos[[#This Row],[Projeto]],tbl_PlanilhaB[Valor previsto]) -> 0 | H16: =SUMIF(tbl_PlanilhaB[Projeto],Base_Projetos[[#This Row],[Projeto]],tbl_PlanilhaB[Valor gasto]) -> 0 | I16: =_xlfn.MINIFS(TAREFAS!E:E,TAREFAS!B:B,Base_Projetos[[#This Row],[Projeto]]) -> 45267 | J16: =_xlfn.MAXIFS(TAREFAS!G:G,TAREFAS!B:B,Base_Projetos[[#This Row],[Projeto]]) -> 45281 | K16: =IF(Base_Projetos[[#This Row],[Total de tarefas]]=Base_Projetos[[#This Row],[Tarefas não iniciadas]],"Não iniciado",_xlfn.MINIFS(TAREFAS!H:H,TAREFAS!B:B,Base_Projetos[[#This Row],[Projeto]])) -> 45267 | L16: =IF(Base_Projetos[[#This Row],[Total de tarefas]]=Base_Projetos[[#This Row],[Tarefas Concluídas]],_xlfn.MAXIFS(TAREFAS!H:H,TAREFAS!B:B,Base_Projetos[[#This Row],[Projeto]]),IF(Base_Projetos[[#This Row],[Total de tarefas]]=Base_Projetos[[#This Row],[Tarefas não iniciadas]],"Não iniciado","Em andamento")) -> Em andamento | M16: =SUM(Base_Projetos[[#This Row],[Tarefas Concluídas]:[Tarefas não iniciadas]]) -> 2 | N16: =COUNTIFS(tbl_PlanilhaB[Projeto],Base_Projetos[[#This Row],[Projeto]],tbl_PlanilhaB[Status],"Concluído") -> 1 | O16: =COUNTIFS(tbl_PlanilhaB[Projeto],Base_Projetos[[#This Row],[Projeto]],tbl_PlanilhaB[Status],"Em andamento") -> 0 | P16: =COUNTIFS(tbl_PlanilhaB[Projeto],Base_Projetos[[#This Row],[Projeto]],tbl_PlanilhaB[Status],"Atrasado") -> 0 | Q16: =COUNTIFS(tbl_PlanilhaB[Projeto],Base_Projetos[[#This Row],[Projeto]],tbl_PlanilhaB[Status],"Não iniciado") -> 1 | R16: =IF(Base_Projetos[[#This Row],[Total de tarefas]]=Base_Projetos[[#This Row],[Tarefas Concluídas]],"Concluído",IF(Base_Projetos[[#This Row],[Tarefas não iniciadas]]=Base_Projetos[[#This Row],[Total de tarefas]],"Não iniciado",IF(Base_Projetos[[#This Row],[Tarefas atrasadas]]>0,"Atrasado","Em andamento"))) -> Em andamento | S16: =Base_Projetos[[#This Row],[Tarefas Concluídas]]/Base_Projetos[[#This Row],[Total de tarefas]] -> 0.5
A17: =A16+1 -> 13 | B17: Gabarito Tubo Intermediário 27 | C17: Projetar Gabarito Tubo Intermediário 27000 | D17: 3- Alta | E17: Evandro | F17: 1 | G17: =SUMIF(tbl_PlanilhaB[Projeto],Base_Projetos[[#This Row],[Projeto]],tbl_PlanilhaB[Valor previsto]) -> 0 | H17: =SUMIF(tbl_PlanilhaB[Projeto],Base_Projetos[[#This Row],[Projeto]],tbl_PlanilhaB[Valor gasto]) -> 0 | I17: =_xlfn.MINIFS(TAREFAS!E:E,TAREFAS!B:B,Base_Projetos[[#This Row],[Projeto]]) -> 45281 | J17: =_xlfn.MAXIFS(TAREFAS!G:G,TAREFAS!B:B,Base_Projetos[[#This Row],[Projeto]]) -> 45295 | K17: =IF(Base_Projetos[[#This Row],[Total de tarefas]]=Base_Projetos[[#This Row],[Tarefas não iniciadas]],"Não iniciado",_xlfn.MINIFS(TAREFAS!H:H,TAREFAS!B:B,Base_Projetos[[#This Row],[Projeto]])) -> 45281 | L17: =IF(Base_Projetos[[#This Row],[Total de tarefas]]=Base_Projetos[[#This Row],[Tarefas Concluídas]],_xlfn.MAXIFS(TAREFAS!H:H,TAREFAS!B:B,Base_Projetos[[#This Row],[Projeto]]),IF(Base_Projetos[[#This Row],[Total de tarefas]]=Base_Projetos[[#This Row],[Tarefas não iniciadas]],"Não iniciado","Em andamento")) -> 45281 | M17: =SUM(Base_Projetos[[#This Row],[Tarefas Concluídas]:[Tarefas não iniciadas]]) -> 1 | N17: =COUNTIFS(tbl_PlanilhaB[Projeto],Base_Projetos[[#This Row],[Projeto]],tbl_PlanilhaB[Status],"Concluído") -> 1 | O17: =COUNTIFS(tbl_PlanilhaB[Projeto],Base_Projetos[[#This Row],[Projeto]],tbl_PlanilhaB[Status],"Em andamento") -> 0 | P17: =COUNTIFS(tbl_PlanilhaB[Projeto],Base_Projetos[[#This Row],[Projeto]],tbl_PlanilhaB[Status],"Atrasado") -> 0 | Q17: =COUNTIFS(tbl_PlanilhaB[Projeto],Base_Projetos[[#This Row],[Projeto]],tbl_PlanilhaB[Status],"Não iniciado") -> 0 | R17: =IF(Base_Projetos[[#This Row],[Total de tarefas]]=Base_Projetos[[#This Row],[Tarefas Concluídas]],"Concluído",IF(Base_Projetos[[#This Row],[Tarefas não iniciadas]]=Base_Projetos[[#This Row],[Total de tarefas]],"Não iniciado",IF(Base_Projetos[[#This Row],[Tarefas atrasadas]]>0,"Atrasado","Em andamento"))) -> Concluído | S17: =Base_Projetos[[#This Row],[Tarefas Concluídas]]/Base_Projetos[[#This Row],[Total de tarefas]] -> 1
A18: =A17+1 -> 14 | B18: Gabarito Cintas Soldadas 21, 25 e 27 | C18: Projetar Gabarito Cintas Soldadas 21,25 e 27 | D18: 3- Alta | E18: Evandro | F18: 1 | G18: =SUMIF(tbl_PlanilhaB[Projeto],Base_Projetos[[#This Row],[Projeto]],tbl_PlanilhaB[Valor previsto]) -> 0 | H18: =SUMIF(tbl_PlanilhaB[Projeto],Base_Projetos[[#This Row],[Projeto]],tbl_PlanilhaB[Valor gasto]) -> 0 | I18: =_xlfn.MINIFS(TAREFAS!E:E,TAREFAS!B:B,Base_Projetos[[#This Row],[Projeto]]) -> 45287 | J18: =_xlfn.MAXIFS(TAREFAS!G:G,TAREFAS!B:B,Base_Projetos[[#This Row],[Projeto]]) -> 45296 | K18: =IF(Base_Projetos[[#This Row],[Total de tarefas]]=Base_Projetos[[#This Row],[Tarefas não iniciadas]],"Não iniciado",_xlfn.MINIFS(TAREFAS!H:H,TAREFAS!B:B,Base_Projetos[[#This Row],[Projeto]])) -> 45287 | L18: =IF(Base_Projetos[[#This Row],[Total de tarefas]]=Base_Projetos[[#This Row],[Tarefas Concluídas]],_xlfn.MAXIFS(TAREFAS!H:H,TAREFAS!B:B,Base_Projetos[[#This Row],[Projeto]]),IF(Base_Projetos[[#This Row],[Total de tarefas]]=Base_Projetos[[#This Row],[Tarefas não iniciadas]],"Não iniciado","Em andamento")) -> 45287 | M18: =SUM(Base_Projetos[[#This Row],[Tarefas Concluídas]:[Tarefas não iniciadas]]) -> 1 | N18: =COUNTIFS(tbl_PlanilhaB[Projeto],Base_Projetos[[#This Row],[Projeto]],tbl_PlanilhaB[Status],"Concluído") -> 1 | O18: =COUNTIFS(tbl_PlanilhaB[Projeto],Base_Projetos[[#This Row],[Projeto]],tbl_PlanilhaB[Status],"Em andamento") -> 0 | P18: =COUNTIFS(tbl_PlanilhaB[Projeto],Base_Projetos[[#This Row],[Projeto]],tbl_PlanilhaB[Status],"Atrasado") -> 0 | Q18: =COUNTIFS(tbl_PlanilhaB[Projeto],Base_Projetos[[#This Row],[Projeto]],tbl_PlanilhaB[Status],"Não iniciado") -> 0 | R18: =IF(Base_Projetos[[#This Row],[Total de tarefas]]=Base_Projetos[[#This Row],[Tarefas Concluídas]],"Concluído",IF(Base_Projetos[[#This Row],[Tarefas não iniciadas]]=Base_Projetos[[#This Row],[Total de tarefas]],"Não iniciado",IF(Base_Projetos[[#This Row],[Tarefas atrasadas]]>0,"Atrasado","Em andamento"))) -> Concluído | S18: =Base_Projetos[[#This Row],[Tarefas Concluídas]]/Base_Projetos[[#This Row],[Total de tarefas]] -> 1
A19: =A18+1 -> 15 | B19: Gabarito Caixa Coletora 16000 | C19: Projetar Gabarito Caixa Coletora 16000 | D19: 3- Alta | E19: Evandro | F19: 1 | G19: =SUMIF(tbl_PlanilhaB[Projeto],Base_Projetos[[#This Row],[Projeto]],tbl_PlanilhaB[Valor previsto]) -> 0 | H19: =SUMIF(tbl_PlanilhaB[Projeto],Base_Projetos[[#This Row],[Projeto]],tbl_PlanilhaB[Valor gasto]) -> 0 | I19: =_xlfn.MINIFS(TAREFAS!E:E,TAREFAS!B:B,Base_Projetos[[#This Row],[Projeto]]) -> 45296 | J19: =_xlfn.MAXIFS(TAREFAS!G:G,TAREFAS!B:B,Base_Projetos[[#This Row],[Projeto]]) -> 45399 | K19: =IF(Base_Projetos[[#This Row],[Total de tarefas]]=Base_Projetos[[#This Row],[Tarefas não iniciadas]],"Não iniciado",_xlfn.MINIFS(TAREFAS!H:H,TAREFAS!B:B,Base_Projetos[[#This Row],[Projeto]])) -> 45296 | L19: =IF(Base_Projetos[[#This Row],[Total de tarefas]]=Base_Projetos[[#This Row],[Tarefas Concluídas]],_xlfn.MAXIFS(TAREFAS!H:H,TAREFAS!B:B,Base_Projetos[[#This Row],[Projeto]]),IF(Base_Projetos[[#This Row],[Total de tarefas]]=Base_Projetos[[#This Row],[Tarefas não iniciadas]],"Não iniciado","Em andamento")) -> 45397 | M19: =SUM(Base_Projetos[[#This Row],[Tarefas Concluídas]:[Tarefas não iniciadas]]) -> 2 | N19: =COUNTIFS(tbl_PlanilhaB[Projeto],Base_Projetos[[#This Row],[Projeto]],tbl_PlanilhaB[Status],"Concluído") -> 2 | O19: =COUNTIFS(tbl_PlanilhaB[Projeto],Base_Projetos[[#This Row],[Projeto]],tbl_PlanilhaB[Status],"Em andamento") -> 0 | P19: =COUNTIFS(tbl_PlanilhaB[Projeto],Base_Projetos[[#This Row],[Projeto]],tbl_PlanilhaB[Status],"Atrasado") -> 0 | Q19: =COUNTIFS(tbl_PlanilhaB[Projeto],Base_Projetos[[#This Row],[Projeto]],tbl_PlanilhaB[Status],"Não iniciado") -> 0 | R19: =IF(Base_Projetos[[#This Row],[Total de tarefas]]=Base_Projetos[[#This Row],[Tarefas Concluídas]],"Concluído",IF(Base_Projetos[[#This Row],[Tarefas não iniciadas]]=Base_Projetos[[#This Row],[Total de tarefas]],"Não iniciado",IF(Base_Projetos[[#This Row],[Tarefas atrasadas]]>0,"Atrasado","Em andamento"))) -> Concluído | S19: =Base_Projetos[[#This Row],[Tarefas Concluídas]]/Base_Projetos[[#This Row],[Total de tarefas]] -> 1
... A38: =A37+1 -> 34 | B38: Gabarito Carro Dianteiro Linha Leve | C38: Desenvolver conceito e o projeto | D38: 2- Média | E38: Fabricio | F38: 1 | G38: =SUMIF(tbl_PlanilhaB[Projeto],Base_Projetos[[#This Row],[Projeto]],tbl_PlanilhaB[Valor previsto]) -> 0 | H38: =SUMIF(tbl_PlanilhaB[Projeto],Base_Projetos[[#This Row],[Projeto]],tbl_PlanilhaB[Valor gasto]) -> 0 | I38: =_xlfn.MINIFS(TAREFAS!E:E,TAREFAS!B:B,Base_Projetos[[#This Row],[Projeto]]) -> 45440 | J38: =_xlfn.MAXIFS(TAREFAS!G:G,TAREFAS!B:B,Base_Projetos[[#This Row],[Projeto]]) -> 45447 | K38: =IF(Base_Projetos[[#This Row],[Total de tarefas]]=Base_Projetos[[#This Row],[Tarefas não iniciadas]],"Não iniciado",_xlfn.MINIFS(TAREFAS!H:H,TAREFAS!B:B,Base_Projetos[[#This Row],[Projeto]])) -> 45440 | L38: =IF(Base_Projetos[[#This Row],[Total de tarefas]]=Base_Projetos[[#This Row],[Tarefas Concluídas]],_xlfn.MAXIFS(TAREFAS!H:H,TAREFAS!B:B,Base_Projetos[[#This Row],[Projeto]]),IF(Base_Projetos[[#This Row],[Total de tarefas]]=Base_Projetos[[#This Row],[Tarefas não iniciadas]],"Não iniciado","Em andamento")) -> 45440 | M38: =SUM(Base_Projetos[[#This Row],[Tarefas Concluídas]:[Tarefas não iniciadas]]) -> 1 | N38: =COUNTIFS(tbl_PlanilhaB[Projeto],Base_Projetos[[#This Row],[Projeto]],tbl_PlanilhaB[Status],"Concluído") -> 1 | O38: =COUNTIFS(tbl_PlanilhaB[Projeto],Base_Projetos[[#This Row],[Projeto]],tbl_PlanilhaB[Status],"Em andamento") -> 0 | P38: =COUNTIFS(tbl_PlanilhaB[Projeto],Base_Projetos[[#This Row],[Projeto]],tbl_PlanilhaB[Status],"Atrasado") -> 0 | Q38: =COUNTIFS(tbl_PlanilhaB[Projeto],Base_Projetos[[#This Row],[Projeto]],tbl_PlanilhaB[Status],"Não iniciado") -> 0 | R38: =IF(Base_Projetos[[#This Row],[Total de tarefas]]=Base_Projetos[[#This Row],[Tarefas Concluídas]],"Concluído",IF(Base_Projetos[[#This Row],[Tarefas não iniciadas]]=Base_Projetos[[#This Row],[Total de tarefas]],"Não iniciado",IF(Base_Projetos[[#This Row],[Tarefas atrasadas]]>0,"Atrasado","Em andamento"))) -> Concluído | S38: =Base_Projetos[[#This Row],[Tarefas Concluídas]]/Base_Projetos[[#This Row],[Total de tarefas]] -> 1
A39: =A38+1 -> 35 | B39: Simulação de Carga Austrália | D39: 3- Alta | E39: Fabricio | F39: 1 | G39: =SUMIF(tbl_PlanilhaB[Projeto],Base_Projetos[[#This Row],[Projeto]],tbl_PlanilhaB[Valor previsto]) -> 0 | H39: =SUMIF(tbl_PlanilhaB[Projeto],Base_Projetos[[#This Row],[Projeto]],tbl_PlanilhaB[Valor gasto]) -> 0 | I39: =_xlfn.MINIFS(TAREFAS!E:E,TAREFAS!B:B,Base_Projetos[[#This Row],[Projeto]]) -> 45415 | J39: =_xlfn.MAXIFS(TAREFAS!G:G,TAREFAS!B:B,Base_Projetos[[#This Row],[Projeto]]) -> 45440 | K39: =IF(Base_Projetos[[#This Row],[Total de tarefas]]=Base_Projetos[[#This Row],[Tarefas não iniciadas]],"Não iniciado",_xlfn.MINIFS(TAREFAS!H:H,TAREFAS!B:B,Base_Projetos[[#This Row],[Projeto]])) -> 45415 | L39: =IF(Base_Projetos[[#This Row],[Total de tarefas]]=Base_Projetos[[#This Row],[Tarefas Concluídas]],_xlfn.MAXIFS(TAREFAS!H:H,TAREFAS!B:B,Base_Projetos[[#This Row],[Projeto]]),IF(Base_Projetos[[#This Row],[Total de tarefas]]=Base_Projetos[[#This Row],[Tarefas não iniciadas]],"Não iniciado","Em andamento")) -> 45433 | M39: =SUM(Base_Projetos[[#This Row],[Tarefas Concluídas]:[Tarefas não iniciadas]]) -> 2 | N39: =COUNTIFS(tbl_PlanilhaB[Projeto],Base_Projetos[[#This Row],[Projeto]],tbl_PlanilhaB[Status],"Concluído") -> 2 | O39: =COUNTIFS(tbl_PlanilhaB[Projeto],Base_Projetos[[#This Row],[Projeto]],tbl_PlanilhaB[Status],"Em andamento") -> 0 | P39: =COUNTIFS(tbl_PlanilhaB[Projeto],Base_Projetos[[#This Row],[Projeto]],tbl_PlanilhaB[Status],"Atrasado") -> 0 | Q39: =COUNTIFS(tbl_PlanilhaB[Projeto],Base_Projetos[[#This Row],[Projeto]],tbl_PlanilhaB[Status],"Não iniciado") -> 0 | R39: =IF(Base_Projetos[[#This Row],[Total de tarefas]]=Base_Projetos[[#This Row],[Tarefas Concluídas]],"Concluído",IF(Base_Projetos[[#This Row],[Tarefas não iniciadas]]=Base_Projetos[[#This Row],[Total de tarefas]],"Não iniciado",IF(Base_Projetos[[#This Row],[Tarefas atrasadas]]>0,"Atrasado","Em andamento"))) -> Concluído | S39: =Base_Projetos[[#This Row],[Tarefas Concluídas]]/Base_Projetos[[#This Row],[Total de tarefas]] -> 1
A40: =A39+1 -> 36 | B40: Suportes para Carga conteiner 2 | C40: projetar suportes para carga | D40: 3- Alta | E40: Evandro | F40: 1 | G40: =SUMIF(tbl_PlanilhaB[Projeto],Base_Projetos[[#This Row],[Projeto]],tbl_PlanilhaB[Valor previsto]) -> 0 | H40: =SUMIF(tbl_PlanilhaB[Projeto],Base_Projetos[[#This Row],[Projeto]],tbl_PlanilhaB[Valor gasto]) -> 0 | I40: =_xlfn.MINIFS(TAREFAS!E:E,TAREFAS!B:B,Base_Projetos[[#This Row],[Projeto]]) -> 45415 | J40: =_xlfn.MAXIFS(TAREFAS!G:G,TAREFAS!B:B,Base_Projetos[[#This Row],[Projeto]]) -> 45439 | K40: =IF(Base_Projetos[[#This Row],[Total de tarefas]]=Base_Projetos[[#This Row],[Tarefas não iniciadas]],"Não iniciado",_xlfn.MINIFS(TAREFAS!H:H,TAREFAS!B:B,Base_Projetos[[#This Row],[Projeto]])) -> 45415 | L40: =IF(Base_Projetos[[#This Row],[Total de tarefas]]=Base_Projetos[[#This Row],[Tarefas Concluídas]],_xlfn.MAXIFS(TAREFAS!H:H,TAREFAS!B:B,Base_Projetos[[#This Row],[Projeto]]),IF(Base_Projetos[[#This Row],[Total de tarefas]]=Base_Projetos[[#This Row],[Tarefas não iniciadas]],"Não iniciado","Em andamento")) -> 45432 | M40: =SUM(Base_Projetos[[#This Row],[Tarefas Concluídas]:[Tarefas não iniciadas]]) -> 3 | N40: =COUNTIFS(tbl_PlanilhaB[Projeto],Base_Projetos[[#This Row],[Projeto]],tbl_PlanilhaB[Status],"Concluído") -> 3 | O40: =COUNTIFS(tbl_PlanilhaB[Projeto],Base_Projetos[[#This Row],[Projeto]],tbl_PlanilhaB[Status],"Em andamento") -> 0 | P40: =COUNTIFS(tbl_PlanilhaB[Projeto],Base_Projetos[[#This Row],[Projeto]],tbl_PlanilhaB[Status],"Atrasado") -> 0 | Q40: =COUNTIFS(tbl_PlanilhaB[Projeto],Base_Projetos[[#This Row],[Projeto]],tbl_PlanilhaB[Status],"Não iniciado") -> 0 | R40: =IF(Base_Projetos[[#This Row],[Total de tarefas]]=Base_Projetos[[#This Row],[Tarefas Concluídas]],"Concluído",IF(Base_Projetos[[#This Row],[Tarefas não iniciadas]]=Base_Projetos[[#This Row],[Total de tarefas]],"Não iniciado",IF(Base_Projetos[[#This Row],[Tarefas atrasadas]]>0,"Atrasado","Em andamento"))) -> Concluído | S40: =Base_Projetos[[#This Row],[Tarefas Concluídas]]/Base_Projetos[[#This Row],[Total de tarefas]] -> 1
A41: =A40+1 -> 37 | B41: Suportes para Carga conteiner 2X32.000 | C41: projetar suportes para carga | D41: 3- Alta | E41: Evandro | F41: 1 | G41: =SUMIF(tbl_PlanilhaB[Projeto],Base_Projetos[[#This Row],[Projeto]],tbl_PlanilhaB[Valor previsto]) -> 0 | H41: =SUMIF(tbl_PlanilhaB[Projeto],Base_Projetos[[#This Row],[Projeto]],tbl_PlanilhaB[Valor gasto]) -> 0 | I41: =_xlfn.MINIFS(TAREFAS!E:E,TAREFAS!B:B,Base_Projetos[[#This Row],[Projeto]]) -> 45423 | J41: =_xlfn.MAXIFS(TAREFAS!G:G,TAREFAS!B:B,Base_Projetos[[#This Row],[Projeto]]) -> 45436 | K41: =IF(Base_Projetos[[#This Row],[Total de tarefas]]=Base_Projetos[[#This Row],[Tarefas não iniciadas]],"Não iniciado",_xlfn.MINIFS(TAREFAS!H:H,TAREFAS!B:B,Base_Projetos[[#This Row],[Projeto]])) -> 45423 | L41: =IF(Base_Projetos[[#This Row],[Total de tarefas]]=Base_Projetos[[#This Row],[Tarefas Concluídas]],_xlfn.MAXIFS(TAREFAS!H:H,TAREFAS!B:B,Base_Projetos[[#This Row],[Projeto]]),IF(Base_Projetos[[#This Row],[Total de tarefas]]=Base_Projetos[[#This Row],[Tarefas não iniciadas]],"Não iniciado","Em andamento")) -> Em andamento | M41: =SUM(Base_Projetos[[#This Row],[Tarefas Concluídas]:[Tarefas não iniciadas]]) -> 3 | N41: =COUNTIFS(tbl_PlanilhaB[Projeto],Base_Projetos[[#This Row],[Projeto]],tbl_PlanilhaB[Status],"Concluído") -> 2 | O41: =COUNTIFS(tbl_PlanilhaB[Projeto],Base_Projetos[[#This Row],[Projeto]],tbl_PlanilhaB[Status],"Em andamento") -> 0 | P41: =COUNTIFS(tbl_PlanilhaB[Projeto],Base_Projetos[[#This Row],[Projeto]],tbl_PlanilhaB[Status],"Atrasado") -> 0 | Q41: =COUNTIFS(tbl_PlanilhaB[Projeto],Base_Projetos[[#This Row],[Projeto]],tbl_PlanilhaB[Status],"Não iniciado") -> 1 | R41: =IF(Base_Projetos[[#This Row],[Total de tarefas]]=Base_Projetos[[#This Row],[Tarefas Concluídas]],"Concluído",IF(Base_Projetos[[#This Row],[Tarefas não iniciadas]]=Base_Projetos[[#This Row],[Total de tarefas]],"Não iniciado",IF(Base_Projetos[[#This Row],[Tarefas atrasadas]]>0,"Atrasado","Em andamento"))) -> Em andamento | S41: =Base_Projetos[[#This Row],[Tarefas Concluídas]]/Base_Projetos[[#This Row],[Total de tarefas]] -> 0.66666667
A42: =A41+1 -> 38 | B42: GAB FRESAGEM SUPORTE LAMINA CRS | C42: PROJETAR E DESENVOLVER GABARITO | D42: 3- Alta | E42: Evandro | F42: 1 | G42: =SUMIF(tbl_PlanilhaB[Projeto],Base_Projetos[[#This Row],[Projeto]],tbl_PlanilhaB[Valor previsto]) -> 0 | H42: =SUMIF(tbl_PlanilhaB[Projeto],Base_Projetos[[#This Row],[Projeto]],tbl_PlanilhaB[Valor gasto]) -> 0 | I42: =_xlfn.MINIFS(TAREFAS!E:E,TAREFAS!B:B,Base_Projetos[[#This Row],[Projeto]]) -> 45436 | J42: =_xlfn.MAXIFS(TAREFAS!G:G,TAREFAS!B:B,Base_Projetos[[#This Row],[Projeto]]) -> 45449 | K42: =IF(Base_Projetos[[#This Row],[Total de tarefas]]=Base_Projetos[[#This Row],[Tarefas não iniciadas]],"Não iniciado",_xlfn.MINIFS(TAREFAS!H:H,TAREFAS!B:B,Base_Projetos[[#This Row],[Projeto]])) -> 45436 | L42: =IF(Base_Projetos[[#This Row],[Total de tarefas]]=Base_Projetos[[#This Row],[Tarefas Concluídas]],_xlfn.MAXIFS(TAREFAS!H:H,TAREFAS!B:B,Base_Projetos[[#This Row],[Projeto]]),IF(Base_Projetos[[#This Row],[Total de tarefas]]=Base_Projetos[[#This Row],[Tarefas não iniciadas]],"Não iniciado","Em andamento")) -> 45444 | M42: =SUM(Base_Projetos[[#This Row],[Tarefas Concluídas]:[Tarefas não iniciadas]]) -> 3 | N42: =COUNTIFS(tbl_PlanilhaB[Projeto],Base_Projetos[[#This Row],[Projeto]],tbl_PlanilhaB[Status],"Concluído") -> 3 | O42: =COUNTIFS(tbl_PlanilhaB[Projeto],Base_Projetos[[#This Row],[Projeto]],tbl_PlanilhaB[Status],"Em andamento") -> 0 | P42: =COUNTIFS(tbl_PlanilhaB[Projeto],Base_Projetos[[#This Row],[Projeto]],tbl_PlanilhaB[Status],"Atrasado") -> 0 | Q42: =COUNTIFS(tbl_PlanilhaB[Projeto],Base_Projetos[[#This Row],[Projeto]],tbl_PlanilhaB[Status],"Não iniciado") -> 0 | R42: =IF(Base_Projetos[[#This Row],[Total de tarefas]]=Base_Projetos[[#This Row],[Tarefas Concluídas]],"Concluído",IF(Base_Projetos[[#This Row],[Tarefas não iniciadas]]=Base_Projetos[[#This Row],[Total de tarefas]],"Não iniciado",IF(Base_Projetos[[#This Row],[Tarefas atrasadas]]>0,"Atrasado","Em andamento"))) -> Concluído | S42: =Base_Projetos[[#This Row],[Tarefas Concluídas]]/Base_Projetos[[#This Row],[Total de tarefas]] -> 1
A43: =A42+1 -> 39 | B43: GAB CHASSI NOVA CRS 7 | C43: PROJETAR E DESENVOLVER GABARITO | D43: 3- Alta | E43: Evandro | F43: 1 | G43: =SUMIF(tbl_PlanilhaB[Projeto],Base_Projetos[[#This Row],[Projeto]],tbl_PlanilhaB[Valor previsto]) -> 0 | H43: =SUMIF(tbl_PlanilhaB[Projeto],Base_Projetos[[#This Row],[Projeto]],tbl_PlanilhaB[Valor gasto]) -> 0 | I43: =_xlfn.MINIFS(TAREFAS!E:E,TAREFAS!B:B,Base_Projetos[[#This Row],[Projeto]]) -> 45441 | J43: =_xlfn.MAXIFS(TAREFAS!G:G,TAREFAS!B:B,Base_Projetos[[#This Row],[Projeto]]) -> 45455 | K43: =IF(Base_Projetos[[#This Row],[Total de tarefas]]=Base_Projetos[[#This Row],[Tarefas não iniciadas]],"Não iniciado",_xlfn.MINIFS(TAREFAS!H:H,TAREFAS!B:B,Base_Projetos[[#This Row],[Projeto]])) -> 45441 | L43: =IF(Base_Projetos[[#This Row],[Total de tarefas]]=Base_Projetos[[#This Row],[Tarefas Concluídas]],_xlfn.MAXIFS(TAREFAS!H:H,TAREFAS!B:B,Base_Projetos[[#This Row],[Projeto]]),IF(Base_Projetos[[#This Row],[Total de tarefas]]=Base_Projetos[[#This Row],[Tarefas não iniciadas]],"Não iniciado","Em andamento")) -> Em andamento | M43: =SUM(Base_Projetos[[#This Row],[Tarefas Concluídas]:[Tarefas não iniciadas]]) -> 4 | N43: =COUNTIFS(tbl_PlanilhaB[Projeto],Base_Projetos[[#This Row],[Projeto]],tbl_PlanilhaB[Status],"Concluído") -> 0 | O43: =COUNTIFS(tbl_PlanilhaB[Projeto],Base_Projetos[[#This Row],[Projeto]],tbl_PlanilhaB[Status],"Em andamento") -> 0 | P43: =COUNTIFS(tbl_PlanilhaB[Projeto],Base_Projetos[[#This Row],[Projeto]],tbl_PlanilhaB[Status],"Atrasado") -> 2 | Q43: =COUNTIFS(tbl_PlanilhaB[Projeto],Base_Projetos[[#This Row],[Projeto]],tbl_PlanilhaB[Status],"Não iniciado") -> 2 | R43: =IF(Base_Projetos[[#This Row],[Total de tarefas]]=Base_Projetos[[#This Row],[Tarefas Concluídas]],"Concluído",IF(Base_Projetos[[#This Row],[Tarefas não iniciadas]]=Base_Projetos[[#This Row],[Total de tarefas]],"Não iniciado",IF(Base_Projetos[[#This Row],[Tarefas atrasadas]]>0,"Atrasado","Em andamento"))) -> Atrasado | S43: =Base_Projetos[[#This Row],[Tarefas Concluídas]]/Base_Projetos[[#This Row],[Total de tarefas]] -> 0
A44: =A43+1 -> 40 | B44: GAB CAÇAMBA CRS 7 NOVA | C44: PROJETAR E DESENVOLVER GABARITO | D44: 3- Alta | E44: Evandro | F44: 1 | G44: =SUMIF(tbl_PlanilhaB[Projeto],Base_Projetos[[#This Row],[Projeto]],tbl_PlanilhaB[Valor previsto]) -> 0 | H44: =SUMIF(tbl_PlanilhaB[Projeto],Base_Projetos[[#This Row],[Projeto]],tbl_PlanilhaB[Valor gasto]) -> 0 | I44: =_xlfn.MINIFS(TAREFAS!E:E,TAREFAS!B:B,Base_Projetos[[#This Row],[Projeto]]) -> 45456 | J44: =_xlfn.MAXIFS(TAREFAS!G:G,TAREFAS!B:B,Base_Projetos[[#This Row],[Projeto]]) -> 45474 | K44: =IF(Base_Projetos[[#This Row],[Total de tarefas]]=Base_Projetos[[#This Row],[Tarefas não iniciadas]],"Não iniciado",_xlfn.MINIFS(TAREFAS!H:H,TAREFAS!B:B,Base_Projetos[[#This Row],[Projeto]])) -> 45456 | L44: =IF(Base_Projetos[[#This Row],[Total de tarefas]]=Base_Projetos[[#This Row],[Tarefas Concluídas]],_xlfn.MAXIFS(TAREFAS!H:H,TAREFAS!B:B,Base_Projetos[[#This Row],[Projeto]]),IF(Base_Projetos[[#This Row],[Total de tarefas]]=Base_Projetos[[#This Row],[Tarefas não iniciadas]],"Não iniciado","Em andamento")) -> 45471 | M44: =SUM(Base_Projetos[[#This Row],[Tarefas Concluídas]:[Tarefas não iniciadas]]) -> 4 | N44: =COUNTIFS(tbl_PlanilhaB[Projeto],Base_Projetos[[#This Row],[Projeto]],tbl_PlanilhaB[Status],"Concluído") -> 4 | O44: =COUNTIFS(tbl_PlanilhaB[Projeto],Base_Projetos[[#This Row],[Projeto]],tbl_PlanilhaB[Status],"Em andamento") -> 0 | P44: =COUNTIFS(tbl_PlanilhaB[Projeto],Base_Projetos[[#This Row],[Projeto]],tbl_PlanilhaB[Status],"Atrasado") -> 0 | Q44: =COUNTIFS(tbl_PlanilhaB[Projeto],Base_Projetos[[#This Row],[Projeto]],tbl_PlanilhaB[Status],"Não iniciado") -> 0 | R44: =IF(Base_Projetos[[#This Row],[Total de tarefas]]=Base_Projetos[[#This Row],[Tarefas Concluídas]],"Concluído",IF(Base_Projetos[[#This Row],[Tarefas não iniciadas]]=Base_Projetos[[#This Row],[Total de tarefas]],"Não iniciado",IF(Base_Projetos[[#This Row],[Tarefas atrasadas]]>0,"Atrasado","Em andamento"))) -> Concluído | S44: =Base_Projetos[[#This Row],[Tarefas Concluídas]]/Base_Projetos[[#This Row],[Total de tarefas]] -> 1
A45: =A44+1 -> 41 | B45: GAB LATERAL CRS3 E 4 PARA ROBO | C45: AJUSTAR GABARITO | D45: 3- Alta | E45: Evandro | F45: 1 | G45: =SUMIF(tbl_PlanilhaB[Projeto],Base_Projetos[[#This Row],[Projeto]],tbl_PlanilhaB[Valor previsto]) -> 0 | H45: =SUMIF(tbl_PlanilhaB[Projeto],Base_Projetos[[#This Row],[Projeto]],tbl_PlanilhaB[Valor gasto]) -> 0 | I45: =_xlfn.MINIFS(TAREFAS!E:E,TAREFAS!B:B,Base_Projetos[[#This Row],[Projeto]]) -> 45444 | J45: =_xlfn.MAXIFS(TAREFAS!G:G,TAREFAS!B:B,Base_Projetos[[#This Row],[Projeto]]) -> 45478 | K45: =IF(Base_Projetos[[#This Row],[Total de tarefas]]=Base_Projetos[[#This Row],[Tarefas não iniciadas]],"Não iniciado",_xlfn.MINIFS(TAREFAS!H:H,TAREFAS!B:B,Base_Projetos[[#This Row],[Projeto]])) -> 45444 | L45: =IF(Base_Projetos[[#This Row],[Total de tarefas]]=Base_Projetos[[#This Row],[Tarefas Concluídas]],_xlfn.MAXIFS(TAREFAS!H:H,TAREFAS!B:B,Base_Projetos[[#This Row],[Projeto]]),IF(Base_Projetos[[#This Row],[Total de tarefas]]=Base_Projetos[[#This Row],[Tarefas não iniciadas]],"Não iniciado","Em andamento")) -> 45476 | M45: =SUM(Base_Projetos[[#This Row],[Tarefas Concluídas]:[Tarefas não iniciadas]]) -> 2 | N45: =COUNTIFS(tbl_PlanilhaB[Projeto],Base_Projetos[[#This Row],[Projeto]],tbl_PlanilhaB[Status],"Concluído") -> 2 | O45: =COUNTIFS(tbl_PlanilhaB[Projeto],Base_Projetos[[#This Row],[Projeto]],tbl_PlanilhaB[Status],"Em andamento") -> 0 | P45: =COUNTIFS(tbl_PlanilhaB[Projeto],Base_Projetos[[#This Row],[Projeto]],tbl_PlanilhaB[Status],"Atrasado") -> 0 | Q45: =COUNTIFS(tbl_PlanilhaB[Projeto],Base_Projetos[[#This Row],[Projeto]],tbl_PlanilhaB[Status],"Não iniciado") -> 0 | R45: =IF(Base_Projetos[[#This Row],[Total de tarefas]]=Base_Projetos[[#This Row],[Tarefas Concluídas]],"Concluído",IF(Base_Projetos[[#This Row],[Tarefas não iniciadas]]=Base_Projetos[[#This Row],[Total de tarefas]],"Não iniciado",IF(Base_Projetos[[#This Row],[Tarefas atrasadas]]>0,"Atrasado","Em andamento"))) -> Concluído | S45: =Base_Projetos[[#This Row],[Tarefas Concluídas]]/Base_Projetos[[#This Row],[Total de tarefas]] -> 1
A46: =A45+1 -> 42 | B46: TANQUE PARA FLUIDO - USINAGEM | C46: MODELAGEM 3D E DETALHAMENTO | D46: 2- Média | E46: Bruno Pivoto | F46: 1 | G46: =SUMIF(tbl_PlanilhaB[Projeto],Base_Projetos[[#This Row],[Projeto]],tbl_PlanilhaB[Valor previsto]) -> 0 | H46: =SUMIF(tbl_PlanilhaB[Projeto],Base_Projetos[[#This Row],[Projeto]],tbl_PlanilhaB[Valor gasto]) -> 0 | I46: =_xlfn.MINIFS(TAREFAS!E:E,TAREFAS!B:B,Base_Projetos[[#This Row],[Projeto]]) -> 45461 | J46: =_xlfn.MAXIFS(TAREFAS!G:G,TAREFAS!B:B,Base_Projetos[[#This Row],[Projeto]]) -> 45464 | K46: =IF(Base_Projetos[[#This Row],[Total de tarefas]]=Base_Projetos[[#This Row],[Tarefas não iniciadas]],"Não iniciado",_xlfn.MINIFS(TAREFAS!H:H,TAREFAS!B:B,Base_Projetos[[#This Row],[Projeto]])) -> 45461 | L46: =IF(Base_Projetos[[#This Row],[Total de tarefas]]=Base_Projetos[[#This Row],[Tarefas Concluídas]],_xlfn.MAXIFS(TAREFAS!H:H,TAREFAS!B:B,Base_Projetos[[#This Row],[Projeto]]),IF(Base_Projetos[[#This Row],[Total de tarefas]]=Base_Projetos[[#This Row],[Tarefas não iniciadas]],"Não iniciado","Em andamento")) -> 45461 | M46: =SUM(Base_Projetos[[#This Row],[Tarefas Concluídas]:[Tarefas não iniciadas]]) -> 1 | N46: =COUNTIFS(tbl_PlanilhaB[Projeto],Base_Projetos[[#This Row],[Projeto]],tbl_PlanilhaB[Status],"Concluído") -> 1 | O46: =COUNTIFS(tbl_PlanilhaB[Projeto],Base_Projetos[[#This Row],[Projeto]],tbl_PlanilhaB[Status],"Em andamento") -> 0 | P46: =COUNTIFS(tbl_PlanilhaB[Projeto],Base_Projetos[[#This Row],[Projeto]],tbl_PlanilhaB[Status],"Atrasado") -> 0 | Q46: =COUNTIFS(tbl_PlanilhaB[Projeto],Base_Projetos[[#This Row],[Projeto]],tbl_PlanilhaB[Status],"Não iniciado") -> 0 | R46: =IF(Base_Projetos[[#This Row],[Total de tarefas]]=Base_Projetos[[#This Row],[Tarefas Concluídas]],"Concluído",IF(Base_Projetos[[#This Row],[Tarefas não iniciadas]]=Base_Projetos[[#This Row],[Total de tarefas]],"Não iniciado",IF(Base_Projetos[[#This Row],[Tarefas atrasadas]]>0,"Atrasado","Em andamento"))) -> Concluído | S46: =Base_Projetos[[#This Row],[Tarefas Concluídas]]/Base_Projetos[[#This Row],[Total de tarefas]] -> 1
A47: =A46+1 -> 43 | B47: GAB. ROTOR BCI 200, 250, 300, 400, 500 | C47: PROJETAR, MODELAR E DETALHAR | D47: 3- Alta | E47: Bruno Pivoto | F47: 1 | G47: =SUMIF(tbl_PlanilhaB[Projeto],Base_Projetos[[#This Row],[Projeto]],tbl_PlanilhaB[Valor previsto]) -> 0 | H47: =SUMIF(tbl_PlanilhaB[Projeto],Base_Projetos[[#This Row],[Projeto]],tbl_PlanilhaB[Valor gasto]) -> 0 | I47: 45469 | J47: 45475 | K47: =IF(Base_Projetos[[#This Row],[Total de tarefas]]=Base_Projetos[[#This Row],[Tarefas não iniciadas]],"Não iniciado",_xlfn.MINIFS(TAREFAS!H:H,TAREFAS!B:B,Base_Projetos[[#This Row],[Projeto]])) -> 45469 | L47: =IF(Base_Projetos[[#This Row],[Total de tarefas]]=Base_Projetos[[#This Row],[Tarefas Concluídas]],_xlfn.MAXIFS(TAREFAS!H:H,TAREFAS!B:B,Base_Projetos[[#This Row],[Projeto]]),IF(Base_Projetos[[#This Row],[Total de tarefas]]=Base_Projetos[[#This Row],[Tarefas não iniciadas]],"Não iniciado","Em andamento")) -> 45469 | M47: =SUM(Base_Projetos[[#This Row],[Tarefas Concluídas]:[Tarefas não iniciadas]]) -> 1 | N47: =COUNTIFS(tbl_PlanilhaB[Projeto],Base_Projetos[[#This Row],[Projeto]],tbl_PlanilhaB[Status],"Concluído") -> 1 | O47: =COUNTIFS(tbl_PlanilhaB[Projeto],Base_Projetos[[#This Row],[Projeto]],tbl_PlanilhaB[Status],"Em andamento") -> 0 | P47: =COUNTIFS(tbl_PlanilhaB[Projeto],Base_Projetos[[#This Row],[Projeto]],tbl_PlanilhaB[Status],"Atrasado") -> 0 | Q47: =COUNTIFS(tbl_PlanilhaB[Projeto],Base_Projetos[[#This Row],[Projeto]],tbl_PlanilhaB[Status],"Não iniciado") -> 0 | R47: =IF(Base_Projetos[[#This Row],[Total de tarefas]]=Base_Projetos[[#This Row],[Tarefas Concluídas]],"Concluído",IF(Base_Projetos[[#This Row],[Tarefas não iniciadas]]=Base_Projetos[[#This Row],[Total de tarefas]],"Não iniciado",IF(Base_Projetos[[#This Row],[Tarefas atrasadas]]>0,"Atrasado","Em andamento"))) -> Concluído | S47: 0.55
A48: =A47+1 -> 44 | B48: MOLDE ZOCOTEC | C48: PROJETAR, MODELAR E DETALHAR | D48: 1- Baixa | E48: Bruno Pivoto | F48: 1 | G48: =SUMIF(tbl_PlanilhaB[Projeto],Base_Projetos[[#This Row],[Projeto]],tbl_PlanilhaB[Valor previsto]) -> 0 | H48: =SUMIF(tbl_PlanilhaB[Projeto],Base_Projetos[[#This Row],[Projeto]],tbl_PlanilhaB[Valor gasto]) -> 0 | I48: 45475 | J48: 45475 | K48: 45475 | L48: 45475 | M48: =SUM(Base_Projetos[[#This Row],[Tarefas Concluídas]:[Tarefas não iniciadas]]) -> 1 | N48: =COUNTIFS(tbl_PlanilhaB[Projeto],Base_Projetos[[#This Row],[Projeto]],tbl_PlanilhaB[Status],"Concluído") -> 1 | O48: =COUNTIFS(tbl_PlanilhaB[Projeto],Base_Projetos[[#This Row],[Projeto]],tbl_PlanilhaB[Status],"Em andamento") -> 0 | P48: =COUNTIFS(tbl_PlanilhaB[Projeto],Base_Projetos[[#This Row],[Projeto]],tbl_PlanilhaB[Status],"Atrasado") -> 0 | Q48: =COUNTIFS(tbl_PlanilhaB[Projeto],Base_Projetos[[#This Row],[Projeto]],tbl_PlanilhaB[Status],"Não iniciado") -> 0 | R48: =IF(Base_Projetos[[#This Row],[Total de tarefas]]=Base_Projetos[[#This Row],[Tarefas Concluídas]],"Concluído",IF(Base_Projetos[[#This Row],[Tarefas não iniciadas]]=Base_Projetos[[#This Row],[Total de tarefas]],"Não iniciado",IF(Base_Projetos[[#This Row],[Tarefas atrasadas]]>0,"Atrasado","Em andamento"))) -> Concluído | S48: =Base_Projetos[[#This Row],[Tarefas Concluídas]]/Base_Projetos[[#This Row],[Total de tarefas]] -> 1
A49: =A48+1 -> 45 | B49: DISPOSITIVO DE FIXAÇÃO CRP 4.5 | C49: PROJETAR, MODELAR E DETALHAR | D49: 3- Alta | E49: Bruno Pivoto | F49: 1 | G49: =SUMIF(tbl_PlanilhaB[Projeto],Base_Projetos[[#This Row],[Projeto]],tbl_PlanilhaB[Valor previsto]) -> 0 | H49: =SUMIF(tbl_PlanilhaB[Projeto],Base_Projetos[[#This Row],[Projeto]],tbl_PlanilhaB[Valor gasto]) -> 0 | I49: 45471 | J49: 45478 | K49: 45471 | L49: =IF(Base_Projetos[[#This Row],[Total de tarefas]]=Base_Projetos[[#This Row],[Tarefas Concluídas]],_xlfn.MAXIFS(TAREFAS!H:H,TAREFAS!B:B,Base_Projetos[[#This Row],[Projeto]]),IF(Base_Projetos[[#This Row],[Total de tarefas]]=Base_Projetos[[#This Row],[Tarefas não iniciadas]],"Não iniciado","Em andamento")) -> Em andamento | M49: 2 | N49: =COUNTIFS(tbl_PlanilhaB[Projeto],Base_Projetos[[#This Row],[Projeto]],tbl_PlanilhaB[Status],"Concluído") -> 1 | O49: =COUNTIFS(tbl_PlanilhaB[Projeto],Base_Projetos[[#This Row],[Projeto]],tbl_PlanilhaB[Status],"Em andamento") -> 0 | P49: =COUNTIFS(tbl_PlanilhaB[Projeto],Base_Projetos[[#This Row],[Projeto]],tbl_PlanilhaB[Status],"Atrasado") -> 0 | Q49: =COUNTIFS(tbl_PlanilhaB[Projeto],Base_Projetos[[#This Row],[Projeto]],tbl_PlanilhaB[Status],"Não iniciado") -> 0 | R49: =IF(Base_Projetos[[#This Row],[Total de tarefas]]=Base_Projetos[[#This Row],[Tarefas Concluídas]],"Concluído",IF(Base_Projetos[[#This Row],[Tarefas não iniciadas]]=Base_Projetos[[#This Row],[Total de tarefas]],"Não iniciado",IF(Base_Projetos[[#This Row],[Tarefas atrasadas]]>0,"Atrasado","Em andamento"))) -> Em andamento | S49: =Base_Projetos[[#This Row],[Tarefas Concluídas]]/Base_Projetos[[#This Row],[Total de tarefas]] -> 0.5
A50: =A49+1 -> 46 | B50: Plataforma BCI 500 Expointer | C50: Modelar estrutura para expor as BCI's na Expointer | D50: 2- Média | E50: Bruno Pivoto | F50: 1 | G50: =SUMIF(tbl_PlanilhaB[Projeto],Base_Projetos[[#This Row],[Projeto]],tbl_PlanilhaB[Valor previsto]) -> 0 | H50: =SUMIF(tbl_PlanilhaB[Projeto],Base_Projetos[[#This Row],[Projeto]],tbl_PlanilhaB[Valor gasto]) -> 0 | I50: 45489 | J50: 45491 | K50: 45489 | L50: 45491 | M50: 3 | N50: =COUNTIFS(tbl_PlanilhaB[Projeto],Base_Projetos[[#This Row],[Projeto]],tbl_PlanilhaB[Status],"Concluído") -> 3 | O50: =COUNTIFS(tbl_PlanilhaB[Projeto],Base_Projetos[[#This Row],[Projeto]],tbl_PlanilhaB[Status],"Em andamento") -> 0 | P50: =COUNTIFS(tbl_PlanilhaB[Projeto],Base_Projetos[[#This Row],[Projeto]],tbl_PlanilhaB[Status],"Atrasado") -> 0 | Q50: =COUNTIFS(tbl_PlanilhaB[Projeto],Base_Projetos[[#This Row],[Projeto]],tbl_PlanilhaB[Status],"Não iniciado") -> 0 | R50: =IF(Base_Projetos[[#This Row],[Total de tarefas]]=Base_Projetos[[#This Row],[Tarefas Concluídas]],"Concluído",IF(Base_Projetos[[#This Row],[Tarefas não iniciadas]]=Base_Projetos[[#This Row],[Total de tarefas]],"Não iniciado",IF(Base_Projetos[[#This Row],[Tarefas atrasadas]]>0,"Atrasado","Em andamento"))) -> Concluído | S50: =Base_Projetos[[#This Row],[Tarefas Concluídas]]/Base_Projetos[[#This Row],[Total de tarefas]] -> 1
A51: =A50+1 -> 47 | B51: Passa ou não Passa Plainas Niveladoras linha leve e pesada | C51: Projetar, Modelar e detalhar | D51: 1- Baixa | E51: Bruno Pivoto | F51: 1 | G51: =SUMIF(tbl_PlanilhaB[Projeto],Base_Projetos[[#This Row],[Projeto]],tbl_PlanilhaB[Valor previsto]) -> 0 | H51: =SUMIF(tbl_PlanilhaB[Projeto],Base_Projetos[[#This Row],[Projeto]],tbl_PlanilhaB[Valor gasto]) -> 0 | I51: 45505 | J51: 45505 | K51: =IF(Base_Projetos[[#This Row],[Total de tarefas]]=Base_Projetos[[#This Row],[Tarefas não iniciadas]],"Não iniciado",_xlfn.MINIFS(TAREFAS!H:H,TAREFAS!B:B,Base_Projetos[[#This Row],[Projeto]])) -> 45505 | L51: =IF(Base_Projetos[[#This Row],[Total de tarefas]]=Base_Projetos[[#This Row],[Tarefas Concluídas]],_xlfn.MAXIFS(TAREFAS!H:H,TAREFAS!B:B,Base_Projetos[[#This Row],[Projeto]]),IF(Base_Projetos[[#This Row],[Total de tarefas]]=Base_Projetos[[#This Row],[Tarefas não iniciadas]],"Não iniciado","Em andamento")) -> 45505 | M51: =SUM(Base_Projetos[[#This Row],[Tarefas Concluídas]:[Tarefas não iniciadas]]) -> 1 | N51: =COUNTIFS(tbl_PlanilhaB[Projeto],Base_Projetos[[#This Row],[Projeto]],tbl_PlanilhaB[Status],"Concluído") -> 1 | O51: =COUNTIFS(tbl_PlanilhaB[Projeto],Base_Projetos[[#This Row],[Projeto]],tbl_PlanilhaB[Status],"Em andamento") -> 0 | P51: =COUNTIFS(tbl_PlanilhaB[Projeto],Base_Projetos[[#This Row],[Projeto]],tbl_PlanilhaB[Status],"Atrasado") -> 0 | Q51: =COUNTIFS(tbl_PlanilhaB[Projeto],Base_Projetos[[#This Row],[Projeto]],tbl_PlanilhaB[Status],"Não iniciado") -> 0 | R51: =IF(Base_Projetos[[#This Row],[Total de tarefas]]=Base_Projetos[[#This Row],[Tarefas Concluídas]],"Concluído",IF(Base_Projetos[[#This Row],[Tarefas não iniciadas]]=Base_Projetos[[#This Row],[Total de tarefas]],"Não iniciado",IF(Base_Projetos[[#This Row],[Tarefas atrasadas]]>0,"Atrasado","Em andamento"))) -> Concluído | S51: =Base_Projetos[[#This Row],[Tarefas Concluídas]]/Base_Projetos[[#This Row],[Total de tarefas]] -> 1
A52: =A51+1 -> 48 | B52: Passa ou não passa flanges superiores AGRIVAL 60L | C52: Projetar, Modelar e detalhar | D52: 1- Baixa | E52: Bruno Pivoto | F52: 1 | G52: =SUMIF(tbl_PlanilhaB[Projeto],Base_Projetos[[#This Row],[Projeto]],tbl_PlanilhaB[Valor previsto]) -> 0 | H52: =SUMIF(tbl_PlanilhaB[Projeto],Base_Projetos[[#This Row],[Projeto]],tbl_PlanilhaB[Valor gasto]) -> 0 | I52: 45509 | J52: 45509 | K52: =IF(Base_Projetos[[#This Row],[Total de tarefas]]=Base_Projetos[[#This Row],[Tarefas não iniciadas]],"Não iniciado",_xlfn.MINIFS(TAREFAS!H:H,TAREFAS!B:B,Base_Projetos[[#This Row],[Projeto]])) -> 45509 | L52: =IF(Base_Projetos[[#This Row],[Total de tarefas]]=Base_Projetos[[#This Row],[Tarefas Concluídas]],_xlfn.MAXIFS(TAREFAS!H:H,TAREFAS!B:B,Base_Projetos[[#This Row],[Projeto]]),IF(Base_Projetos[[#This Row],[Total de tarefas]]=Base_Projetos[[#This Row],[Tarefas não iniciadas]],"Não iniciado","Em andamento")) -> 45509 | M52: =SUM(Base_Projetos[[#This Row],[Tarefas Concluídas]:[Tarefas não iniciadas]]) -> 1 | N52: =COUNTIFS(tbl_PlanilhaB[Projeto],Base_Projetos[[#This Row],[Projeto]],tbl_PlanilhaB[Status],"Concluído") -> 1 | O52: =COUNTIFS(tbl_PlanilhaB[Projeto],Base_Projetos[[#This Row],[Projeto]],tbl_PlanilhaB[Status],"Em andamento") -> 0 | P52: =COUNTIFS(tbl_PlanilhaB[Projeto],Base_Projetos[[#This Row],[Projeto]],tbl_PlanilhaB[Status],"Atrasado") -> 0 | Q52: =COUNTIFS(tbl_PlanilhaB[Projeto],Base_Projetos[[#This Row],[Projeto]],tbl_PlanilhaB[Status],"Não iniciado") -> 0 | R52: =IF(Base_Projetos[[#This Row],[Total de tarefas]]=Base_Projetos[[#This Row],[Tarefas Concluídas]],"Concluído",IF(Base_Projetos[[#This Row],[Tarefas não iniciadas]]=Base_Projetos[[#This Row],[Total de tarefas]],"Não iniciado",IF(Base_Projetos[[#This Row],[Tarefas atrasadas]]>0,"Atrasado","Em andamento"))) -> Concluído | S52: =Base_Projetos[[#This Row],[Tarefas Concluídas]]/Base_Projetos[[#This Row],[Total de tarefas]] -> 1
A53: =A52+1 -> 49 | B53: U e I de transporte para as plainas da linha leve | C53: Projetar, Modelar e detalhar | D53: 1- Baixa | E53: Bruno Pivoto | F53: 1 | G53: =SUMIF(tbl_PlanilhaB[Projeto],Base_Projetos[[#This Row],[Projeto]],tbl_PlanilhaB[Valor previsto]) -> 0 | H53: =SUMIF(tbl_PlanilhaB[Projeto],Base_Projetos[[#This Row],[Projeto]],tbl_PlanilhaB[Valor gasto]) -> 0 | I53: 45520 | J53: 45523 | K53: =IF(Base_Projetos[[#This Row],[Total de tarefas]]=Base_Projetos[[#This Row],[Tarefas não iniciadas]],"Não iniciado",_xlfn.MINIFS(TAREFAS!H:H,TAREFAS!B:B,Base_Projetos[[#This Row],[Projeto]])) -> 45520 | L53: =IF(Base_Projetos[[#This Row],[Total de tarefas]]=Base_Projetos[[#This Row],[Tarefas Concluídas]],_xlfn.MAXIFS(TAREFAS!H:H,TAREFAS!B:B,Base_Projetos[[#This Row],[Projeto]]),IF(Base_Projetos[[#This Row],[Total de tarefas]]=Base_Projetos[[#This Row],[Tarefas não iniciadas]],"Não iniciado","Em andamento")) -> 45523 | M53: =SUM(Base_Projetos[[#This Row],[Tarefas Concluídas]:[Tarefas não iniciadas]]) -> 3 | N53: =COUNTIFS(tbl_PlanilhaB[Projeto],Base_Projetos[[#This Row],[Projeto]],tbl_PlanilhaB[Status],"Concluído") -> 3 | O53: =COUNTIFS(tbl_PlanilhaB[Projeto],Base_Projetos[[#This Row],[Projeto]],tbl_PlanilhaB[Status],"Em andamento") -> 0 | P53: =COUNTIFS(tbl_PlanilhaB[Projeto],Base_Projetos[[#This Row],[Projeto]],tbl_PlanilhaB[Status],"Atrasado") -> 0 | Q53: =COUNTIFS(tbl_PlanilhaB[Projeto],Base_Projetos[[#This Row],[Projeto]],tbl_PlanilhaB[Status],"Não iniciado") -> 0 | R53: =IF(Base_Projetos[[#This Row],[Total de tarefas]]=Base_Projetos[[#This Row],[Tarefas Concluídas]],"Concluído",IF(Base_Projetos[[#This Row],[Tarefas não iniciadas]]=Base_Projetos[[#This Row],[Total de tarefas]],"Não iniciado",IF(Base_Projetos[[#This Row],[Tarefas atrasadas]]>0,"Atrasado","Em andamento"))) -> Concluído | S53: =Base_Projetos[[#This Row],[Tarefas Concluídas]]/Base_Projetos[[#This Row],[Total de tarefas]] -> 1
A54: =A53+1 -> 50 | B54: Suporte de transporte TA 10 e TA14 | C54: Projetar, Modelar e detalhar | D54: 1- Baixa | E54: Bruno Pivoto | F54: 1 | G54: =SUMIF(tbl_PlanilhaB[Projeto],Base_Projetos[[#This Row],[Projeto]],tbl_PlanilhaB[Valor previsto]) -> 0 | H54: =SUMIF(tbl_PlanilhaB[Projeto],Base_Projetos[[#This Row],[Projeto]],tbl_PlanilhaB[Valor gasto]) -> 0 | I54: 45520 | J54: 45523 | K54: =IF(Base_Projetos[[#This Row],[Total de tarefas]]=Base_Projetos[[#This Row],[Tarefas não iniciadas]],"Não iniciado",_xlfn.MINIFS(TAREFAS!H:H,TAREFAS!B:B,Base_Projetos[[#This Row],[Projeto]])) -> 45520 | L54: =IF(Base_Projetos[[#This Row],[Total de tarefas]]=Base_Projetos[[#This Row],[Tarefas Concluídas]],_xlfn.MAXIFS(TAREFAS!H:H,TAREFAS!B:B,Base_Projetos[[#This Row],[Projeto]]),IF(Base_Projetos[[#This Row],[Total de tarefas]]=Base_Projetos[[#This Row],[Tarefas não iniciadas]],"Não iniciado","Em andamento")) -> 45523 | M54: =SUM(Base_Projetos[[#This Row],[Tarefas Concluídas]:[Tarefas não iniciadas]]) -> 3 | N54: =COUNTIFS(tbl_PlanilhaB[Projeto],Base_Projetos[[#This Row],[Projeto]],tbl_PlanilhaB[Status],"Concluído") -> 3 | O54: =COUNTIFS(tbl_PlanilhaB[Projeto],Base_Projetos[[#This Row],[Projeto]],tbl_PlanilhaB[Status],"Em andamento") -> 0 | P54: =COUNTIFS(tbl_PlanilhaB[Projeto],Base_Projetos[[#This Row],[Projeto]],tbl_PlanilhaB[Status],"Atrasado") -> 0 | Q54: =COUNTIFS(tbl_PlanilhaB[Projeto],Base_Projetos[[#This Row],[Projeto]],tbl_PlanilhaB[Status],"Não iniciado") -> 0 | R54: =IF(Base_Projetos[[#This Row],[Total de tarefas]]=Base_Projetos[[#This Row],[Tarefas Concluídas]],"Concluído",IF(Base_Projetos[[#This Row],[Tarefas não iniciadas]]=Base_Projetos[[#This Row],[Total de tarefas]],"Não iniciado",IF(Base_Projetos[[#This Row],[Tarefas atrasadas]]>0,"Atrasado","Em andamento"))) -> Concluído | S54: =Base_Projetos[[#This Row],[Tarefas Concluídas]]/Base_Projetos[[#This Row],[Total de tarefas]] -> 1
A55: =A54+1 -> 51 | B55: Caixa para Walkie Talkies | C55: Projetar, Modelar e detalhar | D55: 1- Baixa | E55: Bruno Pivoto | F55: 1 | G55: =SUMIF(tbl_PlanilhaB[Projeto],Base_Projetos[[#This Row],[Projeto]],tbl_PlanilhaB[Valor previsto]) -> 0 | H55: =SUMIF(tbl_PlanilhaB[Projeto],Base_Projetos[[#This Row],[Projeto]],tbl_PlanilhaB[Valor gasto]) -> 0 | I55: 45532 | J55: 45534 | K55: =IF(Base_Projetos[[#This Row],[Total de tarefas]]=Base_Projetos[[#This Row],[Tarefas não iniciadas]],"Não iniciado",_xlfn.MINIFS(TAREFAS!H:H,TAREFAS!B:B,Base_Projetos[[#This Row],[Projeto]])) -> 45532 | L55: =IF(Base_Projetos[[#This Row],[Total de tarefas]]=Base_Projetos[[#This Row],[Tarefas Concluídas]],_xlfn.MAXIFS(TAREFAS!H:H,TAREFAS!B:B,Base_Projetos[[#This Row],[Projeto]]),IF(Base_Projetos[[#This Row],[Total de tarefas]]=Base_Projetos[[#This Row],[Tarefas não iniciadas]],"Não iniciado","Em andamento")) -> 45533 | M55: =SUM(Base_Projetos[[#This Row],[Tarefas Concluídas]:[Tarefas não iniciadas]]) -> 3 | N55: =COUNTIFS(tbl_PlanilhaB[Projeto],Base_Projetos[[#This Row],[Projeto]],tbl_PlanilhaB[Status],"Concluído") -> 3 | O55: =COUNTIFS(tbl_PlanilhaB[Projeto],Base_Projetos[[#This Row],[Projeto]],tbl_PlanilhaB[Status],"Em andamento") -> 0 | P55: =COUNTIFS(tbl_PlanilhaB[Projeto],Base_Projetos[[#This Row],[Projeto]],tbl_PlanilhaB[Status],"Atrasado") -> 0 | Q55: =COUNTIFS(tbl_PlanilhaB[Projeto],Base_Projetos[[#This Row],[Projeto]],tbl_PlanilhaB[Status],"Não iniciado") -> 0 | R55: =IF(Base_Projetos[[#This Row],[Total de tarefas]]=Base_Projetos[[#This Row],[Tarefas Concluídas]],"Concluído",IF(Base_Projetos[[#This Row],[Tarefas não iniciadas]]=Base_Projetos[[#This Row],[Total de tarefas]],"Não iniciado",IF(Base_Projetos[[#This Row],[Tarefas atrasadas]]>0,"Atrasado","Em andamento"))) -> Concluído | S55: =Base_Projetos[[#This Row],[Tarefas Concluídas]]/Base_Projetos[[#This Row],[Total de tarefas]] -> 1
A56: =A55+1 -> 52 | B56: Suporte para quadro sala de reunião | C56: Projetar, Modelar e detalhar | D56: 1- Baixa | E56: Bruno Pivoto | F56: 1 | G56: =SUMIF(tbl_PlanilhaB[Projeto],Base_Projetos[[#This Row],[Projeto]],tbl_PlanilhaB[Valor previsto]) -> 0 | H56: =SUMIF(tbl_PlanilhaB[Projeto],Base_Projetos[[#This Row],[Projeto]],tbl_PlanilhaB[Valor gasto]) -> 0 | I56: =_xlfn.MINIFS(TAREFAS!E:E,TAREFAS!B:B,Base_Projetos[[#This Row],[Projeto]]) -> 45548 | J56: =_xlfn.MAXIFS(TAREFAS!G:G,TAREFAS!B:B,Base_Projetos[[#This Row],[Projeto]]) -> 45552 | K56: =IF(Base_Projetos[[#This Row],[Total de tarefas]]=Base_Projetos[[#This Row],[Tarefas não iniciadas]],"Não iniciado",_xlfn.MINIFS(TAREFAS!H:H,TAREFAS!B:B,Base_Projetos[[#This Row],[Projeto]])) -> 45548 | L56: =IF(Base_Projetos[[#This Row],[Total de tarefas]]=Base_Projetos[[#This Row],[Tarefas Concluídas]],_xlfn.MAXIFS(TAREFAS!H:H,TAREFAS!B:B,Base_Projetos[[#This Row],[Projeto]]),IF(Base_Projetos[[#This Row],[Total de tarefas]]=Base_Projetos[[#This Row],[Tarefas não iniciadas]],"Não iniciado","Em andamento")) -> 45551 | M56: =SUM(Base_Projetos[[#This Row],[Tarefas Concluídas]:[Tarefas não iniciadas]]) -> 2 | N56: =COUNTIFS(tbl_PlanilhaB[Projeto],Base_Projetos[[#This Row],[Projeto]],tbl_PlanilhaB[Status],"Concluído") -> 2 | O56: =COUNTIFS(tbl_PlanilhaB[Projeto],Base_Projetos[[#This Row],[Projeto]],tbl_PlanilhaB[Status],"Em andamento") -> 0 | P56: =COUNTIFS(tbl_PlanilhaB[Projeto],Base_Projetos[[#This Row],[Projeto]],tbl_PlanilhaB[Status],"Atrasado") -> 0 | Q56: =COUNTIFS(tbl_PlanilhaB[Projeto],Base_Projetos[[#This Row],[Projeto]],tbl_PlanilhaB[Status],"Não iniciado") -> 0 | R56: =IF(Base_Projetos[[#This Row],[Total de tarefas]]=Base_Projetos[[#This Row],[Tarefas Concluídas]],"Concluído",IF(Base_Projetos[[#This Row],[Tarefas não iniciadas]]=Base_Projetos[[#This Row],[Total de tarefas]],"Não iniciado",IF(Base_Projetos[[#This Row],[Tarefas atrasadas]]>0,"Atrasado","Em andamento"))) -> Concluído | S56: =Base_Projetos[[#This Row],[Tarefas Concluídas]]/Base_Projetos[[#This Row],[Total de tarefas]] -> 1
A57: =A56+1 -> 53 | B57: Dispositivo de transporte rexter | C57: Detalhar | D57: 1- Baixa | E57: Bruno Pivoto | F57: 1 | G57: =SUMIF(tbl_PlanilhaB[Projeto],Base_Projetos[[#This Row],[Projeto]],tbl_PlanilhaB[Valor previsto]) -> 0 | H57: =SUMIF(tbl_PlanilhaB[Projeto],Base_Projetos[[#This Row],[Projeto]],tbl_PlanilhaB[Valor gasto]) -> 0 | I57: =_xlfn.MINIFS(TAREFAS!E:E,TAREFAS!B:B,Base_Projetos[[#This Row],[Projeto]]) -> 45551 | J57: =_xlfn.MAXIFS(TAREFAS!G:G,TAREFAS!B:B,Base_Projetos[[#This Row],[Projeto]]) -> 45552 | K57: =IF(Base_Projetos[[#This Row],[Total de tarefas]]=Base_Projetos[[#This Row],[Tarefas não iniciadas]],"Não iniciado",_xlfn.MINIFS(TAREFAS!H:H,TAREFAS!B:B,Base_Projetos[[#This Row],[Projeto]])) -> 45551 | L57: =IF(Base_Projetos[[#This Row],[Total de tarefas]]=Base_Projetos[[#This Row],[Tarefas Concluídas]],_xlfn.MAXIFS(TAREFAS!H:H,TAREFAS!B:B,Base_Projetos[[#This Row],[Projeto]]),IF(Base_Projetos[[#This Row],[Total de tarefas]]=Base_Projetos[[#This Row],[Tarefas não iniciadas]],"Não iniciado","Em andamento")) -> 45551 | M57: =SUM(Base_Projetos[[#This Row],[Tarefas Concluídas]:[Tarefas não iniciadas]]) -> 1 | N57: =COUNTIFS(tbl_PlanilhaB[Projeto],Base_Projetos[[#This Row],[Projeto]],tbl_PlanilhaB[Status],"Concluído") -> 1 | O57: =COUNTIFS(tbl_PlanilhaB[Projeto],Base_Projetos[[#This Row],[Projeto]],tbl_PlanilhaB[Status],"Em andamento") -> 0 | P57: =COUNTIFS(tbl_PlanilhaB[Projeto],Base_Projetos[[#This Row],[Projeto]],tbl_PlanilhaB[Status],"Atrasado") -> 0 | Q57: =COUNTIFS(tbl_PlanilhaB[Projeto],Base_Projetos[[#This Row],[Projeto]],tbl_PlanilhaB[Status],"Não iniciado") -> 0 | R57: =IF(Base_Projetos[[#This Row],[Total de tarefas]]=Base_Projetos[[#This Row],[Tarefas Concluídas]],"Concluído",IF(Base_Projetos[[#This Row],[Tarefas não iniciadas]]=Base_Projetos[[#This Row],[Total de tarefas]],"Não iniciado",IF(Base_Projetos[[#This Row],[Tarefas atrasadas]]>0,"Atrasado","Em andamento"))) -> Concluído | S57: =Base_Projetos[[#This Row],[Tarefas Concluídas]]/Base_Projetos[[#This Row],[Total de tarefas]] -> 1
A58: =A57+1 -> 54 | B58: Relatório Processo de Solda em Inox MIG/MAG | C58: Testes e Elaboração | D58: 3- Alta | E58: João Calheiros | F58: 1 | G58: =SUMIF(tbl_PlanilhaB[Projeto],Base_Projetos[[#This Row],[Projeto]],tbl_PlanilhaB[Valor previsto]) -> 0 | H58: =SUMIF(tbl_PlanilhaB[Projeto],Base_Projetos[[#This Row],[Projeto]],tbl_PlanilhaB[Valor gasto]) -> 0 | I58: =_xlfn.MINIFS(TAREFAS!E:E,TAREFAS!B:B,Base_Projetos[[#This Row],[Projeto]]) -> 45553 | J58: =_xlfn.MAXIFS(TAREFAS!G:G,TAREFAS!B:B,Base_Projetos[[#This Row],[Projeto]]) -> 45559 | K58: =IF(Base_Projetos[[#This Row],[Total de tarefas]]=Base_Projetos[[#This Row],[Tarefas não iniciadas]],"Não iniciado",_xlfn.MINIFS(TAREFAS!H:H,TAREFAS!B:B,Base_Projetos[[#This Row],[Projeto]])) -> 45553 | L58: =IF(Base_Projetos[[#This Row],[Total de tarefas]]=Base_Projetos[[#This Row],[Tarefas Concluídas]],_xlfn.MAXIFS(TAREFAS!H:H,TAREFAS!B:B,Base_Projetos[[#This Row],[Projeto]]),IF(Base_Projetos[[#This Row],[Total de tarefas]]=Base_Projetos[[#This Row],[Tarefas não iniciadas]],"Não iniciado","Em andamento")) -> 45558 | M58: =SUM(Base_Projetos[[#This Row],[Tarefas Concluídas]:[Tarefas não iniciadas]]) -> 2 | N58: =COUNTIFS(tbl_PlanilhaB[Projeto],Base_Projetos[[#This Row],[Projeto]],tbl_PlanilhaB[Status],"Concluído") -> 2 | O58: =COUNTIFS(tbl_PlanilhaB[Projeto],Base_Projetos[[#This Row],[Projeto]],tbl_PlanilhaB[Status],"Em andamento") -> 0 | P58: =COUNTIFS(tbl_PlanilhaB[Projeto],Base_Projetos[[#This Row],[Projeto]],tbl_PlanilhaB[Status],"Atrasado") -> 0 | Q58: =COUNTIFS(tbl_PlanilhaB[Projeto],Base_Projetos[[#This Row],[Projeto]],tbl_PlanilhaB[Status],"Não iniciado") -> 0 | R58: =IF(Base_Projetos[[#This Row],[Total de tarefas]]=Base_Projetos[[#This Row],[Tarefas Concluídas]],"Concluído",IF(Base_Projetos[[#This Row],[Tarefas não iniciadas]]=Base_Projetos[[#This Row],[Total de tarefas]],"Não iniciado",IF(Base_Projetos[[#This Row],[Tarefas atrasadas]]>0,"Atrasado","Em andamento"))) -> Concluído | S58: =Base_Projetos[[#This Row],[Tarefas Concluídas]]/Base_Projetos[[#This Row],[Total de tarefas]] -> 1
A59: =A58+1 -> 55 | B59: Gabarito para os gabaritos | C59: Auxilio e acompanhamento na montagem | D59: 2- Média | E59: Bruno Pivoto | F59: 1 | G59: =SUMIF(tbl_PlanilhaB[Projeto],Base_Projetos[[#This Row],[Projeto]],tbl_PlanilhaB[Valor previsto]) -> 0 | H59: =SUMIF(tbl_PlanilhaB[Projeto],Base_Projetos[[#This Row],[Projeto]],tbl_PlanilhaB[Valor gasto]) -> 0 | I59: =_xlfn.MINIFS(TAREFAS!E:E,TAREFAS!B:B,Base_Projetos[[#This Row],[Projeto]]) -> 45538 | J59: =_xlfn.MAXIFS(TAREFAS!G:G,TAREFAS!B:B,Base_Projetos[[#This Row],[Projeto]]) -> 45540 | K59: =IF(Base_Projetos[[#This Row],[Total de tarefas]]=Base_Projetos[[#This Row],[Tarefas não iniciadas]],"Não iniciado",_xlfn.MINIFS(TAREFAS!H:H,TAREFAS!B:B,Base_Projetos[[#This Row],[Projeto]])) -> 45538 | L59: =IF(Base_Projetos[[#This Row],[Total de tarefas]]=Base_Projetos[[#This Row],[Tarefas Concluídas]],_xlfn.MAXIFS(TAREFAS!H:H,TAREFAS!B:B,Base_Projetos[[#This Row],[Projeto]]),IF(Base_Projetos[[#This Row],[Total de tarefas]]=Base_Projetos[[#This Row],[Tarefas não iniciadas]],"Não iniciado","Em andamento")) -> 45538 | M59: =SUM(Base_Projetos[[#This Row],[Tarefas Concluídas]:[Tarefas não iniciadas]]) -> 2 | N59: =COUNTIFS(tbl_PlanilhaB[Projeto],Base_Projetos[[#This Row],[Projeto]],tbl_PlanilhaB[Status],"Concluído") -> 2 | O59: =COUNTIFS(tbl_PlanilhaB[Projeto],Base_Projetos[[#This Row],[Projeto]],tbl_PlanilhaB[Status],"Em andamento") -> 0 | P59: =COUNTIFS(tbl_PlanilhaB[Projeto],Base_Projetos[[#This Row],[Projeto]],tbl_PlanilhaB[Status],"Atrasado") -> 0 | Q59: =COUNTIFS(tbl_PlanilhaB[Projeto],Base_Projetos[[#This Row],[Projeto]],tbl_PlanilhaB[Status],"Não iniciado") -> 0 | R59: =IF(Base_Projetos[[#This Row],[Total de tarefas]]=Base_Projetos[[#This Row],[Tarefas Concluídas]],"Concluído",IF(Base_Projetos[[#This Row],[Tarefas não iniciadas]]=Base_Projetos[[#This Row],[Total de tarefas]],"Não iniciado",IF(Base_Projetos[[#This Row],[Tarefas atrasadas]]>0,"Atrasado","Em andamento"))) -> Concluído | S59: =Base_Projetos[[#This Row],[Tarefas Concluídas]]/Base_Projetos[[#This Row],[Total de tarefas]] -> 1
A60: =A59+1 -> 56 | B60: Gerar DXF's de peças para o CNC | C60: Gerar DXF's | D60: 3- Alta | E60: Bruno Pivoto | F60: 1 | G60: =SUMIF(tbl_PlanilhaB[Projeto],Base_Projetos[[#This Row],[Projeto]],tbl_PlanilhaB[Valor previsto]) -> 0 | H60: =SUMIF(tbl_PlanilhaB[Projeto],Base_Projetos[[#This Row],[Projeto]],tbl_PlanilhaB[Valor gasto]) -> 0 | I60: =_xlfn.MINIFS(TAREFAS!E:E,TAREFAS!B:B,Base_Projetos[[#This Row],[Projeto]]) -> 45551 | J60: =_xlfn.MAXIFS(TAREFAS!G:G,TAREFAS!B:B,Base_Projetos[[#This Row],[Projeto]]) -> 45554 | K60: =IF(Base_Projetos[[#This Row],[Total de tarefas]]=Base_Projetos[[#This Row],[Tarefas não iniciadas]],"Não iniciado",_xlfn.MINIFS(TAREFAS!H:H,TAREFAS!B:B,Base_Projetos[[#This Row],[Projeto]])) -> 45551 | L60: =IF(Base_Projetos[[#This Row],[Total de tarefas]]=Base_Projetos[[#This Row],[Tarefas Concluídas]],_xlfn.MAXIFS(TAREFAS!H:H,TAREFAS!B:B,Base_Projetos[[#This Row],[Projeto]]),IF(Base_Projetos[[#This Row],[Total de tarefas]]=Base_Projetos[[#This Row],[Tarefas não iniciadas]],"Não iniciado","Em andamento")) -> 45551 | M60: =SUM(Base_Projetos[[#This Row],[Tarefas Concluídas]:[Tarefas não iniciadas]]) -> 1 | N60: =COUNTIFS(tbl_PlanilhaB[Projeto],Base_Projetos[[#This Row],[Projeto]],tbl_PlanilhaB[Status],"Concluído") -> 1 | O60: =COUNTIFS(tbl_PlanilhaB[Projeto],Base_Projetos[[#This Row],[Projeto]],tbl_PlanilhaB[Status],"Em andamento") -> 0 | P60: =COUNTIFS(tbl_PlanilhaB[Projeto],Base_Projetos[[#This Row],[Projeto]],tbl_PlanilhaB[Status],"Atrasado") -> 0 | Q60: =COUNTIFS(tbl_PlanilhaB[Projeto],Base_Projetos[[#This Row],[Projeto]],tbl_PlanilhaB[Status],"Não iniciado") -> 0 | R60: =IF(Base_Projetos[[#This Row],[Total de tarefas]]=Base_Projetos[[#This Row],[Tarefas Concluídas]],"Concluído",IF(Base_Projetos[[#This Row],[Tarefas não iniciadas]]=Base_Projetos[[#This Row],[Total de tarefas]],"Não iniciado",IF(Base_Projetos[[#This Row],[Tarefas atrasadas]]>0,"Atrasado","Em andamento"))) -> Concluído | S60: =Base_Projetos[[#This Row],[Tarefas Concluídas]]/Base_Projetos[[#This Row],[Total de tarefas]] -> 1
A61: =A60+1 -> 57 | B61: Suportes para transporte REXTER | C61: Projetar, Modelar e detalhar | D61: 2- Média | E61: Bruno Pivoto | F61: 1 | G61: =SUMIF(tbl_PlanilhaB[Projeto],Base_Projetos[[#This Row],[Projeto]],tbl_PlanilhaB[Valor previsto]) -> 0 | H61: =SUMIF(tbl_PlanilhaB[Projeto],Base_Projetos[[#This Row],[Projeto]],tbl_PlanilhaB[Valor gasto]) -> 0 | I61: =_xlfn.MINIFS(TAREFAS!E:E,TAREFAS!B:B,Base_Projetos[[#This Row],[Projeto]]) -> 45558 | J61: =_xlfn.MAXIFS(TAREFAS!G:G,TAREFAS!B:B,Base_Projetos[[#This Row],[Projeto]]) -> 45559 | K61: =IF(Base_Projetos[[#This Row],[Total de tarefas]]=Base_Projetos[[#This Row],[Tarefas não iniciadas]],"Não iniciado",_xlfn.MINIFS(TAREFAS!H:H,TAREFAS!B:B,Base_Projetos[[#This Row],[Projeto]])) -> 45558 | L61: =IF(Base_Projetos[[#This Row],[Total de tarefas]]=Base_Projetos[[#This Row],[Tarefas Concluídas]],_xlfn.MAXIFS(TAREFAS!H:H,TAREFAS!B:B,Base_Projetos[[#This Row],[Projeto]]),IF(Base_Projetos[[#This Row],[Total de tarefas]]=Base_Projetos[[#This Row],[Tarefas não iniciadas]],"Não iniciado","Em andamento")) -> 45558 | M61: =SUM(Base_Projetos[[#This Row],[Tarefas Concluídas]:[Tarefas não iniciadas]]) -> 1 | N61: =COUNTIFS(tbl_PlanilhaB[Projeto],Base_Projetos[[#This Row],[Projeto]],tbl_PlanilhaB[Status],"Concluído") -> 1 | O61: =COUNTIFS(tbl_PlanilhaB[Projeto],Base_Projetos[[#This Row],[Projeto]],tbl_PlanilhaB[Status],"Em andamento") -> 0 | P61: =COUNTIFS(tbl_PlanilhaB[Projeto],Base_Projetos[[#This Row],[Projeto]],tbl_PlanilhaB[Status],"Atrasado") -> 0 | Q61: =COUNTIFS(tbl_PlanilhaB[Projeto],Base_Projetos[[#This Row],[Projeto]],tbl_PlanilhaB[Status],"Não iniciado") -> 0 | R61: =IF(Base_Projetos[[#This Row],[Total de tarefas]]=Base_Projetos[[#This Row],[Tarefas Concluídas]],"Concluído",IF(Base_Projetos[[#This Row],[Tarefas não iniciadas]]=Base_Projetos[[#This Row],[Total de tarefas]],"Não iniciado",IF(Base_Projetos[[#This Row],[Tarefas atrasadas]]>0,"Atrasado","Em andamento"))) -> Concluído | S61: =Base_Projetos[[#This Row],[Tarefas Concluídas]]/Base_Projetos[[#This Row],[Total de tarefas]] -> 1
A62: =A61+1 -> 58 | B62: Montagem do eixo do graneleiro para exportação da AUSTRALIA | C62: Acompanhar e auxiliar montagem | D62: 2- Média | E62: Bruno Pivoto | F62: 1 | G62: =SUMIF(tbl_PlanilhaB[Projeto],Base_Projetos[[#This Row],[Projeto]],tbl_PlanilhaB[Valor previsto]) -> 0 | H62: =SUMIF(tbl_PlanilhaB[Projeto],Base_Projetos[[#This Row],[Projeto]],tbl_PlanilhaB[Valor gasto]) -> 0 | I62: =_xlfn.MINIFS(TAREFAS!E:E,TAREFAS!B:B,Base_Projetos[[#This Row],[Projeto]]) -> 45538 | J62: =_xlfn.MAXIFS(TAREFAS!G:G,TAREFAS!B:B,Base_Projetos[[#This Row],[Projeto]]) -> 45540 | K62: =IF(Base_Projetos[[#This Row],[Total de tarefas]]=Base_Projetos[[#This Row],[Tarefas não iniciadas]],"Não iniciado",_xlfn.MINIFS(TAREFAS!H:H,TAREFAS!B:B,Base_Projetos[[#This Row],[Projeto]])) -> 45538 | L62: =IF(Base_Projetos[[#This Row],[Total de tarefas]]=Base_Projetos[[#This Row],[Tarefas Concluídas]],_xlfn.MAXIFS(TAREFAS!H:H,TAREFAS!B:B,Base_Projetos[[#This Row],[Projeto]]),IF(Base_Projetos[[#This Row],[Total de tarefas]]=Base_Projetos[[#This Row],[Tarefas não iniciadas]],"Não iniciado","Em andamento")) -> 45538 | M62: =SUM(Base_Projetos[[#This Row],[Tarefas Concluídas]:[Tarefas não iniciadas]]) -> 1 | N62: =COUNTIFS(tbl_PlanilhaB[Projeto],Base_Projetos[[#This Row],[Projeto]],tbl_PlanilhaB[Status],"Concluído") -> 1 | O62: =COUNTIFS(tbl_PlanilhaB[Projeto],Base_Projetos[[#This Row],[Projeto]],tbl_PlanilhaB[Status],"Em andamento") -> 0 | P62: =COUNTIFS(tbl_PlanilhaB[Projeto],Base_Projetos[[#This Row],[Projeto]],tbl_PlanilhaB[Status],"Atrasado") -> 0 | Q62: =COUNTIFS(tbl_PlanilhaB[Projeto],Base_Projetos[[#This Row],[Projeto]],tbl_PlanilhaB[Status],"Não iniciado") -> 0 | R62: =IF(Base_Projetos[[#This Row],[Total de tarefas]]=Base_Projetos[[#This Row],[Tarefas Concluídas]],"Concluído",IF(Base_Projetos[[#This Row],[Tarefas não iniciadas]]=Base_Projetos[[#This Row],[Total de tarefas]],"Não iniciado",IF(Base_Projetos[[#This Row],[Tarefas atrasadas]]>0,"Atrasado","Em andamento"))) -> Concluído | S62: =Base_Projetos[[#This Row],[Tarefas Concluídas]]/Base_Projetos[[#This Row],[Total de tarefas]] -> 1
A63: =A62+1 -> 59 | B63: Trabalho Padrão da Operação de Serragem de Aços | C63: Estudar processo e elaborar dovcumentação | D63: 3- Alta | E63: João Calheiros | F63: 1 | G63: =SUMIF(tbl_PlanilhaB[Projeto],Base_Projetos[[#This Row],[Projeto]],tbl_PlanilhaB[Valor previsto]) -> 0 | H63: =SUMIF(tbl_PlanilhaB[Projeto],Base_Projetos[[#This Row],[Projeto]],tbl_PlanilhaB[Valor gasto]) -> 0 | I63: =_xlfn.MINIFS(TAREFAS!E:E,TAREFAS!B:B,Base_Projetos[[#This Row],[Projeto]]) -> 45565 | J63: =_xlfn.MAXIFS(TAREFAS!G:G,TAREFAS!B:B,Base_Projetos[[#This Row],[Projeto]]) -> 45568 | K63: =IF(Base_Projetos[[#This Row],[Total de tarefas]]=Base_Projetos[[#This Row],[Tarefas não iniciadas]],"Não iniciado",_xlfn.MINIFS(TAREFAS!H:H,TAREFAS!B:B,Base_Projetos[[#This Row],[Projeto]])) -> 45565 | L63: =IF(Base_Projetos[[#This Row],[Total de tarefas]]=Base_Projetos[[#This Row],[Tarefas Concluídas]],_xlfn.MAXIFS(TAREFAS!H:H,TAREFAS!B:B,Base_Projetos[[#This Row],[Projeto]]),IF(Base_Projetos[[#This Row],[Total de tarefas]]=Base_Projetos[[#This Row],[Tarefas não iniciadas]],"Não iniciado","Em andamento")) -> 45567 | M63: =SUM(Base_Projetos[[#This Row],[Tarefas Concluídas]:[Tarefas não iniciadas]]) -> 2 | N63: =COUNTIFS(tbl_PlanilhaB[Projeto],Base_Projetos[[#This Row],[Projeto]],tbl_PlanilhaB[Status],"Concluído") -> 2 | O63: =COUNTIFS(tbl_PlanilhaB[Projeto],Base_Projetos[[#This Row],[Projeto]],tbl_PlanilhaB[Status],"Em andamento") -> 0 | P63: =COUNTIFS(tbl_PlanilhaB[Projeto],Base_Projetos[[#This Row],[Projeto]],tbl_PlanilhaB[Status],"Atrasado") -> 0 | Q63: =COUNTIFS(tbl_PlanilhaB[Projeto],Base_Projetos[[#This Row],[Projeto]],tbl_PlanilhaB[Status],"Não iniciado") -> 0 | R63: =IF(Base_Projetos[[#This Row],[Total de tarefas]]=Base_Projetos[[#This Row],[Tarefas Concluídas]],"Concluído",IF(Base_Projetos[[#This Row],[Tarefas não iniciadas]]=Base_Projetos[[#This Row],[Total de tarefas]],"Não iniciado",IF(Base_Projetos[[#This Row],[Tarefas atrasadas]]>0,"Atrasado","Em andamento"))) -> Concluído | S63: =Base_Projetos[[#This Row],[Tarefas Concluídas]]/Base_Projetos[[#This Row],[Total de tarefas]] -> 1
A64: =A63+1 -> 60 | B64: Relatório Processo de Solda TIG | D64: 3- Alta | E64: João Calheiros | F64: 1 | G64: =SUMIF(tbl_PlanilhaB[Projeto],Base_Projetos[[#This Row],[Projeto]],tbl_PlanilhaB[Valor previsto]) -> 0 | H64: =SUMIF(tbl_PlanilhaB[Projeto],Base_Projetos[[#This Row],[Projeto]],tbl_PlanilhaB[Valor gasto]) -> 0 | I64: =_xlfn.MINIFS(TAREFAS!E:E,TAREFAS!B:B,Base_Projetos[[#This Row],[Projeto]]) -> 45569 | J64: =_xlfn.MAXIFS(TAREFAS!G:G,TAREFAS!B:B,Base_Projetos[[#This Row],[Projeto]]) -> 45597 | K64: =IF(Base_Projetos[[#This Row],[Total de tarefas]]=Base_Projetos[[#This Row],[Tarefas não iniciadas]],"Não iniciado",_xlfn.MINIFS(TAREFAS!H:H,TAREFAS!B:B,Base_Projetos[[#This Row],[Projeto]])) -> 45569 | L64: =IF(Base_Projetos[[#This Row],[Total de tarefas]]=Base_Projetos[[#This Row],[Tarefas Concluídas]],_xlfn.MAXIFS(TAREFAS!H:H,TAREFAS!B:B,Base_Projetos[[#This Row],[Projeto]]),IF(Base_Projetos[[#This Row],[Total de tarefas]]=Base_Projetos[[#This Row],[Tarefas não iniciadas]],"Não iniciado","Em andamento")) -> 45575 | M64: =SUM(Base_Projetos[[#This Row],[Tarefas Concluídas]:[Tarefas não iniciadas]]) -> 4 | N64: =COUNTIFS(tbl_PlanilhaB[Projeto],Base_Projetos[[#This Row],[Projeto]],tbl_PlanilhaB[Status],"Concluído") -> 4 | O64: =COUNTIFS(tbl_PlanilhaB[Projeto],Base_Projetos[[#This Row],[Projeto]],tbl_PlanilhaB[Status],"Em andamento") -> 0 | P64: =COUNTIFS(tbl_PlanilhaB[Projeto],Base_Projetos[[#This Row],[Projeto]],tbl_PlanilhaB[Status],"Atrasado") -> 0 | Q64: =COUNTIFS(tbl_PlanilhaB[Projeto],Base_Projetos[[#This Row],[Projeto]],tbl_PlanilhaB[Status],"Não iniciado") -> 0 | R64: =IF(Base_Projetos[[#This Row],[Total de tarefas]]=Base_Projetos[[#This Row],[Tarefas Concluídas]],"Concluído",IF(Base_Projetos[[#This Row],[Tarefas não iniciadas]]=Base_Projetos[[#This Row],[Total de tarefas]],"Não iniciado",IF(Base_Projetos[[#This Row],[Tarefas atrasadas]]>0,"Atrasado","Em andamento"))) -> Concluído | S64: =Base_Projetos[[#This Row],[Tarefas Concluídas]]/Base_Projetos[[#This Row],[Total de tarefas]] -> 1
A65: =A64+1 -> 61 | B65: Documentação Máquinas de Corte a Laser | C65: Elaborar Instrução de Trabalho e Sequência Operacional | D65: 3- Alta | E65: João Calheiros | F65: 1 | G65: =SUMIF(tbl_PlanilhaB[Projeto],Base_Projetos[[#This Row],[Projeto]],tbl_PlanilhaB[Valor previsto]) -> 0 | H65: =SUMIF(tbl_PlanilhaB[Projeto],Base_Projetos[[#This Row],[Projeto]],tbl_PlanilhaB[Valor gasto]) -> 0 | I65: =_xlfn.MINIFS(TAREFAS!E:E,TAREFAS!B:B,Base_Projetos[[#This Row],[Projeto]]) -> 45583 | J65: =_xlfn.MAXIFS(TAREFAS!G:G,TAREFAS!B:B,Base_Projetos[[#This Row],[Projeto]]) -> 45595 | K65: =IF(Base_Projetos[[#This Row],[Total de tarefas]]=Base_Projetos[[#This Row],[Tarefas não iniciadas]],"Não iniciado",_xlfn.MINIFS(TAREFAS!H:H,TAREFAS!B:B,Base_Projetos[[#This Row],[Projeto]])) -> 45583 | L65: =IF(Base_Projetos[[#This Row],[Total de tarefas]]=Base_Projetos[[#This Row],[Tarefas Concluídas]],_xlfn.MAXIFS(TAREFAS!H:H,TAREFAS!B:B,Base_Projetos[[#This Row],[Projeto]]),IF(Base_Projetos[[#This Row],[Total de tarefas]]=Base_Projetos[[#This Row],[Tarefas não iniciadas]],"Não iniciado","Em andamento")) -> 45586 | M65: =SUM(Base_Projetos[[#This Row],[Tarefas Concluídas]:[Tarefas não iniciadas]]) -> 2 | N65: =COUNTIFS(tbl_PlanilhaB[Projeto],Base_Projetos[[#This Row],[Projeto]],tbl_PlanilhaB[Status],"Concluído") -> 2 | O65: =COUNTIFS(tbl_PlanilhaB[Projeto],Base_Projetos[[#This Row],[Projeto]],tbl_PlanilhaB[Status],"Em andamento") -> 0 | P65: =COUNTIFS(tbl_PlanilhaB[Projeto],Base_Projetos[[#This Row],[Projeto]],tbl_PlanilhaB[Status],"Atrasado") -> 0 | Q65: =COUNTIFS(tbl_PlanilhaB[Projeto],Base_Projetos[[#This Row],[Projeto]],tbl_PlanilhaB[Status],"Não iniciado") -> 0 | R65: =IF(Base_Projetos[[#This Row],[Total de tarefas]]=Base_Projetos[[#This Row],[Tarefas Concluídas]],"Concluído",IF(Base_Projetos[[#This Row],[Tarefas não iniciadas]]=Base_Projetos[[#This Row],[Total de tarefas]],"Não iniciado",IF(Base_Projetos[[#This Row],[Tarefas atrasadas]]>0,"Atrasado","Em andamento"))) -> Concluído | S65: =Base_Projetos[[#This Row],[Tarefas Concluídas]]/Base_Projetos[[#This Row],[Total de tarefas]] -> 1
A66: =A65+1 -> 62 | B66: Simulação de Carga Zambia | C66: Simular carga em container | D66: 3- Alta | E66: Bruno Pivoto | F66: 1 | G66: =SUMIF(tbl_PlanilhaB[Projeto],Base_Projetos[[#This Row],[Projeto]],tbl_PlanilhaB[Valor previsto]) -> 0 | H66: =SUMIF(tbl_PlanilhaB[Projeto],Base_Projetos[[#This Row],[Projeto]],tbl_PlanilhaB[Valor gasto]) -> 0 | I66: =_xlfn.MINIFS(TAREFAS!E:E,TAREFAS!B:B,Base_Projetos[[#This Row],[Projeto]]) -> 45589 | J66: =_xlfn.MAXIFS(TAREFAS!G:G,TAREFAS!B:B,Base_Projetos[[#This Row],[Projeto]]) -> 45593 | K66: =IF(Base_Projetos[[#This Row],[Total de tarefas]]=Base_Projetos[[#This Row],[Tarefas não iniciadas]],"Não iniciado",_xlfn.MINIFS(TAREFAS!H:H,TAREFAS!B:B,Base_Projetos[[#This Row],[Projeto]])) -> 45589 | L66: =IF(Base_Projetos[[#This Row],[Total de tarefas]]=Base_Projetos[[#This Row],[Tarefas Concluídas]],_xlfn.MAXIFS(TAREFAS!H:H,TAREFAS!B:B,Base_Projetos[[#This Row],[Projeto]]),IF(Base_Projetos[[#This Row],[Total de tarefas]]=Base_Projetos[[#This Row],[Tarefas não iniciadas]],"Não iniciado","Em andamento")) -> 45589 | M66: =SUM(Base_Projetos[[#This Row],[Tarefas Concluídas]:[Tarefas não iniciadas]]) -> 1 | N66: =COUNTIFS(tbl_PlanilhaB[Projeto],Base_Projetos[[#This Row],[Projeto]],tbl_PlanilhaB[Status],"Concluído") -> 1 | O66: =COUNTIFS(tbl_PlanilhaB[Projeto],Base_Projetos[[#This Row],[Projeto]],tbl_PlanilhaB[Status],"Em andamento") -> 0 | P66: =COUNTIFS(tbl_PlanilhaB[Projeto],Base_Projetos[[#This Row],[Projeto]],tbl_PlanilhaB[Status],"Atrasado") -> 0 | Q66: =COUNTIFS(tbl_PlanilhaB[Projeto],Base_Projetos[[#This Row],[Projeto]],tbl_PlanilhaB[Status],"Não iniciado") -> 0 | R66: =IF(Base_Projetos[[#This Row],[Total de tarefas]]=Base_Projetos[[#This Row],[Tarefas Concluídas]],"Concluído",IF(Base_Projetos[[#This Row],[Tarefas não iniciadas]]=Base_Projetos[[#This Row],[Total de tarefas]],"Não iniciado",IF(Base_Projetos[[#This Row],[Tarefas atrasadas]]>0,"Atrasado","Em andamento"))) -> Concluído | S66: =Base_Projetos[[#This Row],[Tarefas Concluídas]]/Base_Projetos[[#This Row],[Total de tarefas]] -> 1
A67: =A66+1 -> 63 | B67: Simulação de Carga Colombia | C67: Simular carga em container | D67: 3- Alta | E67: Bruno Pivoto | F67: 1 | G67: =SUMIF(tbl_PlanilhaB[Projeto],Base_Projetos[[#This Row],[Projeto]],tbl_PlanilhaB[Valor previsto]) -> 0 | H67: =SUMIF(tbl_PlanilhaB[Projeto],Base_Projetos[[#This Row],[Projeto]],tbl_PlanilhaB[Valor gasto]) -> 0 | I67: =_xlfn.MINIFS(TAREFAS!E:E,TAREFAS!B:B,Base_Projetos[[#This Row],[Projeto]]) -> 45593 | J67: =_xlfn.MAXIFS(TAREFAS!G:G,TAREFAS!B:B,Base_Projetos[[#This Row],[Projeto]]) -> 45595 | K67: =IF(Base_Projetos[[#This Row],[Total de tarefas]]=Base_Projetos[[#This Row],[Tarefas não iniciadas]],"Não iniciado",_xlfn.MINIFS(TAREFAS!H:H,TAREFAS!B:B,Base_Projetos[[#This Row],[Projeto]])) -> 45593 | L67: =IF(Base_Projetos[[#This Row],[Total de tarefas]]=Base_Projetos[[#This Row],[Tarefas Concluídas]],_xlfn.MAXIFS(TAREFAS!H:H,TAREFAS!B:B,Base_Projetos[[#This Row],[Projeto]]),IF(Base_Projetos[[#This Row],[Total de tarefas]]=Base_Projetos[[#This Row],[Tarefas não iniciadas]],"Não iniciado","Em andamento")) -> 45593 | M67: =SUM(Base_Projetos[[#This Row],[Tarefas Concluídas]:[Tarefas não iniciadas]]) -> 1 | N67: =COUNTIFS(tbl_PlanilhaB[Projeto],Base_Projetos[[#This Row],[Projeto]],tbl_PlanilhaB[Status],"Concluído") -> 1 | O67: =COUNTIFS(tbl_PlanilhaB[Projeto],Base_Projetos[[#This Row],[Projeto]],tbl_PlanilhaB[Status],"Em andamento") -> 0 | P67: =COUNTIFS(tbl_PlanilhaB[Projeto],Base_Projetos[[#This Row],[Projeto]],tbl_PlanilhaB[Status],"Atrasado") -> 0 | Q67: =COUNTIFS(tbl_PlanilhaB[Projeto],Base_Projetos[[#This Row],[Projeto]],tbl_PlanilhaB[Status],"Não iniciado") -> 0 | R67: =IF(Base_Projetos[[#This Row],[Total de tarefas]]=Base_Projetos[[#This Row],[Tarefas Concluídas]],"Concluído",IF(Base_Projetos[[#This Row],[Tarefas não iniciadas]]=Base_Projetos[[#This Row],[Total de tarefas]],"Não iniciado",IF(Base_Projetos[[#This Row],[Tarefas atrasadas]]>0,"Atrasado","Em andamento"))) -> Concluído | S67: =Base_Projetos[[#This Row],[Tarefas Concluídas]]/Base_Projetos[[#This Row],[Total de tarefas]] -> 1
A68: =A67+1 -> 64 | B68: Simulação de Carga Panamá | C68: Simular carga em container | D68: 3- Alta | E68: Bruno Pivoto | F68: 1 | G68: =SUMIF(tbl_PlanilhaB[Projeto],Base_Projetos[[#This Row],[Projeto]],tbl_PlanilhaB[Valor previsto]) -> 0 | H68: =SUMIF(tbl_PlanilhaB[Projeto],Base_Projetos[[#This Row],[Projeto]],tbl_PlanilhaB[Valor gasto]) -> 0 | I68: =_xlfn.MINIFS(TAREFAS!E:E,TAREFAS!B:B,Base_Projetos[[#This Row],[Projeto]]) -> 45594 | J68: =_xlfn.MAXIFS(TAREFAS!G:G,TAREFAS!B:B,Base_Projetos[[#This Row],[Projeto]]) -> 45597 | K68: =IF(Base_Projetos[[#This Row],[Total de tarefas]]=Base_Projetos[[#This Row],[Tarefas não iniciadas]],"Não iniciado",_xlfn.MINIFS(TAREFAS!H:H,TAREFAS!B:B,Base_Projetos[[#This Row],[Projeto]])) -> 45594 | L68: =IF(Base_Projetos[[#This Row],[Total de tarefas]]=Base_Projetos[[#This Row],[Tarefas Concluídas]],_xlfn.MAXIFS(TAREFAS!H:H,TAREFAS!B:B,Base_Projetos[[#This Row],[Projeto]]),IF(Base_Projetos[[#This Row],[Total de tarefas]]=Base_Projetos[[#This Row],[Tarefas não iniciadas]],"Não iniciado","Em andamento")) -> 45595 | M68: =SUM(Base_Projetos[[#This Row],[Tarefas Concluídas]:[Tarefas não iniciadas]]) -> 2 | N68: =COUNTIFS(tbl_PlanilhaB[Projeto],Base_Projetos[[#This Row],[Projeto]],tbl_PlanilhaB[Status],"Concluído") -> 2 | O68: =COUNTIFS(tbl_PlanilhaB[Projeto],Base_Projetos[[#This Row],[Projeto]],tbl_PlanilhaB[Status],"Em andamento") -> 0 | P68: =COUNTIFS(tbl_PlanilhaB[Projeto],Base_Projetos[[#This Row],[Projeto]],tbl_PlanilhaB[Status],"Atrasado") -> 0 | Q68: =COUNTIFS(tbl_PlanilhaB[Projeto],Base_Projetos[[#This Row],[Projeto]],tbl_PlanilhaB[Status],"Não iniciado") -> 0 | R68: =IF(Base_Projetos[[#This Row],[Total de tarefas]]=Base_Projetos[[#This Row],[Tarefas Concluídas]],"Concluído",IF(Base_Projetos[[#This Row],[Tarefas não iniciadas]]=Base_Projetos[[#This Row],[Total de tarefas]],"Não iniciado",IF(Base_Projetos[[#This Row],[Tarefas atrasadas]]>0,"Atrasado","Em andamento"))) -> Concluído | S68: =Base_Projetos[[#This Row],[Tarefas Concluídas]]/Base_Projetos[[#This Row],[Total de tarefas]] -> 1
A69: =A68+1 -> 65 | B69: Gabarito para corte de eixo FTA | C69: Projetar, Modelar e detalhar | D69: 1- Baixa | E69: Bruno Pivoto | F69: 1 | G69: =SUMIF(tbl_PlanilhaB[Projeto],Base_Projetos[[#This Row],[Projeto]],tbl_PlanilhaB[Valor previsto]) -> 0 | H69: =SUMIF(tbl_PlanilhaB[Projeto],Base_Projetos[[#This Row],[Projeto]],tbl_PlanilhaB[Valor gasto]) -> 0 | I69: =_xlfn.MINIFS(TAREFAS!E:E,TAREFAS!B:B,Base_Projetos[[#This Row],[Projeto]]) -> 45594 | J69: =_xlfn.MAXIFS(TAREFAS!G:G,TAREFAS!B:B,Base_Projetos[[#This Row],[Projeto]]) -> 45596 | K69: =IF(Base_Projetos[[#This Row],[Total de tarefas]]=Base_Projetos[[#This Row],[Tarefas não iniciadas]],"Não iniciado",_xlfn.MINIFS(TAREFAS!H:H,TAREFAS!B:B,Base_Projetos[[#This Row],[Projeto]])) -> 45594 | L69: =IF(Base_Projetos[[#This Row],[Total de tarefas]]=Base_Projetos[[#This Row],[Tarefas Concluídas]],_xlfn.MAXIFS(TAREFAS!H:H,TAREFAS!B:B,Base_Projetos[[#This Row],[Projeto]]),IF(Base_Projetos[[#This Row],[Total de tarefas]]=Base_Projetos[[#This Row],[Tarefas não iniciadas]],"Não iniciado","Em andamento")) -> 45595 | M69: =SUM(Base_Projetos[[#This Row],[Tarefas Concluídas]:[Tarefas não iniciadas]]) -> 2 | N69: =COUNTIFS(tbl_PlanilhaB[Projeto],Base_Projetos[[#This Row],[Projeto]],tbl_PlanilhaB[Status],"Concluído") -> 2 | O69: =COUNTIFS(tbl_PlanilhaB[Projeto],Base_Projetos[[#This Row],[Projeto]],tbl_PlanilhaB[Status],"Em andamento") -> 0 | P69: =COUNTIFS(tbl_PlanilhaB[Projeto],Base_Projetos[[#This Row],[Projeto]],tbl_PlanilhaB[Status],"Atrasado") -> 0 | Q69: =COUNTIFS(tbl_PlanilhaB[Projeto],Base_Projetos[[#This Row],[Projeto]],tbl_PlanilhaB[Status],"Não iniciado") -> 0 | R69: =IF(Base_Projetos[[#This Row],[Total de tarefas]]=Base_Projetos[[#This Row],[Tarefas Concluídas]],"Concluído",IF(Base_Projetos[[#This Row],[Tarefas não iniciadas]]=Base_Projetos[[#This Row],[Total de tarefas]],"Não iniciado",IF(Base_Projetos[[#This Row],[Tarefas atrasadas]]>0,"Atrasado","Em andamento"))) -> Concluído | S69: =Base_Projetos[[#This Row],[Tarefas Concluídas]]/Base_Projetos[[#This Row],[Total de tarefas]] -> 1
A70: =A69+1 -> 66 | B70: Produção de caixas pradrão para peças de reposição em carregamentos | C70: Simular, projetar, modelar e detalhar | D70: 2- Média | E70: Bruno Pivoto | F70: 1 | G70: =SUMIF(tbl_PlanilhaB[Projeto],Base_Projetos[[#This Row],[Projeto]],tbl_PlanilhaB[Valor previsto]) -> 0 | H70: =SUMIF(tbl_PlanilhaB[Projeto],Base_Projetos[[#This Row],[Projeto]],tbl_PlanilhaB[Valor gasto]) -> 0 | I70: =_xlfn.MINIFS(TAREFAS!E:E,TAREFAS!B:B,Base_Projetos[[#This Row],[Projeto]]) -> 45600 | J70: =_xlfn.MAXIFS(TAREFAS!G:G,TAREFAS!B:B,Base_Projetos[[#This Row],[Projeto]]) -> 45621 | K70: =IF(Base_Projetos[[#This Row],[Total de tarefas]]=Base_Projetos[[#This Row],[Tarefas não iniciadas]],"Não iniciado",_xlfn.MINIFS(TAREFAS!H:H,TAREFAS!B:B,Base_Projetos[[#This Row],[Projeto]])) -> 45600 | L70: =IF(Base_Projetos[[#This Row],[Total de tarefas]]=Base_Projetos[[#This Row],[Tarefas Concluídas]],_xlfn.MAXIFS(TAREFAS!H:H,TAREFAS!B:B,Base_Projetos[[#This Row],[Projeto]]),IF(Base_Projetos[[#This Row],[Total de tarefas]]=Base_Projetos[[#This Row],[Tarefas não iniciadas]],"Não iniciado","Em andamento")) -> 45600 | M70: =SUM(Base_Projetos[[#This Row],[Tarefas Concluídas]:[Tarefas não iniciadas]]) -> 1 | N70: =COUNTIFS(tbl_PlanilhaB[Projeto],Base_Projetos[[#This Row],[Projeto]],tbl_PlanilhaB[Status],"Concluído") -> 1 | O70: =COUNTIFS(tbl_PlanilhaB[Projeto],Base_Projetos[[#This Row],[Projeto]],tbl_PlanilhaB[Status],"Em andamento") -> 0 | P70: =COUNTIFS(tbl_PlanilhaB[Projeto],Base_Projetos[[#This Row],[Projeto]],tbl_PlanilhaB[Status],"Atrasado") -> 0 | Q70: =COUNTIFS(tbl_PlanilhaB[Projeto],Base_Projetos[[#This Row],[Projeto]],tbl_PlanilhaB[Status],"Não iniciado") -> 0 | R70: =IF(Base_Projetos[[#This Row],[Total de tarefas]]=Base_Projetos[[#This Row],[Tarefas Concluídas]],"Concluído",IF(Base_Projetos[[#This Row],[Tarefas não iniciadas]]=Base_Projetos[[#This Row],[Total de tarefas]],"Não iniciado",IF(Base_Projetos[[#This Row],[Tarefas atrasadas]]>0,"Atrasado","Em andamento"))) -> Concluído | S70: =Base_Projetos[[#This Row],[Tarefas Concluídas]]/Base_Projetos[[#This Row],[Total de tarefas]] -> 1
A71: =A70+1 -> 67 | B71: Planilha de Controle Corte e Sobra | C71: Estudar , Elaborar, Implementar | D71: 3- Alta | E71: João Calheiros | F71: 1 | G71: =SUMIF(tbl_PlanilhaB[Projeto],Base_Projetos[[#This Row],[Projeto]],tbl_PlanilhaB[Valor previsto]) -> 0 | H71: =SUMIF(tbl_PlanilhaB[Projeto],Base_Projetos[[#This Row],[Projeto]],tbl_PlanilhaB[Valor gasto]) -> 0 | I71: =_xlfn.MINIFS(TAREFAS!E:E,TAREFAS!B:B,Base_Projetos[[#This Row],[Projeto]]) -> 45597 | J71: =_xlfn.MAXIFS(TAREFAS!G:G,TAREFAS!B:B,Base_Projetos[[#This Row],[Projeto]]) -> 45604 | K71: =IF(Base_Projetos[[#This Row],[Total de tarefas]]=Base_Projetos[[#This Row],[Tarefas não iniciadas]],"Não iniciado",_xlfn.MINIFS(TAREFAS!H:H,TAREFAS!B:B,Base_Projetos[[#This Row],[Projeto]])) -> 45600 | L71: =IF(Base_Projetos[[#This Row],[Total de tarefas]]=Base_Projetos[[#This Row],[Tarefas Concluídas]],_xlfn.MAXIFS(TAREFAS!H:H,TAREFAS!B:B,Base_Projetos[[#This Row],[Projeto]]),IF(Base_Projetos[[#This Row],[Total de tarefas]]=Base_Projetos[[#This Row],[Tarefas não iniciadas]],"Não iniciado","Em andamento")) -> 45604 | M71: =SUM(Base_Projetos[[#This Row],[Tarefas Concluídas]:[Tarefas não iniciadas]]) -> 2 | N71: =COUNTIFS(tbl_PlanilhaB[Projeto],Base_Projetos[[#This Row],[Projeto]],tbl_PlanilhaB[Status],"Concluído") -> 2 | O71: =COUNTIFS(tbl_PlanilhaB[Projeto],Base_Projetos[[#This Row],[Projeto]],tbl_PlanilhaB[Status],"Em andamento") -> 0 | P71: =COUNTIFS(tbl_PlanilhaB[Projeto],Base_Projetos[[#This Row],[Projeto]],tbl_PlanilhaB[Status],"Atrasado") -> 0 | Q71: =COUNTIFS(tbl_PlanilhaB[Projeto],Base_Projetos[[#This Row],[Projeto]],tbl_PlanilhaB[Status],"Não iniciado") -> 0 | R71: =IF(Base_Projetos[[#This Row],[Total de tarefas]]=Base_Projetos[[#This Row],[Tarefas Concluídas]],"Concluído",IF(Base_Projetos[[#This Row],[Tarefas não iniciadas]]=Base_Projetos[[#This Row],[Total de tarefas]],"Não iniciado",IF(Base_Projetos[[#This Row],[Tarefas atrasadas]]>0,"Atrasado","Em andamento"))) -> Concluído | S71: =Base_Projetos[[#This Row],[Tarefas Concluídas]]/Base_Projetos[[#This Row],[Total de tarefas]] -> 1
A72: =A71+1 -> 68 | B72: Teste de Soldagem MIG e TIG para Orçamento de Máquinas Sumig | C72: Observar e Testar | D72: 3- Alta | E72: João Calheiros | F72: 1 | G72: =SUMIF(tbl_PlanilhaB[Projeto],Base_Projetos[[#This Row],[Projeto]],tbl_PlanilhaB[Valor previsto]) -> 0 | H72: =SUMIF(tbl_PlanilhaB[Projeto],Base_Projetos[[#This Row],[Projeto]],tbl_PlanilhaB[Valor gasto]) -> 0 | I72: =_xlfn.MINIFS(TAREFAS!E:E,TAREFAS!B:B,Base_Projetos[[#This Row],[Projeto]]) -> 45604 | J72: =_xlfn.MAXIFS(TAREFAS!G:G,TAREFAS!B:B,Base_Projetos[[#This Row],[Projeto]]) -> 45608 | K72: =IF(Base_Projetos[[#This Row],[Total de tarefas]]=Base_Projetos[[#This Row],[Tarefas não iniciadas]],"Não iniciado",_xlfn.MINIFS(TAREFAS!H:H,TAREFAS!B:B,Base_Projetos[[#This Row],[Projeto]])) -> 45604 | L72: =IF(Base_Projetos[[#This Row],[Total de tarefas]]=Base_Projetos[[#This Row],[Tarefas Concluídas]],_xlfn.MAXIFS(TAREFAS!H:H,TAREFAS!B:B,Base_Projetos[[#This Row],[Projeto]]),IF(Base_Projetos[[#This Row],[Total de tarefas]]=Base_Projetos[[#This Row],[Tarefas não iniciadas]],"Não iniciado","Em andamento")) -> 45604 | M72: =SUM(Base_Projetos[[#This Row],[Tarefas Concluídas]:[Tarefas não iniciadas]]) -> 1 | N72: =COUNTIFS(tbl_PlanilhaB[Projeto],Base_Projetos[[#This Row],[Projeto]],tbl_PlanilhaB[Status],"Concluído") -> 1 | O72: =COUNTIFS(tbl_PlanilhaB[Projeto],Base_Projetos[[#This Row],[Projeto]],tbl_PlanilhaB[Status],"Em andamento") -> 0 | P72: =COUNTIFS(tbl_PlanilhaB[Projeto],Base_Projetos[[#This Row],[Projeto]],tbl_PlanilhaB[Status],"Atrasado") -> 0 | Q72: =COUNTIFS(tbl_PlanilhaB[Projeto],Base_Projetos[[#This Row],[Projeto]],tbl_PlanilhaB[Status],"Não iniciado") -> 0 | R72: =IF(Base_Projetos[[#This Row],[Total de tarefas]]=Base_Projetos[[#This Row],[Tarefas Concluídas]],"Concluído",IF(Base_Projetos[[#This Row],[Tarefas não iniciadas]]=Base_Projetos[[#This Row],[Total de tarefas]],"Não iniciado",IF(Base_Projetos[[#This Row],[Tarefas atrasadas]]>0,"Atrasado","Em andamento"))) -> Concluído | S72: =Base_Projetos[[#This Row],[Tarefas Concluídas]]/Base_Projetos[[#This Row],[Total de tarefas]] -> 1
A73: =A72+1 -> 69 | B73: Relatório Processo de Solda MIG/MAG Aços Carbono | C73: Pesquisar, Escrever, Simular e Testar | D73: 3- Alta | E73: João Calheiros | F73: 1 | G73: =SUMIF(tbl_PlanilhaB[Projeto],Base_Projetos[[#This Row],[Projeto]],tbl_PlanilhaB[Valor previsto]) -> 0 | H73: =SUMIF(tbl_PlanilhaB[Projeto],Base_Projetos[[#This Row],[Projeto]],tbl_PlanilhaB[Valor gasto]) -> 0 | I73: =_xlfn.MINIFS(TAREFAS!E:E,TAREFAS!B:B,Base_Projetos[[#This Row],[Projeto]]) -> 45608 | J73: =_xlfn.MAXIFS(TAREFAS!G:G,TAREFAS!B:B,Base_Projetos[[#This Row],[Projeto]]) -> 45615 | K73: =IF(Base_Projetos[[#This Row],[Total de tarefas]]=Base_Projetos[[#This Row],[Tarefas não iniciadas]],"Não iniciado",_xlfn.MINIFS(TAREFAS!H:H,TAREFAS!B:B,Base_Projetos[[#This Row],[Projeto]])) -> 45607 | L73: =IF(Base_Projetos[[#This Row],[Total de tarefas]]=Base_Projetos[[#This Row],[Tarefas Concluídas]],_xlfn.MAXIFS(TAREFAS!H:H,TAREFAS!B:B,Base_Projetos[[#This Row],[Projeto]]),IF(Base_Projetos[[#This Row],[Total de tarefas]]=Base_Projetos[[#This Row],[Tarefas não iniciadas]],"Não iniciado","Em andamento")) -> 45610 | M73: =SUM(Base_Projetos[[#This Row],[Tarefas Concluídas]:[Tarefas não iniciadas]]) -> 2 | N73: =COUNTIFS(tbl_PlanilhaB[Projeto],Base_Projetos[[#This Row],[Projeto]],tbl_PlanilhaB[Status],"Concluído") -> 2 | O73: =COUNTIFS(tbl_PlanilhaB[Projeto],Base_Projetos[[#This Row],[Projeto]],tbl_PlanilhaB[Status],"Em andamento") -> 0 | P73: =COUNTIFS(tbl_PlanilhaB[Projeto],Base_Projetos[[#This Row],[Projeto]],tbl_PlanilhaB[Status],"Atrasado") -> 0 | Q73: =COUNTIFS(tbl_PlanilhaB[Projeto],Base_Projetos[[#This Row],[Projeto]],tbl_PlanilhaB[Status],"Não iniciado") -> 0 | R73: =IF(Base_Projetos[[#This Row],[Total de tarefas]]=Base_Projetos[[#This Row],[Tarefas Concluídas]],"Concluído",IF(Base_Projetos[[#This Row],[Tarefas não iniciadas]]=Base_Projetos[[#This Row],[Total de tarefas]],"Não iniciado",IF(Base_Projetos[[#This Row],[Tarefas atrasadas]]>0,"Atrasado","Em andamento"))) -> Concluído | S73: =Base_Projetos[[#This Row],[Tarefas Concluídas]]/Base_Projetos[[#This Row],[Total de tarefas]] -> 1
A74: =A73+1 -> 70 | B74: Simulação de Carga EUA - Agrival 60L | C74: Simular carga em container | D74: 1- Baixa | E74: Bruno Pivoto | F74: 1 | G74: =SUMIF(tbl_PlanilhaB[Projeto],Base_Projetos[[#This Row],[Projeto]],tbl_PlanilhaB[Valor previsto]) -> 0 | H74: =SUMIF(tbl_PlanilhaB[Projeto],Base_Projetos[[#This Row],[Projeto]],tbl_PlanilhaB[Valor gasto]) -> 0 | I74: =_xlfn.MINIFS(TAREFAS!E:E,TAREFAS!B:B,Base_Projetos[[#This Row],[Projeto]]) -> 45622 | J74: =_xlfn.MAXIFS(TAREFAS!G:G,TAREFAS!B:B,Base_Projetos[[#This Row],[Projeto]]) -> 45624 | K74: =IF(Base_Projetos[[#This Row],[Total de tarefas]]=Base_Projetos[[#This Row],[Tarefas não iniciadas]],"Não iniciado",_xlfn.MINIFS(TAREFAS!H:H,TAREFAS!B:B,Base_Projetos[[#This Row],[Projeto]])) -> 45623 | L74: =IF(Base_Projetos[[#This Row],[Total de tarefas]]=Base_Projetos[[#This Row],[Tarefas Concluídas]],_xlfn.MAXIFS(TAREFAS!H:H,TAREFAS!B:B,Base_Projetos[[#This Row],[Projeto]]),IF(Base_Projetos[[#This Row],[Total de tarefas]]=Base_Projetos[[#This Row],[Tarefas não iniciadas]],"Não iniciado","Em andamento")) -> 45623 | M74: =SUM(Base_Projetos[[#This Row],[Tarefas Concluídas]:[Tarefas não iniciadas]]) -> 1 | N74: =COUNTIFS(tbl_PlanilhaB[Projeto],Base_Projetos[[#This Row],[Projeto]],tbl_PlanilhaB[Status],"Concluído") -> 1 | O74: =COUNTIFS(tbl_PlanilhaB[Projeto],Base_Projetos[[#This Row],[Projeto]],tbl_PlanilhaB[Status],"Em andamento") -> 0 | P74: =COUNTIFS(tbl_PlanilhaB[Projeto],Base_Projetos[[#This Row],[Projeto]],tbl_PlanilhaB[Status],"Atrasado") -> 0 | Q74: =COUNTIFS(tbl_PlanilhaB[Projeto],Base_Projetos[[#This Row],[Projeto]],tbl_PlanilhaB[Status],"Não iniciado") -> 0 | R74: =IF(Base_Projetos[[#This Row],[Total de tarefas]]=Base_Projetos[[#This Row],[Tarefas Concluídas]],"Concluído",IF(Base_Projetos[[#This Row],[Tarefas não iniciadas]]=Base_Projetos[[#This Row],[Total de tarefas]],"Não iniciado",IF(Base_Projetos[[#This Row],[Tarefas atrasadas]]>0,"Atrasado","Em andamento"))) -> Concluído | S74: =Base_Projetos[[#This Row],[Tarefas Concluídas]]/Base_Projetos[[#This Row],[Total de tarefas]] -> 1
A75: =A74+1 -> 71 | B75: Dispositivo de solda para travamento tubos GBX | C75: Desenvolver conceito e o projeto | D75: 2- Média | E75: Fagner | F75: 1 | G75: =SUMIF(tbl_PlanilhaB[Projeto],Base_Projetos[[#This Row],[Projeto]],tbl_PlanilhaB[Valor previsto]) -> 0 | H75: =SUMIF(tbl_PlanilhaB[Projeto],Base_Projetos[[#This Row],[Projeto]],tbl_PlanilhaB[Valor gasto]) -> 0 | I75: =_xlfn.MINIFS(TAREFAS!E:E,TAREFAS!B:B,Base_Projetos[[#This Row],[Projeto]]) -> 45642 | J75: =_xlfn.MAXIFS(TAREFAS!G:G,TAREFAS!B:B,Base_Projetos[[#This Row],[Projeto]]) -> 45663 | K75: =IF(Base_Projetos[[#This Row],[Total de tarefas]]=Base_Projetos[[#This Row],[Tarefas não iniciadas]],"Não iniciado",_xlfn.MINIFS(TAREFAS!H:H,TAREFAS!B:B,Base_Projetos[[#This Row],[Projeto]])) -> 45642 | L75: 45659 | M75: =SUM(Base_Projetos[[#This Row],[Tarefas Concluídas]:[Tarefas não iniciadas]]) -> 3 | N75: =COUNTIFS(tbl_PlanilhaB[Projeto],Base_Projetos[[#This Row],[Projeto]],tbl_PlanilhaB[Status],"Concluído") -> 3 | O75: =COUNTIFS(tbl_PlanilhaB[Projeto],Base_Projetos[[#This Row],[Projeto]],tbl_PlanilhaB[Status],"Em andamento") -> 0 | P75: =COUNTIFS(tbl_PlanilhaB[Projeto],Base_Projetos[[#This Row],[Projeto]],tbl_PlanilhaB[Status],"Atrasado") -> 0 | Q75: =COUNTIFS(tbl_PlanilhaB[Projeto],Base_Projetos[[#This Row],[Projeto]],tbl_PlanilhaB[Status],"Não iniciado") -> 0 | R75: =IF(Base_Projetos[[#This Row],[Total de tarefas]]=Base_Projetos[[#This Row],[Tarefas Concluídas]],"Concluído",IF(Base_Projetos[[#This Row],[Tarefas não iniciadas]]=Base_Projetos[[#This Row],[Total de tarefas]],"Não iniciado",IF(Base_Projetos[[#This Row],[Tarefas atrasadas]]>0,"Atrasado","Em andamento"))) -> Concluído | S75: =Base_Projetos[[#This Row],[Tarefas Concluídas]]/Base_Projetos[[#This Row],[Total de tarefas]] -> 1
A76: =A75+1 -> 72 | B76: Dispositivo de armazenagem paineis GBX | C76: Desenvolver conceito e o projeto | D76: 2- Média | E76: Fagner | F76: 1 | G76: =SUMIF(tbl_PlanilhaB[Projeto],Base_Projetos[[#This Row],[Projeto]],tbl_PlanilhaB[Valor previsto]) -> 0 | H76: =SUMIF(tbl_PlanilhaB[Projeto],Base_Projetos[[#This Row],[Projeto]],tbl_PlanilhaB[Valor gasto]) -> 0 | I76: =_xlfn.MINIFS(TAREFAS!E:E,TAREFAS!B:B,Base_Projetos[[#This Row],[Projeto]]) -> 45671 | J76: =_xlfn.MAXIFS(TAREFAS!G:G,TAREFAS!B:B,Base_Projetos[[#This Row],[Projeto]]) -> 45672 | K76: =IF(Base_Projetos[[#This Row],[Total de tarefas]]=Base_Projetos[[#This Row],[Tarefas não iniciadas]],"Não iniciado",_xlfn.MINIFS(TAREFAS!H:H,TAREFAS!B:B,Base_Projetos[[#This Row],[Projeto]])) -> 45671 | L76: 45671 | M76: =SUM(Base_Projetos[[#This Row],[Tarefas Concluídas]:[Tarefas não iniciadas]]) -> 1 | N76: 1 | O76: =COUNTIFS(tbl_PlanilhaB[Projeto],Base_Projetos[[#This Row],[Projeto]],tbl_PlanilhaB[Status],"Em andamento") -> 0 | P76: =COUNTIFS(tbl_PlanilhaB[Projeto],Base_Projetos[[#This Row],[Projeto]],tbl_PlanilhaB[Status],"Atrasado") -> 0 | Q76: =COUNTIFS(tbl_PlanilhaB[Projeto],Base_Projetos[[#This Row],[Projeto]],tbl_PlanilhaB[Status],"Não iniciado") -> 0 | R76: =IF(Base_Projetos[[#This Row],[Total de tarefas]]=Base_Projetos[[#This Row],[Tarefas Concluídas]],"Concluído",IF(Base_Projetos[[#This Row],[Tarefas não iniciadas]]=Base_Projetos[[#This Row],[Total de tarefas]],"Não iniciado",IF(Base_Projetos[[#This Row],[Tarefas atrasadas]]>0,"Atrasado","Em andamento"))) -> Concluído | S76: =Base_Projetos[[#This Row],[Tarefas Concluídas]]/Base_Projetos[[#This Row],[Total de tarefas]] -> 1
A77: =A76+1 -> 73 | B77: Layout Agrimec Simulação robôs | C77: Desenvolver Layout estado atual e futuro simulando performance dos componente soldados nos robôs. | D77: 3- Alta | E77: Alison | F77: 2 | G77: =SUMIF(tbl_PlanilhaB[Projeto],Base_Projetos[[#This Row],[Projeto]],tbl_PlanilhaB[Valor previsto]) -> 0 | H77: =SUMIF(tbl_PlanilhaB[Projeto],Base_Projetos[[#This Row],[Projeto]],tbl_PlanilhaB[Valor gasto]) -> 0 | I77: =_xlfn.MINIFS(TAREFAS!E:E,TAREFAS!B:B,Base_Projetos[[#This Row],[Projeto]]) -> 45652 | J77: =_xlfn.MAXIFS(TAREFAS!G:G,TAREFAS!B:B,Base_Projetos[[#This Row],[Projeto]]) -> 45667 | K77: =IF(Base_Projetos[[#This Row],[Total de tarefas]]=Base_Projetos[[#This Row],[Tarefas não iniciadas]],"Não iniciado",_xlfn.MINIFS(TAREFAS!H:H,TAREFAS!B:B,Base_Projetos[[#This Row],[Projeto]])) -> 45652 | L77: =IF(Base_Projetos[[#This Row],[Total de tarefas]]=Base_Projetos[[#This Row],[Tarefas Concluídas]],_xlfn.MAXIFS(TAREFAS!H:H,TAREFAS!B:B,Base_Projetos[[#This Row],[Projeto]]),IF(Base_Projetos[[#This Row],[Total de tarefas]]=Base_Projetos[[#This Row],[Tarefas não iniciadas]],"Não iniciado","Em andamento")) -> 45664 | M77: =SUM(Base_Projetos[[#This Row],[Tarefas Concluídas]:[Tarefas não iniciadas]]) -> 2 | N77: =COUNTIFS(tbl_PlanilhaB[Projeto],Base_Projetos[[#This Row],[Projeto]],tbl_PlanilhaB[Status],"Concluído") -> 2 | O77: =COUNTIFS(tbl_PlanilhaB[Projeto],Base_Projetos[[#This Row],[Projeto]],tbl_PlanilhaB[Status],"Em andamento") -> 0 | P77: =COUNTIFS(tbl_PlanilhaB[Projeto],Base_Projetos[[#This Row],[Projeto]],tbl_PlanilhaB[Status],"Atrasado") -> 0 | Q77: =COUNTIFS(tbl_PlanilhaB[Projeto],Base_Projetos[[#This Row],[Projeto]],tbl_PlanilhaB[Status],"Não iniciado") -> 0 | R77: =IF(Base_Projetos[[#This Row],[Total de tarefas]]=Base_Projetos[[#This Row],[Tarefas Concluídas]],"Concluído",IF(Base_Projetos[[#This Row],[Tarefas não iniciadas]]=Base_Projetos[[#This Row],[Total de tarefas]],"Não iniciado",IF(Base_Projetos[[#This Row],[Tarefas atrasadas]]>0,"Atrasado","Em andamento"))) -> Concluído | S77: =Base_Projetos[[#This Row],[Tarefas Concluídas]]/Base_Projetos[[#This Row],[Total de tarefas]] -> 1
A78: =A77+1 -> 74 | B78: Dispositivo para pintura e estufagem | C78: Desenvolver conceito e o projeto | D78: 2- Média | E78: Fagner | F78: 1 | G78: =SUMIF(tbl_PlanilhaB[Projeto],Base_Projetos[[#This Row],[Projeto]],tbl_PlanilhaB[Valor previsto]) -> 0 | H78: =SUMIF(tbl_PlanilhaB[Projeto],Base_Projetos[[#This Row],[Projeto]],tbl_PlanilhaB[Valor gasto]) -> 0 | I78: =_xlfn.MINIFS(TAREFAS!E:E,TAREFAS!B:B,Base_Projetos[[#This Row],[Projeto]]) -> 45671 | J78: =_xlfn.MAXIFS(TAREFAS!G:G,TAREFAS!B:B,Base_Projetos[[#This Row],[Projeto]]) -> 45680 | K78: =IF(Base_Projetos[[#This Row],[Total de tarefas]]=Base_Projetos[[#This Row],[Tarefas não iniciadas]],"Não iniciado",_xlfn.MINIFS(TAREFAS!H:H,TAREFAS!B:B,Base_Projetos[[#This Row],[Projeto]])) -> 45671 | L78: =IF(Base_Projetos[[#This Row],[Total de tarefas]]=Base_Projetos[[#This Row],[Tarefas Concluídas]],_xlfn.MAXIFS(TAREFAS!H:H,TAREFAS!B:B,Base_Projetos[[#This Row],[Projeto]]),IF(Base_Projetos[[#This Row],[Total de tarefas]]=Base_Projetos[[#This Row],[Tarefas não iniciadas]],"Não iniciado","Em andamento")) -> 45678 | M78: =SUM(Base_Projetos[[#This Row],[Tarefas Concluídas]:[Tarefas não iniciadas]]) -> 2 | N78: =COUNTIFS(tbl_PlanilhaB[Projeto],Base_Projetos[[#This Row],[Projeto]],tbl_PlanilhaB[Status],"Concluído") -> 2 | O78: =COUNTIFS(tbl_PlanilhaB[Projeto],Base_Projetos[[#This Row],[Projeto]],tbl_PlanilhaB[Status],"Em andamento") -> 0 | P78: =COUNTIFS(tbl_PlanilhaB[Projeto],Base_Projetos[[#This Row],[Projeto]],tbl_PlanilhaB[Status],"Atrasado") -> 0 | Q78: =COUNTIFS(tbl_PlanilhaB[Projeto],Base_Projetos[[#This Row],[Projeto]],tbl_PlanilhaB[Status],"Não iniciado") -> 0 | R78: =IF(Base_Projetos[[#This Row],[Total de tarefas]]=Base_Projetos[[#This Row],[Tarefas Concluídas]],"Concluído",IF(Base_Projetos[[#This Row],[Tarefas não iniciadas]]=Base_Projetos[[#This Row],[Total de tarefas]],"Não iniciado",IF(Base_Projetos[[#This Row],[Tarefas atrasadas]]>0,"Atrasado","Em andamento"))) -> Concluído | S78: =Base_Projetos[[#This Row],[Tarefas Concluídas]]/Base_Projetos[[#This Row],[Total de tarefas]] -> 1
A79: =A78+1 -> 75 | B79: layout conteiner 20 pés plantadora de toletes | C79: Projetar layout | D79: 3- Alta | E79: Fagner | F79: 1 | G79: =SUMIF(tbl_PlanilhaB[Projeto],Base_Projetos[[#This Row],[Projeto]],tbl_PlanilhaB[Valor previsto]) -> 0 | H79: =SUMIF(tbl_PlanilhaB[Projeto],Base_Projetos[[#This Row],[Projeto]],tbl_PlanilhaB[Valor gasto]) -> 0 | I79: =_xlfn.MINIFS(TAREFAS!E:E,TAREFAS!B:B,Base_Projetos[[#This Row],[Projeto]]) -> 45677 | J79: =_xlfn.MAXIFS(TAREFAS!G:G,TAREFAS!B:B,Base_Projetos[[#This Row],[Projeto]]) -> 45681 | K79: =IF(Base_Projetos[[#This Row],[Total de tarefas]]=Base_Projetos[[#This Row],[Tarefas não iniciadas]],"Não iniciado",_xlfn.MINIFS(TAREFAS!H:H,TAREFAS!B:B,Base_Projetos[[#This Row],[Projeto]])) -> 45677 | L79: =IF(Base_Projetos[[#This Row],[Total de tarefas]]=Base_Projetos[[#This Row],[Tarefas Concluídas]],_xlfn.MAXIFS(TAREFAS!H:H,TAREFAS!B:B,Base_Projetos[[#This Row],[Projeto]]),IF(Base_Projetos[[#This Row],[Total de tarefas]]=Base_Projetos[[#This Row],[Tarefas não iniciadas]],"Não iniciado","Em andamento")) -> 45678 | M79: =SUM(Base_Projetos[[#This Row],[Tarefas Concluídas]:[Tarefas não iniciadas]]) -> 2 | N79: =COUNTIFS(tbl_PlanilhaB[Projeto],Base_Projetos[[#This Row],[Projeto]],tbl_PlanilhaB[Status],"Concluído") -> 2 | O79: =COUNTIFS(tbl_PlanilhaB[Projeto],Base_Projetos[[#This Row],[Projeto]],tbl_PlanilhaB[Status],"Em andamento") -> 0 | P79: =COUNTIFS(tbl_PlanilhaB[Projeto],Base_Projetos[[#This Row],[Projeto]],tbl_PlanilhaB[Status],"Atrasado") -> 0 | Q79: =COUNTIFS(tbl_PlanilhaB[Projeto],Base_Projetos[[#This Row],[Projeto]],tbl_PlanilhaB[Status],"Não iniciado") -> 0 | R79: =IF(Base_Projetos[[#This Row],[Total de tarefas]]=Base_Projetos[[#This Row],[Tarefas Concluídas]],"Concluído",IF(Base_Projetos[[#This Row],[Tarefas não iniciadas]]=Base_Projetos[[#This Row],[Total de tarefas]],"Não iniciado",IF(Base_Projetos[[#This Row],[Tarefas atrasadas]]>0,"Atrasado","Em andamento"))) -> Concluído | S79: =Base_Projetos[[#This Row],[Tarefas Concluídas]]/Base_Projetos[[#This Row],[Total de tarefas]] -> 1
A80: =A79+1 -> 76 | B80: Dispositivo de fixação de barra para posicionamento da caixa de descarga do gbx 16000 (solicitado pelo rudi) | C80: Desenvolver conceito e o projeto | D80: 3- Alta | E80: Fagner | F80: 1 | G80: =SUMIF(tbl_PlanilhaB[Projeto],Base_Projetos[[#This Row],[Projeto]],tbl_PlanilhaB[Valor previsto]) -> 0 | H80: =SUMIF(tbl_PlanilhaB[Projeto],Base_Projetos[[#This Row],[Projeto]],tbl_PlanilhaB[Valor gasto]) -> 0 | I80: =_xlfn.MINIFS(TAREFAS!E:E,TAREFAS!B:B,Base_Projetos[[#This Row],[Projeto]]) -> 45678 | J80: =_xlfn.MAXIFS(TAREFAS!G:G,TAREFAS!B:B,Base_Projetos[[#This Row],[Projeto]]) -> 45692 | K80: =IF(Base_Projetos[[#This Row],[Total de tarefas]]=Base_Projetos[[#This Row],[Tarefas não iniciadas]],"Não iniciado",_xlfn.MINIFS(TAREFAS!H:H,TAREFAS!B:B,Base_Projetos[[#This Row],[Projeto]])) -> 45660 | L80: =IF(Base_Projetos[[#This Row],[Total de tarefas]]=Base_Projetos[[#This Row],[Tarefas Concluídas]],_xlfn.MAXIFS(TAREFAS!H:H,TAREFAS!B:B,Base_Projetos[[#This Row],[Projeto]]),IF(Base_Projetos[[#This Row],[Total de tarefas]]=Base_Projetos[[#This Row],[Tarefas não iniciadas]],"Não iniciado","Em andamento")) -> 45678 | M80: =SUM(Base_Projetos[[#This Row],[Tarefas Concluídas]:[Tarefas não iniciadas]]) -> 2 | N80: =COUNTIFS(tbl_PlanilhaB[Projeto],Base_Projetos[[#This Row],[Projeto]],tbl_PlanilhaB[Status],"Concluído") -> 2 | O80: =COUNTIFS(tbl_PlanilhaB[Projeto],Base_Projetos[[#This Row],[Projeto]],tbl_PlanilhaB[Status],"Em andamento") -> 0 | P80: =COUNTIFS(tbl_PlanilhaB[Projeto],Base_Projetos[[#This Row],[Projeto]],tbl_PlanilhaB[Status],"Atrasado") -> 0 | Q80: =COUNTIFS(tbl_PlanilhaB[Projeto],Base_Projetos[[#This Row],[Projeto]],tbl_PlanilhaB[Status],"Não iniciado") -> 0 | R80: =IF(Base_Projetos[[#This Row],[Total de tarefas]]=Base_Projetos[[#This Row],[Tarefas Concluídas]],"Concluído",IF(Base_Projetos[[#This Row],[Tarefas não iniciadas]]=Base_Projetos[[#This Row],[Total de tarefas]],"Não iniciado",IF(Base_Projetos[[#This Row],[Tarefas atrasadas]]>0,"Atrasado","Em andamento"))) -> Concluído | S80: =Base_Projetos[[#This Row],[Tarefas Concluídas]]/Base_Projetos[[#This Row],[Total de tarefas]] -> 1
A81: =A80+1 -> 77 | B81: Dispositivo de fixação de barra para posicionamento da caixa de descarga do gbx 16000 (solicitado pelo rudi) | C81: Desenvolver conceito e o projeto | D81: 3- Alta | E81: Fagner | F81: 1 | G81: =SUMIF(tbl_PlanilhaB[Projeto],Base_Projetos[[#This Row],[Projeto]],tbl_PlanilhaB[Valor previsto]) -> 0 | H81: =SUMIF(tbl_PlanilhaB[Projeto],Base_Projetos[[#This Row],[Projeto]],tbl_PlanilhaB[Valor gasto]) -> 0 | I81: =_xlfn.MINIFS(TAREFAS!E:E,TAREFAS!B:B,Base_Projetos[[#This Row],[Projeto]]) -> 45678 | J81: =_xlfn.MAXIFS(TAREFAS!G:G,TAREFAS!B:B,Base_Projetos[[#This Row],[Projeto]]) -> 45692 | K81: =IF(Base_Projetos[[#This Row],[Total de tarefas]]=Base_Projetos[[#This Row],[Tarefas não iniciadas]],"Não iniciado",_xlfn.MINIFS(TAREFAS!H:H,TAREFAS!B:B,Base_Projetos[[#This Row],[Projeto]])) -> 45660 | L81: =IF(Base_Projetos[[#This Row],[Total de tarefas]]=Base_Projetos[[#This Row],[Tarefas Concluídas]],_xlfn.MAXIFS(TAREFAS!H:H,TAREFAS!B:B,Base_Projetos[[#This Row],[Projeto]]),IF(Base_Projetos[[#This Row],[Total de tarefas]]=Base_Projetos[[#This Row],[Tarefas não iniciadas]],"Não iniciado","Em andamento")) -> 45678 | M81: =SUM(Base_Projetos[[#This Row],[Tarefas Concluídas]:[Tarefas não iniciadas]]) -> 2 | N81: =COUNTIFS(tbl_PlanilhaB[Projeto],Base_Projetos[[#This Row],[Projeto]],tbl_PlanilhaB[Status],"Concluído") -> 2 | O81: =COUNTIFS(tbl_PlanilhaB[Projeto],Base_Projetos[[#This Row],[Projeto]],tbl_PlanilhaB[Status],"Em andamento") -> 0 | P81: =COUNTIFS(tbl_PlanilhaB[Projeto],Base_Projetos[[#This Row],[Projeto]],tbl_PlanilhaB[Status],"Atrasado") -> 0 | Q81: =COUNTIFS(tbl_PlanilhaB[Projeto],Base_Projetos[[#This Row],[Projeto]],tbl_PlanilhaB[Status],"Não iniciado") -> 0 | R81: =IF(Base_Projetos[[#This Row],[Total de tarefas]]=Base_Projetos[[#This Row],[Tarefas Concluídas]],"Concluído",IF(Base_Projetos[[#This Row],[Tarefas não iniciadas]]=Base_Projetos[[#This Row],[Total de tarefas]],"Não iniciado",IF(Base_Projetos[[#This Row],[Tarefas atrasadas]]>0,"Atrasado","Em andamento"))) -> Concluído | S81: =Base_Projetos[[#This Row],[Tarefas Concluídas]]/Base_Projetos[[#This Row],[Total de tarefas]] -> 1
A82: =A81+1 -> 78 | B82: Gabarito para estrutura do carro dianteiro da plaina robust 440 e 480 | C82: Projeto e detalhamento | D82: 3- Alta | E82: Fagner | F82: 1 | G82: =SUMIF(tbl_PlanilhaB[Projeto],Base_Projetos[[#This Row],[Projeto]],tbl_PlanilhaB[Valor previsto]) -> 0 | H82: =SUMIF(tbl_PlanilhaB[Projeto],Base_Projetos[[#This Row],[Projeto]],tbl_PlanilhaB[Valor gasto]) -> 0 | I82: =_xlfn.MINIFS(TAREFAS!E:E,TAREFAS!B:B,Base_Projetos[[#This Row],[Projeto]]) -> 45684 | J82: =_xlfn.MAXIFS(TAREFAS!G:G,TAREFAS!B:B,Base_Projetos[[#This Row],[Projeto]]) -> 45698 | K82: =IF(Base_Projetos[[#This Row],[Total de tarefas]]=Base_Projetos[[#This Row],[Tarefas não iniciadas]],"Não iniciado",_xlfn.MINIFS(TAREFAS!H:H,TAREFAS!B:B,Base_Projetos[[#This Row],[Projeto]])) -> 45684 | L82: =IF(Base_Projetos[[#This Row],[Total de tarefas]]=Base_Projetos[[#This Row],[Tarefas Concluídas]],_xlfn.MAXIFS(TAREFAS!H:H,TAREFAS!B:B,Base_Projetos[[#This Row],[Projeto]]),IF(Base_Projetos[[#This Row],[Total de tarefas]]=Base_Projetos[[#This Row],[Tarefas não iniciadas]],"Não iniciado","Em andamento")) -> 45684 | M82: =SUM(Base_Projetos[[#This Row],[Tarefas Concluídas]:[Tarefas não iniciadas]]) -> 1 | N82: =COUNTIFS(tbl_PlanilhaB[Projeto],Base_Projetos[[#This Row],[Projeto]],tbl_PlanilhaB[Status],"Concluído") -> 1 | O82: =COUNTIFS(tbl_PlanilhaB[Projeto],Base_Projetos[[#This Row],[Projeto]],tbl_PlanilhaB[Status],"Em andamento") -> 0 | P82: =COUNTIFS(tbl_PlanilhaB[Projeto],Base_Projetos[[#This Row],[Projeto]],tbl_PlanilhaB[Status],"Atrasado") -> 0 | Q82: =COUNTIFS(tbl_PlanilhaB[Projeto],Base_Projetos[[#This Row],[Projeto]],tbl_PlanilhaB[Status],"Não iniciado") -> 0 | R82: =IF(Base_Projetos[[#This Row],[Total de tarefas]]=Base_Projetos[[#This Row],[Tarefas Concluídas]],"Concluído",IF(Base_Projetos[[#This Row],[Tarefas não iniciadas]]=Base_Projetos[[#This Row],[Total de tarefas]],"Não iniciado",IF(Base_Projetos[[#This Row],[Tarefas atrasadas]]>0,"Atrasado","Em andamento"))) -> Concluído | S82: =Base_Projetos[[#This Row],[Tarefas Concluídas]]/Base_Projetos[[#This Row],[Total de tarefas]] -> 1
A83: =A82+1 -> 79 | B83: Dispositivo fixação para corte de tubo 80mm usinado | C83: Desenvolver conceito e o projeto | D83: 3- Alta | E83: Fagner | F83: 1 | G83: =SUMIF(tbl_PlanilhaB[Projeto],Base_Projetos[[#This Row],[Projeto]],tbl_PlanilhaB[Valor previsto]) -> 0 | H83: =SUMIF(tbl_PlanilhaB[Projeto],Base_Projetos[[#This Row],[Projeto]],tbl_PlanilhaB[Valor gasto]) -> 0 | I83: =_xlfn.MINIFS(TAREFAS!E:E,TAREFAS!B:B,Base_Projetos[[#This Row],[Projeto]]) -> 45691 | J83: =_xlfn.MAXIFS(TAREFAS!G:G,TAREFAS!B:B,Base_Projetos[[#This Row],[Projeto]]) -> 45692 | K83: =IF(Base_Projetos[[#This Row],[Total de tarefas]]=Base_Projetos[[#This Row],[Tarefas não iniciadas]],"Não iniciado",_xlfn.MINIFS(TAREFAS!H:H,TAREFAS!B:B,Base_Projetos[[#This Row],[Projeto]])) -> 45691 | L83: =IF(Base_Projetos[[#This Row],[Total de tarefas]]=Base_Projetos[[#This Row],[Tarefas Concluídas]],_xlfn.MAXIFS(TAREFAS!H:H,TAREFAS!B:B,Base_Projetos[[#This Row],[Projeto]]),IF(Base_Projetos[[#This Row],[Total de tarefas]]=Base_Projetos[[#This Row],[Tarefas não iniciadas]],"Não iniciado","Em andamento")) -> 45691 | M83: =SUM(Base_Projetos[[#This Row],[Tarefas Concluídas]:[Tarefas não iniciadas]]) -> 1 | N83: =COUNTIFS(tbl_PlanilhaB[Projeto],Base_Projetos[[#This Row],[Projeto]],tbl_PlanilhaB[Status],"Concluído") -> 1 | O83: =COUNTIFS(tbl_PlanilhaB[Projeto],Base_Projetos[[#This Row],[Projeto]],tbl_PlanilhaB[Status],"Em andamento") -> 0 | P83: =COUNTIFS(tbl_PlanilhaB[Projeto],Base_Projetos[[#This Row],[Projeto]],tbl_PlanilhaB[Status],"Atrasado") -> 0 | Q83: =COUNTIFS(tbl_PlanilhaB[Projeto],Base_Projetos[[#This Row],[Projeto]],tbl_PlanilhaB[Status],"Não iniciado") -> 0 | R83: =IF(Base_Projetos[[#This Row],[Total de tarefas]]=Base_Projetos[[#This Row],[Tarefas Concluídas]],"Concluído",IF(Base_Projetos[[#This Row],[Tarefas não iniciadas]]=Base_Projetos[[#This Row],[Total de tarefas]],"Não iniciado",IF(Base_Projetos[[#This Row],[Tarefas atrasadas]]>0,"Atrasado","Em andamento"))) -> Concluído | S83: =Base_Projetos[[#This Row],[Tarefas Concluídas]]/Base_Projetos[[#This Row],[Total de tarefas]] -> 1
A84: =A83+1 -> 80 | B84: Dispositivo para recorte em tubo PVC | C84: Desenvolver conceito e o projeto | D84: 3- Alta | E84: Fagner | F84: 1 | G84: =SUMIF(tbl_PlanilhaB[Projeto],Base_Projetos[[#This Row],[Projeto]],tbl_PlanilhaB[Valor previsto]) -> 0 | H84: =SUMIF(tbl_PlanilhaB[Projeto],Base_Projetos[[#This Row],[Projeto]],tbl_PlanilhaB[Valor gasto]) -> 0 | I84: =_xlfn.MINIFS(TAREFAS!E:E,TAREFAS!B:B,Base_Projetos[[#This Row],[Projeto]]) -> 45691 | J84: =_xlfn.MAXIFS(TAREFAS!G:G,TAREFAS!B:B,Base_Projetos[[#This Row],[Projeto]]) -> 45692 | K84: =IF(Base_Projetos[[#This Row],[Total de tarefas]]=Base_Projetos[[#This Row],[Tarefas não iniciadas]],"Não iniciado",_xlfn.MINIFS(TAREFAS!H:H,TAREFAS!B:B,Base_Projetos[[#This Row],[Projeto]])) -> 45691 | L84: =IF(Base_Projetos[[#This Row],[Total de tarefas]]=Base_Projetos[[#This Row],[Tarefas Concluídas]],_xlfn.MAXIFS(TAREFAS!H:H,TAREFAS!B:B,Base_Projetos[[#This Row],[Projeto]]),IF(Base_Projetos[[#This Row],[Total de tarefas]]=Base_Projetos[[#This Row],[Tarefas não iniciadas]],"Não iniciado","Em andamento")) -> 45691 | M84: =SUM(Base_Projetos[[#This Row],[Tarefas Concluídas]:[Tarefas não iniciadas]]) -> 1 | N84: =COUNTIFS(tbl_PlanilhaB[Projeto],Base_Projetos[[#This Row],[Projeto]],tbl_PlanilhaB[Status],"Concluído") -> 1 | O84: =COUNTIFS(tbl_PlanilhaB[Projeto],Base_Projetos[[#This Row],[Projeto]],tbl_PlanilhaB[Status],"Em andamento") -> 0 | P84: =COUNTIFS(tbl_PlanilhaB[Projeto],Base_Projetos[[#This Row],[Projeto]],tbl_PlanilhaB[Status],"Atrasado") -> 0 | Q84: =COUNTIFS(tbl_PlanilhaB[Projeto],Base_Projetos[[#This Row],[Projeto]],tbl_PlanilhaB[Status],"Não iniciado") -> 0 | R84: =IF(Base_Projetos[[#This Row],[Total de tarefas]]=Base_Projetos[[#This Row],[Tarefas Concluídas]],"Concluído",IF(Base_Projetos[[#This Row],[Tarefas não iniciadas]]=Base_Projetos[[#This Row],[Total de tarefas]],"Não iniciado",IF(Base_Projetos[[#This Row],[Tarefas atrasadas]]>0,"Atrasado","Em andamento"))) -> Concluído | S84: =Base_Projetos[[#This Row],[Tarefas Concluídas]]/Base_Projetos[[#This Row],[Total de tarefas]] -> 1
A85: =A84+1 -> 81 | B85: Dispositivo de fixação de barra para posicionamento da caixa de descarga do gbx 25000 (solicitado pelo rudi) | C85: Desenvolver conceito e o projeto | D85: 3- Alta | E85: Fagner | F85: 1 | G85: =SUMIF(tbl_PlanilhaB[Projeto],Base_Projetos[[#This Row],[Projeto]],tbl_PlanilhaB[Valor previsto]) -> 0 | H85: =SUMIF(tbl_PlanilhaB[Projeto],Base_Projetos[[#This Row],[Projeto]],tbl_PlanilhaB[Valor gasto]) -> 0 | I85: =_xlfn.MINIFS(TAREFAS!E:E,TAREFAS!B:B,Base_Projetos[[#This Row],[Projeto]]) -> 45691 | J85: =_xlfn.MAXIFS(TAREFAS!G:G,TAREFAS!B:B,Base_Projetos[[#This Row],[Projeto]]) -> 45692 | K85: =IF(Base_Projetos[[#This Row],[Total de tarefas]]=Base_Projetos[[#This Row],[Tarefas não iniciadas]],"Não iniciado",_xlfn.MINIFS(TAREFAS!H:H,TAREFAS!B:B,Base_Projetos[[#This Row],[Projeto]])) -> 45691 | L85: =IF(Base_Projetos[[#This Row],[Total de tarefas]]=Base_Projetos[[#This Row],[Tarefas Concluídas]],_xlfn.MAXIFS(TAREFAS!H:H,TAREFAS!B:B,Base_Projetos[[#This Row],[Projeto]]),IF(Base_Projetos[[#This Row],[Total de tarefas]]=Base_Projetos[[#This Row],[Tarefas não iniciadas]],"Não iniciado","Em andamento")) -> 45691 | M85: =SUM(Base_Projetos[[#This Row],[Tarefas Concluídas]:[Tarefas não iniciadas]]) -> 1 | N85: =COUNTIFS(tbl_PlanilhaB[Projeto],Base_Projetos[[#This Row],[Projeto]],tbl_PlanilhaB[Status],"Concluído") -> 1 | O85: =COUNTIFS(tbl_PlanilhaB[Projeto],Base_Projetos[[#This Row],[Projeto]],tbl_PlanilhaB[Status],"Em andamento") -> 0 | P85: =COUNTIFS(tbl_PlanilhaB[Projeto],Base_Projetos[[#This Row],[Projeto]],tbl_PlanilhaB[Status],"Atrasado") -> 0 | Q85: =COUNTIFS(tbl_PlanilhaB[Projeto],Base_Projetos[[#This Row],[Projeto]],tbl_PlanilhaB[Status],"Não iniciado") -> 0 | R85: =IF(Base_Projetos[[#This Row],[Total de tarefas]]=Base_Projetos[[#This Row],[Tarefas Concluídas]],"Concluído",IF(Base_Projetos[[#This Row],[Tarefas não iniciadas]]=Base_Projetos[[#This Row],[Total de tarefas]],"Não iniciado",IF(Base_Projetos[[#This Row],[Tarefas atrasadas]]>0,"Atrasado","Em andamento"))) -> Concluído | S85: =Base_Projetos[[#This Row],[Tarefas Concluídas]]/Base_Projetos[[#This Row],[Total de tarefas]] -> 1
A86: =A85+1 -> 82 | B86: Mudança de Layout Polo | C86: Elaborar proposta de novo layout para Polo | D86: 3- Alta | E86: João Calheiros | F86: 1 | G86: =SUMIF(tbl_PlanilhaB[Projeto],Base_Projetos[[#This Row],[Projeto]],tbl_PlanilhaB[Valor previsto]) -> 0 | H86: =SUMIF(tbl_PlanilhaB[Projeto],Base_Projetos[[#This Row],[Projeto]],tbl_PlanilhaB[Valor gasto]) -> 0 | I86: =_xlfn.MINIFS(TAREFAS!E:E,TAREFAS!B:B,Base_Projetos[[#This Row],[Projeto]]) -> 45677 | J86: =_xlfn.MAXIFS(TAREFAS!G:G,TAREFAS!B:B,Base_Projetos[[#This Row],[Projeto]]) -> 45686 | K86: =IF(Base_Projetos[[#This Row],[Total de tarefas]]=Base_Projetos[[#This Row],[Tarefas não iniciadas]],"Não iniciado",_xlfn.MINIFS(TAREFAS!H:H,TAREFAS!B:B,Base_Projetos[[#This Row],[Projeto]])) -> 45679 | L86: =IF(Base_Projetos[[#This Row],[Total de tarefas]]=Base_Projetos[[#This Row],[Tarefas Concluídas]],_xlfn.MAXIFS(TAREFAS!H:H,TAREFAS!B:B,Base_Projetos[[#This Row],[Projeto]]),IF(Base_Projetos[[#This Row],[Total de tarefas]]=Base_Projetos[[#This Row],[Tarefas não iniciadas]],"Não iniciado","Em andamento")) -> 45679 | M86: =SUM(Base_Projetos[[#This Row],[Tarefas Concluídas]:[Tarefas não iniciadas]]) -> 1 | N86: =COUNTIFS(tbl_PlanilhaB[Projeto],Base_Projetos[[#This Row],[Projeto]],tbl_PlanilhaB[Status],"Concluído") -> 1 | O86: =COUNTIFS(tbl_PlanilhaB[Projeto],Base_Projetos[[#This Row],[Projeto]],tbl_PlanilhaB[Status],"Em andamento") -> 0 | P86: =COUNTIFS(tbl_PlanilhaB[Projeto],Base_Projetos[[#This Row],[Projeto]],tbl_PlanilhaB[Status],"Atrasado") -> 0 | Q86: =COUNTIFS(tbl_PlanilhaB[Projeto],Base_Projetos[[#This Row],[Projeto]],tbl_PlanilhaB[Status],"Não iniciado") -> 0 | R86: =IF(Base_Projetos[[#This Row],[Total de tarefas]]=Base_Projetos[[#This Row],[Tarefas Concluídas]],"Concluído",IF(Base_Projetos[[#This Row],[Tarefas não iniciadas]]=Base_Projetos[[#This Row],[Total de tarefas]],"Não iniciado",IF(Base_Projetos[[#This Row],[Tarefas atrasadas]]>0,"Atrasado","Em andamento"))) -> Concluído | S86: =Base_Projetos[[#This Row],[Tarefas Concluídas]]/Base_Projetos[[#This Row],[Total de tarefas]] -> 1
A87: =A86+1 -> 83 | B87: Simulação de carga. quantidades de máquinas: Conteiner 40 pés: NSA 10, TA 10H, RFA 1360H; Conteiner 20 pés: VA 40L, BCI 200, BCI 300, ROTOCARP 2L | C87: Simular a maior quantidade possível de carga que possa caber dentro do contêiner. | D87: 3- Alta | E87: Fagner | F87: 1 | G87: =SUMIF(tbl_PlanilhaB[Projeto],Base_Projetos[[#This Row],[Projeto]],tbl_PlanilhaB[Valor previsto]) -> 0 | H87: =SUMIF(tbl_PlanilhaB[Projeto],Base_Projetos[[#This Row],[Projeto]],tbl_PlanilhaB[Valor gasto]) -> 0 | I87: =_xlfn.MINIFS(TAREFAS!E:E,TAREFAS!B:B,Base_Projetos[[#This Row],[Projeto]]) -> 45693 | J87: =_xlfn.MAXIFS(TAREFAS!G:G,TAREFAS!B:B,Base_Projetos[[#This Row],[Projeto]]) -> 45701 | K87: =IF(Base_Projetos[[#This Row],[Total de tarefas]]=Base_Projetos[[#This Row],[Tarefas não iniciadas]],"Não iniciado",_xlfn.MINIFS(TAREFAS!H:H,TAREFAS!B:B,Base_Projetos[[#This Row],[Projeto]])) -> 45693 | L87: =IF(Base_Projetos[[#This Row],[Total de tarefas]]=Base_Projetos[[#This Row],[Tarefas Concluídas]],_xlfn.MAXIFS(TAREFAS!H:H,TAREFAS!B:B,Base_Projetos[[#This Row],[Projeto]]),IF(Base_Projetos[[#This Row],[Total de tarefas]]=Base_Projetos[[#This Row],[Tarefas não iniciadas]],"Não iniciado","Em andamento")) -> 45700 | M87: =SUM(Base_Projetos[[#This Row],[Tarefas Concluídas]:[Tarefas não iniciadas]]) -> 8 | N87: =COUNTIFS(tbl_PlanilhaB[Projeto],Base_Projetos[[#This Row],[Projeto]],tbl_PlanilhaB[Status],"Concluído") -> 8 | O87: =COUNTIFS(tbl_PlanilhaB[Projeto],Base_Projetos[[#This Row],[Projeto]],tbl_PlanilhaB[Status],"Em andamento") -> 0 | P87: =COUNTIFS(tbl_PlanilhaB[Projeto],Base_Projetos[[#This Row],[Projeto]],tbl_PlanilhaB[Status],"Atrasado") -> 0 | Q87: =COUNTIFS(tbl_PlanilhaB[Projeto],Base_Projetos[[#This Row],[Projeto]],tbl_PlanilhaB[Status],"Não iniciado") -> 0 | R87: =IF(Base_Projetos[[#This Row],[Total de tarefas]]=Base_Projetos[[#This Row],[Tarefas Concluídas]],"Concluído",IF(Base_Projetos[[#This Row],[Tarefas não iniciadas]]=Base_Projetos[[#This Row],[Total de tarefas]],"Não iniciado",IF(Base_Projetos[[#This Row],[Tarefas atrasadas]]>0,"Atrasado","Em andamento"))) -> Concluído | S87: =Base_Projetos[[#This Row],[Tarefas Concluídas]]/Base_Projetos[[#This Row],[Total de tarefas]] -> 1
A88: =A87+1 -> 84 | B88: Norma de qualidade para engenharia: Determinação de tolerâncias para processos de corte e conformação mecânica | C88: Desenvolver documento padronizando as tolerâncias e fatores K utilizados nos processos de conformação mecânica e corte | D88: 2- Média | E88: Laureane | F88: 1 | G88: =SUMIF(tbl_PlanilhaB[Projeto],Base_Projetos[[#This Row],[Projeto]],tbl_PlanilhaB[Valor previsto]) -> 0 | H88: =SUMIF(tbl_PlanilhaB[Projeto],Base_Projetos[[#This Row],[Projeto]],tbl_PlanilhaB[Valor gasto]) -> 0 | I88: =_xlfn.MINIFS(TAREFAS!E:E,TAREFAS!B:B,Base_Projetos[[#This Row],[Projeto]]) -> 45685 | J88: =_xlfn.MAXIFS(TAREFAS!G:G,TAREFAS!B:B,Base_Projetos[[#This Row],[Projeto]]) -> 45688 | K88: =IF(Base_Projetos[[#This Row],[Total de tarefas]]=Base_Projetos[[#This Row],[Tarefas não iniciadas]],"Não iniciado",_xlfn.MINIFS(TAREFAS!H:H,TAREFAS!B:B,Base_Projetos[[#This Row],[Projeto]])) -> 45685 | L88: =IF(Base_Projetos[[#This Row],[Total de tarefas]]=Base_Projetos[[#This Row],[Tarefas Concluídas]],_xlfn.MAXIFS(TAREFAS!H:H,TAREFAS!B:B,Base_Projetos[[#This Row],[Projeto]]),IF(Base_Projetos[[#This Row],[Total de tarefas]]=Base_Projetos[[#This Row],[Tarefas não iniciadas]],"Não iniciado","Em andamento")) -> 45687 | M88: =SUM(Base_Projetos[[#This Row],[Tarefas Concluídas]:[Tarefas não iniciadas]]) -> 2 | N88: =COUNTIFS(tbl_PlanilhaB[Projeto],Base_Projetos[[#This Row],[Projeto]],tbl_PlanilhaB[Status],"Concluído") -> 2 | O88: =COUNTIFS(tbl_PlanilhaB[Projeto],Base_Projetos[[#This Row],[Projeto]],tbl_PlanilhaB[Status],"Em andamento") -> 0 | P88: =COUNTIFS(tbl_PlanilhaB[Projeto],Base_Projetos[[#This Row],[Projeto]],tbl_PlanilhaB[Status],"Atrasado") -> 0 | Q88: =COUNTIFS(tbl_PlanilhaB[Projeto],Base_Projetos[[#This Row],[Projeto]],tbl_PlanilhaB[Status],"Não iniciado") -> 0 | R88: =IF(Base_Projetos[[#This Row],[Total de tarefas]]=Base_Projetos[[#This Row],[Tarefas Concluídas]],"Concluído",IF(Base_Projetos[[#This Row],[Tarefas não iniciadas]]=Base_Projetos[[#This Row],[Total de tarefas]],"Não iniciado",IF(Base_Projetos[[#This Row],[Tarefas atrasadas]]>0,"Atrasado","Em andamento"))) -> Concluído | S88: =Base_Projetos[[#This Row],[Tarefas Concluídas]]/Base_Projetos[[#This Row],[Total de tarefas]] -> 1
... A129: =A128+1 -> 125 | B129: Atualização Custeio Geral TECNICON 2025 | C129: Estudo para atualização dos custos de mão de obra e máquina no TECNICON | D129: 3- Alta | E129: João Paulo Bubicz | F129: 1 | G129: =SUMIF(tbl_PlanilhaB[Projeto],Base_Projetos[[#This Row],[Projeto]],tbl_PlanilhaB[Valor previsto]) -> 0 | H129: =SUMIF(tbl_PlanilhaB[Projeto],Base_Projetos[[#This Row],[Projeto]],tbl_PlanilhaB[Valor gasto]) -> 0 | I129: =_xlfn.MINIFS(TAREFAS!E:E,TAREFAS!B:B,Base_Projetos[[#This Row],[Projeto]]) -> 45838 | J129: =_xlfn.MAXIFS(TAREFAS!G:G,TAREFAS!B:B,Base_Projetos[[#This Row],[Projeto]]) -> 45845 | K129: =IF(Base_Projetos[[#This Row],[Total de tarefas]]=Base_Projetos[[#This Row],[Tarefas não iniciadas]],"Não iniciado",_xlfn.MINIFS(TAREFAS!H:H,TAREFAS!B:B,Base_Projetos[[#This Row],[Projeto]])) -> 45838 | L129: =IF(Base_Projetos[[#This Row],[Total de tarefas]]=Base_Projetos[[#This Row],[Tarefas Concluídas]],_xlfn.MAXIFS(TAREFAS!H:H,TAREFAS!B:B,Base_Projetos[[#This Row],[Projeto]]),IF(Base_Projetos[[#This Row],[Total de tarefas]]=Base_Projetos[[#This Row],[Tarefas não iniciadas]],"Não iniciado","Em andamento")) -> 45838 | M129: =SUM(Base_Projetos[[#This Row],[Tarefas Concluídas]:[Tarefas não iniciadas]]) -> 1 | N129: =COUNTIFS(tbl_PlanilhaB[Projeto],Base_Projetos[[#This Row],[Projeto]],tbl_PlanilhaB[Status],"Concluído") -> 1 | O129: =COUNTIFS(tbl_PlanilhaB[Projeto],Base_Projetos[[#This Row],[Projeto]],tbl_PlanilhaB[Status],"Em andamento") -> 0 | P129: =COUNTIFS(tbl_PlanilhaB[Projeto],Base_Projetos[[#This Row],[Projeto]],tbl_PlanilhaB[Status],"Atrasado") -> 0 | Q129: =COUNTIFS(tbl_PlanilhaB[Projeto],Base_Projetos[[#This Row],[Projeto]],tbl_PlanilhaB[Status],"Não iniciado") -> 0 | R129: =IF(Base_Projetos[[#This Row],[Total de tarefas]]=Base_Projetos[[#This Row],[Tarefas Concluídas]],"Concluído",IF(Base_Projetos[[#This Row],[Tarefas não iniciadas]]=Base_Projetos[[#This Row],[Total de tarefas]],"Não iniciado",IF(Base_Projetos[[#This Row],[Tarefas atrasadas]]>0,"Atrasado","Em andamento"))) -> Concluído | S129: =Base_Projetos[[#This Row],[Tarefas Concluídas]]/Base_Projetos[[#This Row],[Total de tarefas]] -> 1
A130: =A129+1 -> 126 | B130: Bancada p/rotores BCI conjunto com ponteiras AC | C130: Dispositivo para verificação de empenamento em rotores BCI, utilizando relógio comparador." | D130: 3- Alta | E130: William Rosa | G130: =SUMIF(tbl_PlanilhaB[Projeto],Base_Projetos[[#This Row],[Projeto]],tbl_PlanilhaB[Valor previsto]) -> 0 | H130: =SUMIF(tbl_PlanilhaB[Projeto],Base_Projetos[[#This Row],[Projeto]],tbl_PlanilhaB[Valor gasto]) -> 0 | I130: =_xlfn.MINIFS(TAREFAS!E:E,TAREFAS!B:B,Base_Projetos[[#This Row],[Projeto]]) -> 45833 | J130: =_xlfn.MAXIFS(TAREFAS!G:G,TAREFAS!B:B,Base_Projetos[[#This Row],[Projeto]]) -> 45841 | K130: =IF(Base_Projetos[[#This Row],[Total de tarefas]]=Base_Projetos[[#This Row],[Tarefas não iniciadas]],"Não iniciado",_xlfn.MINIFS(TAREFAS!H:H,TAREFAS!B:B,Base_Projetos[[#This Row],[Projeto]])) -> 45833 | L130: =IF(Base_Projetos[[#This Row],[Total de tarefas]]=Base_Projetos[[#This Row],[Tarefas Concluídas]],_xlfn.MAXIFS(TAREFAS!H:H,TAREFAS!B:B,Base_Projetos[[#This Row],[Projeto]]),IF(Base_Projetos[[#This Row],[Total de tarefas]]=Base_Projetos[[#This Row],[Tarefas não iniciadas]],"Não iniciado","Em andamento")) -> 45841 | M130: =SUM(Base_Projetos[[#This Row],[Tarefas Concluídas]:[Tarefas não iniciadas]]) -> 4 | N130: =COUNTIFS(tbl_PlanilhaB[Projeto],Base_Projetos[[#This Row],[Projeto]],tbl_PlanilhaB[Status],"Concluído") -> 4 | O130: =COUNTIFS(tbl_PlanilhaB[Projeto],Base_Projetos[[#This Row],[Projeto]],tbl_PlanilhaB[Status],"Em andamento") -> 0 | P130: =COUNTIFS(tbl_PlanilhaB[Projeto],Base_Projetos[[#This Row],[Projeto]],tbl_PlanilhaB[Status],"Atrasado") -> 0 | Q130: =COUNTIFS(tbl_PlanilhaB[Projeto],Base_Projetos[[#This Row],[Projeto]],tbl_PlanilhaB[Status],"Não iniciado") -> 0 | R130: =IF(Base_Projetos[[#This Row],[Total de tarefas]]=Base_Projetos[[#This Row],[Tarefas Concluídas]],"Concluído",IF(Base_Projetos[[#This Row],[Tarefas não iniciadas]]=Base_Projetos[[#This Row],[Total de tarefas]],"Não iniciado",IF(Base_Projetos[[#This Row],[Tarefas atrasadas]]>0,"Atrasado","Em andamento"))) -> Concluído | S130: =Base_Projetos[[#This Row],[Tarefas Concluídas]]/Base_Projetos[[#This Row],[Total de tarefas]] -> 1
A131: =A130+1 -> 127 | B131: Simulação carga exportação Republica Dominicana | C131: Simulação de carga de 5 TA10 e 1 PNA 48 no contêiner, criação dos suportes de fixação, definição do layout dos equipamentos com os suportes e elaboração da documentação de carga e descarga individual e geral do conjunto no contêiner. | D131: 3- Alta | E131: Fagner | F131: 1 | G131: =SUMIF(tbl_PlanilhaB[Projeto],Base_Projetos[[#This Row],[Projeto]],tbl_PlanilhaB[Valor previsto]) -> 0 | H131: =SUMIF(tbl_PlanilhaB[Projeto],Base_Projetos[[#This Row],[Projeto]],tbl_PlanilhaB[Valor gasto]) -> 0 | I131: =_xlfn.MINIFS(TAREFAS!E:E,TAREFAS!B:B,Base_Projetos[[#This Row],[Projeto]]) -> 45821 | J131: =_xlfn.MAXIFS(TAREFAS!G:G,TAREFAS!B:B,Base_Projetos[[#This Row],[Projeto]]) -> 45846 | K131: =IF(Base_Projetos[[#This Row],[Total de tarefas]]=Base_Projetos[[#This Row],[Tarefas não iniciadas]],"Não iniciado",_xlfn.MINIFS(TAREFAS!H:H,TAREFAS!B:B,Base_Projetos[[#This Row],[Projeto]])) -> 45821 | L131: =IF(Base_Projetos[[#This Row],[Total de tarefas]]=Base_Projetos[[#This Row],[Tarefas Concluídas]],_xlfn.MAXIFS(TAREFAS!H:H,TAREFAS!B:B,Base_Projetos[[#This Row],[Projeto]]),IF(Base_Projetos[[#This Row],[Total de tarefas]]=Base_Projetos[[#This Row],[Tarefas não iniciadas]],"Não iniciado","Em andamento")) -> 45842 | M131: =SUM(Base_Projetos[[#This Row],[Tarefas Concluídas]:[Tarefas não iniciadas]]) -> 8 | N131: =COUNTIFS(tbl_PlanilhaB[Projeto],Base_Projetos[[#This Row],[Projeto]],tbl_PlanilhaB[Status],"Concluído") -> 8 | O131: =COUNTIFS(tbl_PlanilhaB[Projeto],Base_Projetos[[#This Row],[Projeto]],tbl_PlanilhaB[Status],"Em andamento") -> 0 | P131: =COUNTIFS(tbl_PlanilhaB[Projeto],Base_Projetos[[#This Row],[Projeto]],tbl_PlanilhaB[Status],"Atrasado") -> 0 | Q131: =COUNTIFS(tbl_PlanilhaB[Projeto],Base_Projetos[[#This Row],[Projeto]],tbl_PlanilhaB[Status],"Não iniciado") -> 0 | R131: =IF(Base_Projetos[[#This Row],[Total de tarefas]]=Base_Projetos[[#This Row],[Tarefas Concluídas]],"Concluído",IF(Base_Projetos[[#This Row],[Tarefas não iniciadas]]=Base_Projetos[[#This Row],[Total de tarefas]],"Não iniciado",IF(Base_Projetos[[#This Row],[Tarefas atrasadas]]>0,"Atrasado","Em andamento"))) -> Concluído | S131: =Base_Projetos[[#This Row],[Tarefas Concluídas]]/Base_Projetos[[#This Row],[Total de tarefas]] -> 1
A132: =A131+1 -> 128 | B132: Cj sdd gabarito 440 / 480 | C132: Revisão de projeto antigo com verificação de interferências e análise de possíveis ajustes em componentes. | D132: 3- Alta | E132: William Rosa | F132: 1 | G132: =SUMIF(tbl_PlanilhaB[Projeto],Base_Projetos[[#This Row],[Projeto]],tbl_PlanilhaB[Valor previsto]) -> 0 | H132: =SUMIF(tbl_PlanilhaB[Projeto],Base_Projetos[[#This Row],[Projeto]],tbl_PlanilhaB[Valor gasto]) -> 0 | I132: =_xlfn.MINIFS(TAREFAS!E:E,TAREFAS!B:B,Base_Projetos[[#This Row],[Projeto]]) -> 45842 | J132: =_xlfn.MAXIFS(TAREFAS!G:G,TAREFAS!B:B,Base_Projetos[[#This Row],[Projeto]]) -> 45845 | K132: =IF(Base_Projetos[[#This Row],[Total de tarefas]]=Base_Projetos[[#This Row],[Tarefas não iniciadas]],"Não iniciado",_xlfn.MINIFS(TAREFAS!H:H,TAREFAS!B:B,Base_Projetos[[#This Row],[Projeto]])) -> 45842 | L132: =IF(Base_Projetos[[#This Row],[Total de tarefas]]=Base_Projetos[[#This Row],[Tarefas Concluídas]],_xlfn.MAXIFS(TAREFAS!H:H,TAREFAS!B:B,Base_Projetos[[#This Row],[Projeto]]),IF(Base_Projetos[[#This Row],[Total de tarefas]]=Base_Projetos[[#This Row],[Tarefas não iniciadas]],"Não iniciado","Em andamento")) -> 45842 | M132: =SUM(Base_Projetos[[#This Row],[Tarefas Concluídas]:[Tarefas não iniciadas]]) -> 1 | N132: =COUNTIFS(tbl_PlanilhaB[Projeto],Base_Projetos[[#This Row],[Projeto]],tbl_PlanilhaB[Status],"Concluído") -> 1 | O132: =COUNTIFS(tbl_PlanilhaB[Projeto],Base_Projetos[[#This Row],[Projeto]],tbl_PlanilhaB[Status],"Em andamento") -> 0 | P132: =COUNTIFS(tbl_PlanilhaB[Projeto],Base_Projetos[[#This Row],[Projeto]],tbl_PlanilhaB[Status],"Atrasado") -> 0 | Q132: =COUNTIFS(tbl_PlanilhaB[Projeto],Base_Projetos[[#This Row],[Projeto]],tbl_PlanilhaB[Status],"Não iniciado") -> 0 | R132: =IF(Base_Projetos[[#This Row],[Total de tarefas]]=Base_Projetos[[#This Row],[Tarefas Concluídas]],"Concluído",IF(Base_Projetos[[#This Row],[Tarefas não iniciadas]]=Base_Projetos[[#This Row],[Total de tarefas]],"Não iniciado",IF(Base_Projetos[[#This Row],[Tarefas atrasadas]]>0,"Atrasado","Em andamento"))) -> Concluído | S132: =Base_Projetos[[#This Row],[Tarefas Concluídas]]/Base_Projetos[[#This Row],[Total de tarefas]] -> 1
A133: 129 | B133: Treinamento dos Inspetores de Soldagem | C133: Treinamento ministrado por equipe de engenharia de soldagem que aborda os principais tópicos necessários ao trabalho dos inspetores de soldagem envolvendo aspectos teóricos, práticos e normativos do processos de soldagem e da rotina de inspeção. | D133: 3- Alta | E133: João Calheiros | F133: 2 | G133: =SUMIF(tbl_PlanilhaB[Projeto],Base_Projetos[[#This Row],[Projeto]],tbl_PlanilhaB[Valor previsto]) -> 0 | H133: =SUMIF(tbl_PlanilhaB[Projeto],Base_Projetos[[#This Row],[Projeto]],tbl_PlanilhaB[Valor gasto]) -> 0 | I133: =_xlfn.MINIFS(TAREFAS!E:E,TAREFAS!B:B,Base_Projetos[[#This Row],[Projeto]]) -> 45832 | J133: =_xlfn.MAXIFS(TAREFAS!G:G,TAREFAS!B:B,Base_Projetos[[#This Row],[Projeto]]) -> 45887 | K133: =IF(Base_Projetos[[#This Row],[Total de tarefas]]=Base_Projetos[[#This Row],[Tarefas não iniciadas]],"Não iniciado",_xlfn.MINIFS(TAREFAS!H:H,TAREFAS!B:B,Base_Projetos[[#This Row],[Projeto]])) -> 45833 | L133: =IF(Base_Projetos[[#This Row],[Total de tarefas]]=Base_Projetos[[#This Row],[Tarefas Concluídas]],_xlfn.MAXIFS(TAREFAS!H:H,TAREFAS!B:B,Base_Projetos[[#This Row],[Projeto]]),IF(Base_Projetos[[#This Row],[Total de tarefas]]=Base_Projetos[[#This Row],[Tarefas não iniciadas]],"Não iniciado","Em andamento")) -> 45884 | M133: =SUM(Base_Projetos[[#This Row],[Tarefas Concluídas]:[Tarefas não iniciadas]]) -> 20 | N133: =COUNTIFS(tbl_PlanilhaB[Projeto],Base_Projetos[[#This Row],[Projeto]],tbl_PlanilhaB[Status],"Concluído") -> 20 | O133: =COUNTIFS(tbl_PlanilhaB[Projeto],Base_Projetos[[#This Row],[Projeto]],tbl_PlanilhaB[Status],"Em andamento") -> 0 | P133: =COUNTIFS(tbl_PlanilhaB[Projeto],Base_Projetos[[#This Row],[Projeto]],tbl_PlanilhaB[Status],"Atrasado") -> 0 | Q133: =COUNTIFS(tbl_PlanilhaB[Projeto],Base_Projetos[[#This Row],[Projeto]],tbl_PlanilhaB[Status],"Não iniciado") -> 0 | R133: =IF(Base_Projetos[[#This Row],[Total de tarefas]]=Base_Projetos[[#This Row],[Tarefas Concluídas]],"Concluído",IF(Base_Projetos[[#This Row],[Tarefas não iniciadas]]=Base_Projetos[[#This Row],[Total de tarefas]],"Não iniciado",IF(Base_Projetos[[#This Row],[Tarefas atrasadas]]>0,"Atrasado","Em andamento"))) -> Concluído | S133: =Base_Projetos[[#This Row],[Tarefas Concluídas]]/Base_Projetos[[#This Row],[Total de tarefas]] -> 1
A134: 130 | B134: Gabarito Chassi 440 e 480 | C134: Estudo e definição da posição ideal dos rodízios para garantir mobilidade e estabilidade dos gabaritos, além da bipartição estratégica visando facilitar transporte, armazenamento e montagem. | D134: 3- Alta | E134: William Rosa | F134: 1 | G134: =SUMIF(tbl_PlanilhaB[Projeto],Base_Projetos[[#This Row],[Projeto]],tbl_PlanilhaB[Valor previsto]) -> 0 | H134: =SUMIF(tbl_PlanilhaB[Projeto],Base_Projetos[[#This Row],[Projeto]],tbl_PlanilhaB[Valor gasto]) -> 0 | I134: =_xlfn.MINIFS(TAREFAS!E:E,TAREFAS!B:B,Base_Projetos[[#This Row],[Projeto]]) -> 45845 | J134: =_xlfn.MAXIFS(TAREFAS!G:G,TAREFAS!B:B,Base_Projetos[[#This Row],[Projeto]]) -> 45855 | K134: =IF(Base_Projetos[[#This Row],[Total de tarefas]]=Base_Projetos[[#This Row],[Tarefas não iniciadas]],"Não iniciado",_xlfn.MINIFS(TAREFAS!H:H,TAREFAS!B:B,Base_Projetos[[#This Row],[Projeto]])) -> 45845 | L134: =IF(Base_Projetos[[#This Row],[Total de tarefas]]=Base_Projetos[[#This Row],[Tarefas Concluídas]],_xlfn.MAXIFS(TAREFAS!H:H,TAREFAS!B:B,Base_Projetos[[#This Row],[Projeto]]),IF(Base_Projetos[[#This Row],[Total de tarefas]]=Base_Projetos[[#This Row],[Tarefas não iniciadas]],"Não iniciado","Em andamento")) -> 45852 | M134: =SUM(Base_Projetos[[#This Row],[Tarefas Concluídas]:[Tarefas não iniciadas]]) -> 4 | N134: =COUNTIFS(tbl_PlanilhaB[Projeto],Base_Projetos[[#This Row],[Projeto]],tbl_PlanilhaB[Status],"Concluído") -> 4 | O134: =COUNTIFS(tbl_PlanilhaB[Projeto],Base_Projetos[[#This Row],[Projeto]],tbl_PlanilhaB[Status],"Em andamento") -> 0 | P134: =COUNTIFS(tbl_PlanilhaB[Projeto],Base_Projetos[[#This Row],[Projeto]],tbl_PlanilhaB[Status],"Atrasado") -> 0 | Q134: =COUNTIFS(tbl_PlanilhaB[Projeto],Base_Projetos[[#This Row],[Projeto]],tbl_PlanilhaB[Status],"Não iniciado") -> 0 | R134: =IF(Base_Projetos[[#This Row],[Total de tarefas]]=Base_Projetos[[#This Row],[Tarefas Concluídas]],"Concluído",IF(Base_Projetos[[#This Row],[Tarefas não iniciadas]]=Base_Projetos[[#This Row],[Total de tarefas]],"Não iniciado",IF(Base_Projetos[[#This Row],[Tarefas atrasadas]]>0,"Atrasado","Em andamento"))) -> Concluído | S134: =Base_Projetos[[#This Row],[Tarefas Concluídas]]/Base_Projetos[[#This Row],[Total de tarefas]] -> 1
A135: =A134+1 -> 131 | B135: Gabarito Chassi NSA10 | C135: Instalaçõa dos rodizio | D135: 3- Alta | E135: William Rosa | F135: 1 | G135: 1 | H135: =SUMIF(tbl_PlanilhaB[Projeto],Base_Projetos[[#This Row],[Projeto]],tbl_PlanilhaB[Valor gasto]) -> 0 | I135: =_xlfn.MINIFS(TAREFAS!E:E,TAREFAS!B:B,Base_Projetos[[#This Row],[Projeto]]) -> 45855 | J135: =_xlfn.MAXIFS(TAREFAS!G:G,TAREFAS!B:B,Base_Projetos[[#This Row],[Projeto]]) -> 45856 | K135: =IF(Base_Projetos[[#This Row],[Total de tarefas]]=Base_Projetos[[#This Row],[Tarefas não iniciadas]],"Não iniciado",_xlfn.MINIFS(TAREFAS!H:H,TAREFAS!B:B,Base_Projetos[[#This Row],[Projeto]])) -> 45855 | L135: =IF(Base_Projetos[[#This Row],[Total de tarefas]]=Base_Projetos[[#This Row],[Tarefas Concluídas]],_xlfn.MAXIFS(TAREFAS!H:H,TAREFAS!B:B,Base_Projetos[[#This Row],[Projeto]]),IF(Base_Projetos[[#This Row],[Total de tarefas]]=Base_Projetos[[#This Row],[Tarefas não iniciadas]],"Não iniciado","Em andamento")) -> 45855 | M135: =SUM(Base_Projetos[[#This Row],[Tarefas Concluídas]:[Tarefas não iniciadas]]) -> 1 | N135: =COUNTIFS(tbl_PlanilhaB[Projeto],Base_Projetos[[#This Row],[Projeto]],tbl_PlanilhaB[Status],"Concluído") -> 1 | O135: =COUNTIFS(tbl_PlanilhaB[Projeto],Base_Projetos[[#This Row],[Projeto]],tbl_PlanilhaB[Status],"Em andamento") -> 0 | P135: =COUNTIFS(tbl_PlanilhaB[Projeto],Base_Projetos[[#This Row],[Projeto]],tbl_PlanilhaB[Status],"Atrasado") -> 0 | Q135: =COUNTIFS(tbl_PlanilhaB[Projeto],Base_Projetos[[#This Row],[Projeto]],tbl_PlanilhaB[Status],"Não iniciado") -> 0 | R135: =IF(Base_Projetos[[#This Row],[Total de tarefas]]=Base_Projetos[[#This Row],[Tarefas Concluídas]],"Concluído",IF(Base_Projetos[[#This Row],[Tarefas não iniciadas]]=Base_Projetos[[#This Row],[Total de tarefas]],"Não iniciado",IF(Base_Projetos[[#This Row],[Tarefas atrasadas]]>0,"Atrasado","Em andamento"))) -> Concluído | S135: =Base_Projetos[[#This Row],[Tarefas Concluídas]]/Base_Projetos[[#This Row],[Total de tarefas]] -> 1
A136: =A135+1 -> 132 | B136: Peças complemento conj ( pedido Jorge) | C136: Modelagem complementar de uma peça existente | D136: 3- Alta | E136: William Rosa | F136: 1 | G136: =SUMIF(tbl_PlanilhaB[Projeto],Base_Projetos[[#This Row],[Projeto]],tbl_PlanilhaB[Valor previsto]) -> 0 | H136: =SUMIF(tbl_PlanilhaB[Projeto],Base_Projetos[[#This Row],[Projeto]],tbl_PlanilhaB[Valor gasto]) -> 0 | I136: =_xlfn.MINIFS(TAREFAS!E:E,TAREFAS!B:B,Base_Projetos[[#This Row],[Projeto]]) -> 45859 | J136: =_xlfn.MAXIFS(TAREFAS!G:G,TAREFAS!B:B,Base_Projetos[[#This Row],[Projeto]]) -> 45859 | K136: =IF(Base_Projetos[[#This Row],[Total de tarefas]]=Base_Projetos[[#This Row],[Tarefas não iniciadas]],"Não iniciado",_xlfn.MINIFS(TAREFAS!H:H,TAREFAS!B:B,Base_Projetos[[#This Row],[Projeto]])) -> 45859 | L136: =IF(Base_Projetos[[#This Row],[Total de tarefas]]=Base_Projetos[[#This Row],[Tarefas Concluídas]],_xlfn.MAXIFS(TAREFAS!H:H,TAREFAS!B:B,Base_Projetos[[#This Row],[Projeto]]),IF(Base_Projetos[[#This Row],[Total de tarefas]]=Base_Projetos[[#This Row],[Tarefas não iniciadas]],"Não iniciado","Em andamento")) -> 45859 | M136: =SUM(Base_Projetos[[#This Row],[Tarefas Concluídas]:[Tarefas não iniciadas]]) -> 1 | N136: =COUNTIFS(tbl_PlanilhaB[Projeto],Base_Projetos[[#This Row],[Projeto]],tbl_PlanilhaB[Status],"Concluído") -> 1 | O136: =COUNTIFS(tbl_PlanilhaB[Projeto],Base_Projetos[[#This Row],[Projeto]],tbl_PlanilhaB[Status],"Em andamento") -> 0 | P136: =COUNTIFS(tbl_PlanilhaB[Projeto],Base_Projetos[[#This Row],[Projeto]],tbl_PlanilhaB[Status],"Atrasado") -> 0 | Q136: =COUNTIFS(tbl_PlanilhaB[Projeto],Base_Projetos[[#This Row],[Projeto]],tbl_PlanilhaB[Status],"Não iniciado") -> 0 | R136: =IF(Base_Projetos[[#This Row],[Total de tarefas]]=Base_Projetos[[#This Row],[Tarefas Concluídas]],"Concluído",IF(Base_Projetos[[#This Row],[Tarefas não iniciadas]]=Base_Projetos[[#This Row],[Total de tarefas]],"Não iniciado",IF(Base_Projetos[[#This Row],[Tarefas atrasadas]]>0,"Atrasado","Em andamento"))) -> Concluído | S136: =Base_Projetos[[#This Row],[Tarefas Concluídas]]/Base_Projetos[[#This Row],[Total de tarefas]] -> 1
A137: =A136+1 -> 133 | B137: GABARITO CHASSI ROB 10 | C137: redetalhamento e instalação rodizios | D137: 3- Alta | E137: William Rosa | F137: 1 | G137: =SUMIF(tbl_PlanilhaB[Projeto],Base_Projetos[[#This Row],[Projeto]],tbl_PlanilhaB[Valor previsto]) -> 0 | H137: =SUMIF(tbl_PlanilhaB[Projeto],Base_Projetos[[#This Row],[Projeto]],tbl_PlanilhaB[Valor gasto]) -> 0 | I137: =_xlfn.MINIFS(TAREFAS!E:E,TAREFAS!B:B,Base_Projetos[[#This Row],[Projeto]]) -> 45859 | J137: =_xlfn.MAXIFS(TAREFAS!G:G,TAREFAS!B:B,Base_Projetos[[#This Row],[Projeto]]) -> 45866 | K137: =IF(Base_Projetos[[#This Row],[Total de tarefas]]=Base_Projetos[[#This Row],[Tarefas não iniciadas]],"Não iniciado",_xlfn.MINIFS(TAREFAS!H:H,TAREFAS!B:B,Base_Projetos[[#This Row],[Projeto]])) -> 45859 | L137: =IF(Base_Projetos[[#This Row],[Total de tarefas]]=Base_Projetos[[#This Row],[Tarefas Concluídas]],_xlfn.MAXIFS(TAREFAS!H:H,TAREFAS!B:B,Base_Projetos[[#This Row],[Projeto]]),IF(Base_Projetos[[#This Row],[Total de tarefas]]=Base_Projetos[[#This Row],[Tarefas não iniciadas]],"Não iniciado","Em andamento")) -> 45859 | M137: =SUM(Base_Projetos[[#This Row],[Tarefas Concluídas]:[Tarefas não iniciadas]]) -> 1 | N137: =COUNTIFS(tbl_PlanilhaB[Projeto],Base_Projetos[[#This Row],[Projeto]],tbl_PlanilhaB[Status],"Concluído") -> 1 | O137: =COUNTIFS(tbl_PlanilhaB[Projeto],Base_Projetos[[#This Row],[Projeto]],tbl_PlanilhaB[Status],"Em andamento") -> 0 | P137: =COUNTIFS(tbl_PlanilhaB[Projeto],Base_Projetos[[#This Row],[Projeto]],tbl_PlanilhaB[Status],"Atrasado") -> 0 | Q137: =COUNTIFS(tbl_PlanilhaB[Projeto],Base_Projetos[[#This Row],[Projeto]],tbl_PlanilhaB[Status],"Não iniciado") -> 0 | R137: =IF(Base_Projetos[[#This Row],[Total de tarefas]]=Base_Projetos[[#This Row],[Tarefas Concluídas]],"Concluído",IF(Base_Projetos[[#This Row],[Tarefas não iniciadas]]=Base_Projetos[[#This Row],[Total de tarefas]],"Não iniciado",IF(Base_Projetos[[#This Row],[Tarefas atrasadas]]>0,"Atrasado","Em andamento"))) -> Concluído | S137: =Base_Projetos[[#This Row],[Tarefas Concluídas]]/Base_Projetos[[#This Row],[Total de tarefas]] -> 1
A138: =A137+1 -> 134 | B138: Estudo comparativo entre bicos de contato de soldagem para Soldagem Robotizada - Alternativa de fornecimento. | C138: Analisar o desempenho, avaliar utilização e documentar os dados oriundos dos testes realizados com o novo modelo de bico de contato de soldagem proposto. | D138: 3- Alta | E138: Jackson | F138: 1 | G138: =SUMIF(tbl_PlanilhaB[Projeto],Base_Projetos[[#This Row],[Projeto]],tbl_PlanilhaB[Valor previsto]) -> 0 | H138: =SUMIF(tbl_PlanilhaB[Projeto],Base_Projetos[[#This Row],[Projeto]],tbl_PlanilhaB[Valor gasto]) -> 0 | I138: 45868 | J138: 45870 | K138: 45868 | L138: =IF(Base_Projetos[[#This Row],[Total de tarefas]]=Base_Projetos[[#This Row],[Tarefas Concluídas]],_xlfn.MAXIFS(TAREFAS!H:H,TAREFAS!B:B,Base_Projetos[[#This Row],[Projeto]]),IF(Base_Projetos[[#This Row],[Total de tarefas]]=Base_Projetos[[#This Row],[Tarefas não iniciadas]],"Não iniciado","Em andamento")) -> 45875 | M138: =SUM(Base_Projetos[[#This Row],[Tarefas Concluídas]:[Tarefas não iniciadas]]) -> 2 | N138: =COUNTIFS(tbl_PlanilhaB[Projeto],Base_Projetos[[#This Row],[Projeto]],tbl_PlanilhaB[Status],"Concluído") -> 2 | O138: =COUNTIFS(tbl_PlanilhaB[Projeto],Base_Projetos[[#This Row],[Projeto]],tbl_PlanilhaB[Status],"Em andamento") -> 0 | P138: =COUNTIFS(tbl_PlanilhaB[Projeto],Base_Projetos[[#This Row],[Projeto]],tbl_PlanilhaB[Status],"Atrasado") -> 0 | Q138: =COUNTIFS(tbl_PlanilhaB[Projeto],Base_Projetos[[#This Row],[Projeto]],tbl_PlanilhaB[Status],"Não iniciado") -> 0 | R138: =IF(Base_Projetos[[#This Row],[Total de tarefas]]=Base_Projetos[[#This Row],[Tarefas Concluídas]],"Concluído",IF(Base_Projetos[[#This Row],[Tarefas não iniciadas]]=Base_Projetos[[#This Row],[Total de tarefas]],"Não iniciado",IF(Base_Projetos[[#This Row],[Tarefas atrasadas]]>0,"Atrasado","Em andamento"))) -> Concluído | S138: =Base_Projetos[[#This Row],[Tarefas Concluídas]]/Base_Projetos[[#This Row],[Total de tarefas]] -> 1
A139: =A138+1 -> 135 | B139: Mapeamento de interferências no setor da usinagem | C139: Analisar e relacionar os motivos para acontecer os atravessamentos e retrabalho das peças no setor | D139: 2- Média | E139: Victor Canellas | F139: 1 | G139: =SUMIF(tbl_PlanilhaB[Projeto],Base_Projetos[[#This Row],[Projeto]],tbl_PlanilhaB[Valor previsto]) -> 0 | H139: =SUMIF(tbl_PlanilhaB[Projeto],Base_Projetos[[#This Row],[Projeto]],tbl_PlanilhaB[Valor gasto]) -> 0 | I139: =_xlfn.MINIFS(TAREFAS!E:E,TAREFAS!B:B,Base_Projetos[[#This Row],[Projeto]]) -> 45848 | J139: =_xlfn.MAXIFS(TAREFAS!G:G,TAREFAS!B:B,Base_Projetos[[#This Row],[Projeto]]) -> 45862 | K139: =IF(Base_Projetos[[#This Row],[Total de tarefas]]=Base_Projetos[[#This Row],[Tarefas não iniciadas]],"Não iniciado",_xlfn.MINIFS(TAREFAS!H:H,TAREFAS!B:B,Base_Projetos[[#This Row],[Projeto]])) -> 45849 | L139: =IF(Base_Projetos[[#This Row],[Total de tarefas]]=Base_Projetos[[#This Row],[Tarefas Concluídas]],_xlfn.MAXIFS(TAREFAS!H:H,TAREFAS!B:B,Base_Projetos[[#This Row],[Projeto]]),IF(Base_Projetos[[#This Row],[Total de tarefas]]=Base_Projetos[[#This Row],[Tarefas não iniciadas]],"Não iniciado","Em andamento")) -> 45849 | M139: =SUM(Base_Projetos[[#This Row],[Tarefas Concluídas]:[Tarefas não iniciadas]]) -> 1 | N139: =COUNTIFS(tbl_PlanilhaB[Projeto],Base_Projetos[[#This Row],[Projeto]],tbl_PlanilhaB[Status],"Concluído") -> 1 | O139: =COUNTIFS(tbl_PlanilhaB[Projeto],Base_Projetos[[#This Row],[Projeto]],tbl_PlanilhaB[Status],"Em andamento") -> 0 | P139: =COUNTIFS(tbl_PlanilhaB[Projeto],Base_Projetos[[#This Row],[Projeto]],tbl_PlanilhaB[Status],"Atrasado") -> 0 | Q139: =COUNTIFS(tbl_PlanilhaB[Projeto],Base_Projetos[[#This Row],[Projeto]],tbl_PlanilhaB[Status],"Não iniciado") -> 0 | R139: =IF(Base_Projetos[[#This Row],[Total de tarefas]]=Base_Projetos[[#This Row],[Tarefas Concluídas]],"Concluído",IF(Base_Projetos[[#This Row],[Tarefas não iniciadas]]=Base_Projetos[[#This Row],[Total de tarefas]],"Não iniciado",IF(Base_Projetos[[#This Row],[Tarefas atrasadas]]>0,"Atrasado","Em andamento"))) -> Concluído | S139: =Base_Projetos[[#This Row],[Tarefas Concluídas]]/Base_Projetos[[#This Row],[Total de tarefas]] -> 1
A140: =A139+1 -> 136 | B140: Realização do relatório após o mapeamento da usinagem | C140: Montar um relatório detalhando os motivos de haver diversas pausas no setor de usinagem para realização de retrabalhos e atravessamentos que ocorrem no setor | D140: 2- Média | E140: Victor Canellas | F140: 1 | G140: =SUMIF(tbl_PlanilhaB[Projeto],Base_Projetos[[#This Row],[Projeto]],tbl_PlanilhaB[Valor previsto]) -> 0 | H140: =SUMIF(tbl_PlanilhaB[Projeto],Base_Projetos[[#This Row],[Projeto]],tbl_PlanilhaB[Valor gasto]) -> 0 | I140: =_xlfn.MINIFS(TAREFAS!E:E,TAREFAS!B:B,Base_Projetos[[#This Row],[Projeto]]) -> 45863 | J140: =_xlfn.MAXIFS(TAREFAS!G:G,TAREFAS!B:B,Base_Projetos[[#This Row],[Projeto]]) -> 45870 | K140: =IF(Base_Projetos[[#This Row],[Total de tarefas]]=Base_Projetos[[#This Row],[Tarefas não iniciadas]],"Não iniciado",_xlfn.MINIFS(TAREFAS!H:H,TAREFAS!B:B,Base_Projetos[[#This Row],[Projeto]])) -> 45863 | L140: =IF(Base_Projetos[[#This Row],[Total de tarefas]]=Base_Projetos[[#This Row],[Tarefas Concluídas]],_xlfn.MAXIFS(TAREFAS!H:H,TAREFAS!B:B,Base_Projetos[[#This Row],[Projeto]]),IF(Base_Projetos[[#This Row],[Total de tarefas]]=Base_Projetos[[#This Row],[Tarefas não iniciadas]],"Não iniciado","Em andamento")) -> 45863 | M140: =SUM(Base_Projetos[[#This Row],[Tarefas Concluídas]:[Tarefas não iniciadas]]) -> 1 | N140: =COUNTIFS(tbl_PlanilhaB[Projeto],Base_Projetos[[#This Row],[Projeto]],tbl_PlanilhaB[Status],"Concluído") -> 1 | O140: =COUNTIFS(tbl_PlanilhaB[Projeto],Base_Projetos[[#This Row],[Projeto]],tbl_PlanilhaB[Status],"Em andamento") -> 0 | P140: =COUNTIFS(tbl_PlanilhaB[Projeto],Base_Projetos[[#This Row],[Projeto]],tbl_PlanilhaB[Status],"Atrasado") -> 0 | Q140: =COUNTIFS(tbl_PlanilhaB[Projeto],Base_Projetos[[#This Row],[Projeto]],tbl_PlanilhaB[Status],"Não iniciado") -> 0 | R140: =IF(Base_Projetos[[#This Row],[Total de tarefas]]=Base_Projetos[[#This Row],[Tarefas Concluídas]],"Concluído",IF(Base_Projetos[[#This Row],[Tarefas não iniciadas]]=Base_Projetos[[#This Row],[Total de tarefas]],"Não iniciado",IF(Base_Projetos[[#This Row],[Tarefas atrasadas]]>0,"Atrasado","Em andamento"))) -> Concluído | S140: =Base_Projetos[[#This Row],[Tarefas Concluídas]]/Base_Projetos[[#This Row],[Total de tarefas]] -> 1
A141: =A140+1 -> 137 | B141: Análise de Falha das Juntas Soldadas do RF 3900 REXTER | C141: Descobrir casua raiz da falha e propor soluções | D141: 3- Alta | E141: João Calheiros | F141: 1 | G141: =SUMIF(tbl_PlanilhaB[Projeto],Base_Projetos[[#This Row],[Projeto]],tbl_PlanilhaB[Valor previsto]) -> 0 | H141: =SUMIF(tbl_PlanilhaB[Projeto],Base_Projetos[[#This Row],[Projeto]],tbl_PlanilhaB[Valor gasto]) -> 0 | I141: =_xlfn.MINIFS(TAREFAS!E:E,TAREFAS!B:B,Base_Projetos[[#This Row],[Projeto]]) -> 45866 | J141: =_xlfn.MAXIFS(TAREFAS!G:G,TAREFAS!B:B,Base_Projetos[[#This Row],[Projeto]]) -> 45870 | K141: =IF(Base_Projetos[[#This Row],[Total de tarefas]]=Base_Projetos[[#This Row],[Tarefas não iniciadas]],"Não iniciado",_xlfn.MINIFS(TAREFAS!H:H,TAREFAS!B:B,Base_Projetos[[#This Row],[Projeto]])) -> 45866 | L141: =IF(Base_Projetos[[#This Row],[Total de tarefas]]=Base_Projetos[[#This Row],[Tarefas Concluídas]],_xlfn.MAXIFS(TAREFAS!H:H,TAREFAS!B:B,Base_Projetos[[#This Row],[Projeto]]),IF(Base_Projetos[[#This Row],[Total de tarefas]]=Base_Projetos[[#This Row],[Tarefas não iniciadas]],"Não iniciado","Em andamento")) -> 45868 | M141: =SUM(Base_Projetos[[#This Row],[Tarefas Concluídas]:[Tarefas não iniciadas]]) -> 2 | N141: =COUNTIFS(tbl_PlanilhaB[Projeto],Base_Projetos[[#This Row],[Projeto]],tbl_PlanilhaB[Status],"Concluído") -> 2 | O141: =COUNTIFS(tbl_PlanilhaB[Projeto],Base_Projetos[[#This Row],[Projeto]],tbl_PlanilhaB[Status],"Em andamento") -> 0 | P141: =COUNTIFS(tbl_PlanilhaB[Projeto],Base_Projetos[[#This Row],[Projeto]],tbl_PlanilhaB[Status],"Atrasado") -> 0 | Q141: =COUNTIFS(tbl_PlanilhaB[Projeto],Base_Projetos[[#This Row],[Projeto]],tbl_PlanilhaB[Status],"Não iniciado") -> 0 | R141: =IF(Base_Projetos[[#This Row],[Total de tarefas]]=Base_Projetos[[#This Row],[Tarefas Concluídas]],"Concluído",IF(Base_Projetos[[#This Row],[Tarefas não iniciadas]]=Base_Projetos[[#This Row],[Total de tarefas]],"Não iniciado",IF(Base_Projetos[[#This Row],[Tarefas atrasadas]]>0,"Atrasado","Em andamento"))) -> Concluído | S141: =Base_Projetos[[#This Row],[Tarefas Concluídas]]/Base_Projetos[[#This Row],[Total de tarefas]] -> 1
A142: =A141+1 -> 138 | B142: Peças reforma taipadera ( Davi ) | C142: Modelar peças solicitadas pela Direção | D142: 3- Alta | E142: William Rosa | F142: 1 | G142: =SUMIF(tbl_PlanilhaB[Projeto],Base_Projetos[[#This Row],[Projeto]],tbl_PlanilhaB[Valor previsto]) -> 0 | H142: =SUMIF(tbl_PlanilhaB[Projeto],Base_Projetos[[#This Row],[Projeto]],tbl_PlanilhaB[Valor gasto]) -> 0 | I142: =_xlfn.MINIFS(TAREFAS!E:E,TAREFAS!B:B,Base_Projetos[[#This Row],[Projeto]]) -> 45866 | J142: =_xlfn.MAXIFS(TAREFAS!G:G,TAREFAS!B:B,Base_Projetos[[#This Row],[Projeto]]) -> 45867 | K142: =IF(Base_Projetos[[#This Row],[Total de tarefas]]=Base_Projetos[[#This Row],[Tarefas não iniciadas]],"Não iniciado",_xlfn.MINIFS(TAREFAS!H:H,TAREFAS!B:B,Base_Projetos[[#This Row],[Projeto]])) -> 45866 | L142: =IF(Base_Projetos[[#This Row],[Total de tarefas]]=Base_Projetos[[#This Row],[Tarefas Concluídas]],_xlfn.MAXIFS(TAREFAS!H:H,TAREFAS!B:B,Base_Projetos[[#This Row],[Projeto]]),IF(Base_Projetos[[#This Row],[Total de tarefas]]=Base_Projetos[[#This Row],[Tarefas não iniciadas]],"Não iniciado","Em andamento")) -> 45866 | M142: =SUM(Base_Projetos[[#This Row],[Tarefas Concluídas]:[Tarefas não iniciadas]]) -> 1 | N142: =COUNTIFS(tbl_PlanilhaB[Projeto],Base_Projetos[[#This Row],[Projeto]],tbl_PlanilhaB[Status],"Concluído") -> 1 | O142: =COUNTIFS(tbl_PlanilhaB[Projeto],Base_Projetos[[#This Row],[Projeto]],tbl_PlanilhaB[Status],"Em andamento") -> 0 | P142: =COUNTIFS(tbl_PlanilhaB[Projeto],Base_Projetos[[#This Row],[Projeto]],tbl_PlanilhaB[Status],"Atrasado") -> 0 | Q142: =COUNTIFS(tbl_PlanilhaB[Projeto],Base_Projetos[[#This Row],[Projeto]],tbl_PlanilhaB[Status],"Não iniciado") -> 0 | R142: =IF(Base_Projetos[[#This Row],[Total de tarefas]]=Base_Projetos[[#This Row],[Tarefas Concluídas]],"Concluído",IF(Base_Projetos[[#This Row],[Tarefas não iniciadas]]=Base_Projetos[[#This Row],[Total de tarefas]],"Não iniciado",IF(Base_Projetos[[#This Row],[Tarefas atrasadas]]>0,"Atrasado","Em andamento"))) -> Concluído | S142: =Base_Projetos[[#This Row],[Tarefas Concluídas]]/Base_Projetos[[#This Row],[Total de tarefas]] -> 1
A143: =A142+1 -> 139 | B143: Dispositivo para teste eixo Enleirador | C143: Dispositivo para verificação de esforço no eixo, para analise tempera e vazamentos. | D143: 3- Alta | E143: William Rosa | F143: 1 | G143: =SUMIF(tbl_PlanilhaB[Projeto],Base_Projetos[[#This Row],[Projeto]],tbl_PlanilhaB[Valor previsto]) -> 0 | H143: =SUMIF(tbl_PlanilhaB[Projeto],Base_Projetos[[#This Row],[Projeto]],tbl_PlanilhaB[Valor gasto]) -> 0 | I143: =_xlfn.MINIFS(TAREFAS!E:E,TAREFAS!B:B,Base_Projetos[[#This Row],[Projeto]]) -> 45866 | J143: =_xlfn.MAXIFS(TAREFAS!G:G,TAREFAS!B:B,Base_Projetos[[#This Row],[Projeto]]) -> 45873 | K143: =IF(Base_Projetos[[#This Row],[Total de tarefas]]=Base_Projetos[[#This Row],[Tarefas não iniciadas]],"Não iniciado",_xlfn.MINIFS(TAREFAS!H:H,TAREFAS!B:B,Base_Projetos[[#This Row],[Projeto]])) -> 45839 | L143: =IF(Base_Projetos[[#This Row],[Total de tarefas]]=Base_Projetos[[#This Row],[Tarefas Concluídas]],_xlfn.MAXIFS(TAREFAS!H:H,TAREFAS!B:B,Base_Projetos[[#This Row],[Projeto]]),IF(Base_Projetos[[#This Row],[Total de tarefas]]=Base_Projetos[[#This Row],[Tarefas não iniciadas]],"Não iniciado","Em andamento")) -> 45868 | M143: =SUM(Base_Projetos[[#This Row],[Tarefas Concluídas]:[Tarefas não iniciadas]]) -> 4 | N143: =COUNTIFS(tbl_PlanilhaB[Projeto],Base_Projetos[[#This Row],[Projeto]],tbl_PlanilhaB[Status],"Concluído") -> 4 | O143: =COUNTIFS(tbl_PlanilhaB[Projeto],Base_Projetos[[#This Row],[Projeto]],tbl_PlanilhaB[Status],"Em andamento") -> 0 | P143: =COUNTIFS(tbl_PlanilhaB[Projeto],Base_Projetos[[#This Row],[Projeto]],tbl_PlanilhaB[Status],"Atrasado") -> 0 | Q143: =COUNTIFS(tbl_PlanilhaB[Projeto],Base_Projetos[[#This Row],[Projeto]],tbl_PlanilhaB[Status],"Não iniciado") -> 0 | R143: =IF(Base_Projetos[[#This Row],[Total de tarefas]]=Base_Projetos[[#This Row],[Tarefas Concluídas]],"Concluído",IF(Base_Projetos[[#This Row],[Tarefas não iniciadas]]=Base_Projetos[[#This Row],[Total de tarefas]],"Não iniciado",IF(Base_Projetos[[#This Row],[Tarefas atrasadas]]>0,"Atrasado","Em andamento"))) -> Concluído | S143: =Base_Projetos[[#This Row],[Tarefas Concluídas]]/Base_Projetos[[#This Row],[Total de tarefas]] -> 1
A144: =A143+1 -> 140 | B144: Dispositivo para teste Soldagem | C144: Dispositivo para fixação tubo para prova soldagem. | D144: 3- Alta | E144: William Rosa | F144: 1 | G144: =SUMIF(tbl_PlanilhaB[Projeto],Base_Projetos[[#This Row],[Projeto]],tbl_PlanilhaB[Valor previsto]) -> 0 | H144: =SUMIF(tbl_PlanilhaB[Projeto],Base_Projetos[[#This Row],[Projeto]],tbl_PlanilhaB[Valor gasto]) -> 0 | I144: =_xlfn.MINIFS(TAREFAS!E:E,TAREFAS!B:B,Base_Projetos[[#This Row],[Projeto]]) -> 45873 | J144: =_xlfn.MAXIFS(TAREFAS!G:G,TAREFAS!B:B,Base_Projetos[[#This Row],[Projeto]]) -> 45874 | K144: =IF(Base_Projetos[[#This Row],[Total de tarefas]]=Base_Projetos[[#This Row],[Tarefas não iniciadas]],"Não iniciado",_xlfn.MINIFS(TAREFAS!H:H,TAREFAS!B:B,Base_Projetos[[#This Row],[Projeto]])) -> 45873 | L144: =IF(Base_Projetos[[#This Row],[Total de tarefas]]=Base_Projetos[[#This Row],[Tarefas Concluídas]],_xlfn.MAXIFS(TAREFAS!H:H,TAREFAS!B:B,Base_Projetos[[#This Row],[Projeto]]),IF(Base_Projetos[[#This Row],[Total de tarefas]]=Base_Projetos[[#This Row],[Tarefas não iniciadas]],"Não iniciado","Em andamento")) -> 45873 | M144: =SUM(Base_Projetos[[#This Row],[Tarefas Concluídas]:[Tarefas não iniciadas]]) -> 1 | N144: =COUNTIFS(tbl_PlanilhaB[Projeto],Base_Projetos[[#This Row],[Projeto]],tbl_PlanilhaB[Status],"Concluído") -> 1 | O144: =COUNTIFS(tbl_PlanilhaB[Projeto],Base_Projetos[[#This Row],[Projeto]],tbl_PlanilhaB[Status],"Em andamento") -> 0 | P144: =COUNTIFS(tbl_PlanilhaB[Projeto],Base_Projetos[[#This Row],[Projeto]],tbl_PlanilhaB[Status],"Atrasado") -> 0 | Q144: =COUNTIFS(tbl_PlanilhaB[Projeto],Base_Projetos[[#This Row],[Projeto]],tbl_PlanilhaB[Status],"Não iniciado") -> 0 | R144: =IF(Base_Projetos[[#This Row],[Total de tarefas]]=Base_Projetos[[#This Row],[Tarefas Concluídas]],"Concluído",IF(Base_Projetos[[#This Row],[Tarefas não iniciadas]]=Base_Projetos[[#This Row],[Total de tarefas]],"Não iniciado",IF(Base_Projetos[[#This Row],[Tarefas atrasadas]]>0,"Atrasado","Em andamento"))) -> Concluído | S144: =Base_Projetos[[#This Row],[Tarefas Concluídas]]/Base_Projetos[[#This Row],[Total de tarefas]] -> 1
A145: =A144+1 -> 141 | B145: Dispositivo para soldagem de tubo de descarga de graneleiro | C145: modelagem, detalhamento e fabricação de dispositivo para robo de soldagem | D145: 3- Alta | E145: Fagner | F145: 1 | G145: =SUMIF(tbl_PlanilhaB[Projeto],Base_Projetos[[#This Row],[Projeto]],tbl_PlanilhaB[Valor previsto]) -> 0 | H145: =SUMIF(tbl_PlanilhaB[Projeto],Base_Projetos[[#This Row],[Projeto]],tbl_PlanilhaB[Valor gasto]) -> 0 | I145: =_xlfn.MINIFS(TAREFAS!E:E,TAREFAS!B:B,Base_Projetos[[#This Row],[Projeto]]) -> 45846 | J145: =_xlfn.MAXIFS(TAREFAS!G:G,TAREFAS!B:B,Base_Projetos[[#This Row],[Projeto]]) -> 45848 | K145: =IF(Base_Projetos[[#This Row],[Total de tarefas]]=Base_Projetos[[#This Row],[Tarefas não iniciadas]],"Não iniciado",_xlfn.MINIFS(TAREFAS!H:H,TAREFAS!B:B,Base_Projetos[[#This Row],[Projeto]])) -> 45846 | L145: =IF(Base_Projetos[[#This Row],[Total de tarefas]]=Base_Projetos[[#This Row],[Tarefas Concluídas]],_xlfn.MAXIFS(TAREFAS!H:H,TAREFAS!B:B,Base_Projetos[[#This Row],[Projeto]]),IF(Base_Projetos[[#This Row],[Total de tarefas]]=Base_Projetos[[#This Row],[Tarefas não iniciadas]],"Não iniciado","Em andamento")) -> 45846 | M145: =SUM(Base_Projetos[[#This Row],[Tarefas Concluídas]:[Tarefas não iniciadas]]) -> 1 | N145: =COUNTIFS(tbl_PlanilhaB[Projeto],Base_Projetos[[#This Row],[Projeto]],tbl_PlanilhaB[Status],"Concluído") -> 1 | O145: =COUNTIFS(tbl_PlanilhaB[Projeto],Base_Projetos[[#This Row],[Projeto]],tbl_PlanilhaB[Status],"Em andamento") -> 0 | P145: =COUNTIFS(tbl_PlanilhaB[Projeto],Base_Projetos[[#This Row],[Projeto]],tbl_PlanilhaB[Status],"Atrasado") -> 0 | Q145: =COUNTIFS(tbl_PlanilhaB[Projeto],Base_Projetos[[#This Row],[Projeto]],tbl_PlanilhaB[Status],"Não iniciado") -> 0 | R145: =IF(Base_Projetos[[#This Row],[Total de tarefas]]=Base_Projetos[[#This Row],[Tarefas Concluídas]],"Concluído",IF(Base_Projetos[[#This Row],[Tarefas não iniciadas]]=Base_Projetos[[#This Row],[Total de tarefas]],"Não iniciado",IF(Base_Projetos[[#This Row],[Tarefas atrasadas]]>0,"Atrasado","Em andamento"))) -> Concluído | S145: =Base_Projetos[[#This Row],[Tarefas Concluídas]]/Base_Projetos[[#This Row],[Total de tarefas]] -> 1
A146: =A145+1 -> 142 | B146: Simulação carga exportação Argentina | C146: Modelagem e detalhamento do layout das peças da maquina dispostas na prancha do caminhão junto com a disposição das peças sobressalentes na caixa de kit de reposição | D146: 3- Alta | E146: Fagner | F146: 1 | G146: =SUMIF(tbl_PlanilhaB[Projeto],Base_Projetos[[#This Row],[Projeto]],tbl_PlanilhaB[Valor previsto]) -> 0 | H146: =SUMIF(tbl_PlanilhaB[Projeto],Base_Projetos[[#This Row],[Projeto]],tbl_PlanilhaB[Valor gasto]) -> 0 | I146: =_xlfn.MINIFS(TAREFAS!E:E,TAREFAS!B:B,Base_Projetos[[#This Row],[Projeto]]) -> 45848 | J146: =_xlfn.MAXIFS(TAREFAS!G:G,TAREFAS!B:B,Base_Projetos[[#This Row],[Projeto]]) -> 45856 | K146: =IF(Base_Projetos[[#This Row],[Total de tarefas]]=Base_Projetos[[#This Row],[Tarefas não iniciadas]],"Não iniciado",_xlfn.MINIFS(TAREFAS!H:H,TAREFAS!B:B,Base_Projetos[[#This Row],[Projeto]])) -> 45848 | L146: =IF(Base_Projetos[[#This Row],[Total de tarefas]]=Base_Projetos[[#This Row],[Tarefas Concluídas]],_xlfn.MAXIFS(TAREFAS!H:H,TAREFAS!B:B,Base_Projetos[[#This Row],[Projeto]]),IF(Base_Projetos[[#This Row],[Total de tarefas]]=Base_Projetos[[#This Row],[Tarefas não iniciadas]],"Não iniciado","Em andamento")) -> 45848 | M146: =SUM(Base_Projetos[[#This Row],[Tarefas Concluídas]:[Tarefas não iniciadas]]) -> 1 | N146: =COUNTIFS(tbl_PlanilhaB[Projeto],Base_Projetos[[#This Row],[Projeto]],tbl_PlanilhaB[Status],"Concluído") -> 1 | O146: =COUNTIFS(tbl_PlanilhaB[Projeto],Base_Projetos[[#This Row],[Projeto]],tbl_PlanilhaB[Status],"Em andamento") -> 0 | P146: =COUNTIFS(tbl_PlanilhaB[Projeto],Base_Projetos[[#This Row],[Projeto]],tbl_PlanilhaB[Status],"Atrasado") -> 0 | Q146: =COUNTIFS(tbl_PlanilhaB[Projeto],Base_Projetos[[#This Row],[Projeto]],tbl_PlanilhaB[Status],"Não iniciado") -> 0 | R146: =IF(Base_Projetos[[#This Row],[Total de tarefas]]=Base_Projetos[[#This Row],[Tarefas Concluídas]],"Concluído",IF(Base_Projetos[[#This Row],[Tarefas não iniciadas]]=Base_Projetos[[#This Row],[Total de tarefas]],"Não iniciado",IF(Base_Projetos[[#This Row],[Tarefas atrasadas]]>0,"Atrasado","Em andamento"))) -> Concluído | S146: =Base_Projetos[[#This Row],[Tarefas Concluídas]]/Base_Projetos[[#This Row],[Total de tarefas]] -> 1
A147: =A146+1 -> 143 | B147: Roldana para bandeja de maquina do corte laser | C147: modelar, detalhar e fabricar roldanas para substituir as que sao usadas nas bandejas que recolhem metal derretido das maquinas de corte | D147: 3- Alta | E147: Fagner | F147: 1 | G147: =SUMIF(tbl_PlanilhaB[Projeto],Base_Projetos[[#This Row],[Projeto]],tbl_PlanilhaB[Valor previsto]) -> 0 | H147: =SUMIF(tbl_PlanilhaB[Projeto],Base_Projetos[[#This Row],[Projeto]],tbl_PlanilhaB[Valor gasto]) -> 0 | I147: =_xlfn.MINIFS(TAREFAS!E:E,TAREFAS!B:B,Base_Projetos[[#This Row],[Projeto]]) -> 45856 | J147: =_xlfn.MAXIFS(TAREFAS!G:G,TAREFAS!B:B,Base_Projetos[[#This Row],[Projeto]]) -> 45859 | K147: =IF(Base_Projetos[[#This Row],[Total de tarefas]]=Base_Projetos[[#This Row],[Tarefas não iniciadas]],"Não iniciado",_xlfn.MINIFS(TAREFAS!H:H,TAREFAS!B:B,Base_Projetos[[#This Row],[Projeto]])) -> 45856 | L147: =IF(Base_Projetos[[#This Row],[Total de tarefas]]=Base_Projetos[[#This Row],[Tarefas Concluídas]],_xlfn.MAXIFS(TAREFAS!H:H,TAREFAS!B:B,Base_Projetos[[#This Row],[Projeto]]),IF(Base_Projetos[[#This Row],[Total de tarefas]]=Base_Projetos[[#This Row],[Tarefas não iniciadas]],"Não iniciado","Em andamento")) -> 45856 | M147: =SUM(Base_Projetos[[#This Row],[Tarefas Concluídas]:[Tarefas não iniciadas]]) -> 1 | N147: =COUNTIFS(tbl_PlanilhaB[Projeto],Base_Projetos[[#This Row],[Projeto]],tbl_PlanilhaB[Status],"Concluído") -> 1 | O147: =COUNTIFS(tbl_PlanilhaB[Projeto],Base_Projetos[[#This Row],[Projeto]],tbl_PlanilhaB[Status],"Em andamento") -> 0 | P147: =COUNTIFS(tbl_PlanilhaB[Projeto],Base_Projetos[[#This Row],[Projeto]],tbl_PlanilhaB[Status],"Atrasado") -> 0 | Q147: =COUNTIFS(tbl_PlanilhaB[Projeto],Base_Projetos[[#This Row],[Projeto]],tbl_PlanilhaB[Status],"Não iniciado") -> 0 | R147: =IF(Base_Projetos[[#This Row],[Total de tarefas]]=Base_Projetos[[#This Row],[Tarefas Concluídas]],"Concluído",IF(Base_Projetos[[#This Row],[Tarefas não iniciadas]]=Base_Projetos[[#This Row],[Total de tarefas]],"Não iniciado",IF(Base_Projetos[[#This Row],[Tarefas atrasadas]]>0,"Atrasado","Em andamento"))) -> Concluído | S147: =Base_Projetos[[#This Row],[Tarefas Concluídas]]/Base_Projetos[[#This Row],[Total de tarefas]] -> 1
A148: =A147+1 -> 144 | B148: Alteração de gabarito plaina multilaminas linha leve | C148: modelagem, detalhamento e fabricação e de torre nova para gabarito do carro dianteiro da linha leve | D148: 3- Alta | E148: Fagner | F148: 1 | G148: =SUMIF(tbl_PlanilhaB[Projeto],Base_Projetos[[#This Row],[Projeto]],tbl_PlanilhaB[Valor previsto]) -> 0 | H148: =SUMIF(tbl_PlanilhaB[Projeto],Base_Projetos[[#This Row],[Projeto]],tbl_PlanilhaB[Valor gasto]) -> 0 | I148: =_xlfn.MINIFS(TAREFAS!E:E,TAREFAS!B:B,Base_Projetos[[#This Row],[Projeto]]) -> 45859 | J148: =_xlfn.MAXIFS(TAREFAS!G:G,TAREFAS!B:B,Base_Projetos[[#This Row],[Projeto]]) -> 45866 | K148: =IF(Base_Projetos[[#This Row],[Total de tarefas]]=Base_Projetos[[#This Row],[Tarefas não iniciadas]],"Não iniciado",_xlfn.MINIFS(TAREFAS!H:H,TAREFAS!B:B,Base_Projetos[[#This Row],[Projeto]])) -> 45859 | L148: =IF(Base_Projetos[[#This Row],[Total de tarefas]]=Base_Projetos[[#This Row],[Tarefas Concluídas]],_xlfn.MAXIFS(TAREFAS!H:H,TAREFAS!B:B,Base_Projetos[[#This Row],[Projeto]]),IF(Base_Projetos[[#This Row],[Total de tarefas]]=Base_Projetos[[#This Row],[Tarefas não iniciadas]],"Não iniciado","Em andamento")) -> 45859 | M148: =SUM(Base_Projetos[[#This Row],[Tarefas Concluídas]:[Tarefas não iniciadas]]) -> 1 | N148: =COUNTIFS(tbl_PlanilhaB[Projeto],Base_Projetos[[#This Row],[Projeto]],tbl_PlanilhaB[Status],"Concluído") -> 1 | O148: =COUNTIFS(tbl_PlanilhaB[Projeto],Base_Projetos[[#This Row],[Projeto]],tbl_PlanilhaB[Status],"Em andamento") -> 0 | P148: =COUNTIFS(tbl_PlanilhaB[Projeto],Base_Projetos[[#This Row],[Projeto]],tbl_PlanilhaB[Status],"Atrasado") -> 0 | Q148: =COUNTIFS(tbl_PlanilhaB[Projeto],Base_Projetos[[#This Row],[Projeto]],tbl_PlanilhaB[Status],"Não iniciado") -> 0 | R148: =IF(Base_Projetos[[#This Row],[Total de tarefas]]=Base_Projetos[[#This Row],[Tarefas Concluídas]],"Concluído",IF(Base_Projetos[[#This Row],[Tarefas não iniciadas]]=Base_Projetos[[#This Row],[Total de tarefas]],"Não iniciado",IF(Base_Projetos[[#This Row],[Tarefas atrasadas]]>0,"Atrasado","Em andamento"))) -> Concluído | S148: =Base_Projetos[[#This Row],[Tarefas Concluídas]]/Base_Projetos[[#This Row],[Total de tarefas]] -> 1
A149: =A148+1 -> 145 | B149: Dispositivo de soldagem torre carro dianteiro linha leve | C149: modelar, detalhar e fabricar dispositivo de gabarito para soldagem de torre do carro dianteiro da linha leve | D149: 3- Alta | E149: Fagner | F149: 1 | G149: =SUMIF(tbl_PlanilhaB[Projeto],Base_Projetos[[#This Row],[Projeto]],tbl_PlanilhaB[Valor previsto]) -> 0 | H149: =SUMIF(tbl_PlanilhaB[Projeto],Base_Projetos[[#This Row],[Projeto]],tbl_PlanilhaB[Valor gasto]) -> 0 | I149: =_xlfn.MINIFS(TAREFAS!E:E,TAREFAS!B:B,Base_Projetos[[#This Row],[Projeto]]) -> 45866 | J149: =_xlfn.MAXIFS(TAREFAS!G:G,TAREFAS!B:B,Base_Projetos[[#This Row],[Projeto]]) -> 45869 | K149: =IF(Base_Projetos[[#This Row],[Total de tarefas]]=Base_Projetos[[#This Row],[Tarefas não iniciadas]],"Não iniciado",_xlfn.MINIFS(TAREFAS!H:H,TAREFAS!B:B,Base_Projetos[[#This Row],[Projeto]])) -> 45866 | L149: =IF(Base_Projetos[[#This Row],[Total de tarefas]]=Base_Projetos[[#This Row],[Tarefas Concluídas]],_xlfn.MAXIFS(TAREFAS!H:H,TAREFAS!B:B,Base_Projetos[[#This Row],[Projeto]]),IF(Base_Projetos[[#This Row],[Total de tarefas]]=Base_Projetos[[#This Row],[Tarefas não iniciadas]],"Não iniciado","Em andamento")) -> 45866 | M149: =SUM(Base_Projetos[[#This Row],[Tarefas Concluídas]:[Tarefas não iniciadas]]) -> 1 | N149: =COUNTIFS(tbl_PlanilhaB[Projeto],Base_Projetos[[#This Row],[Projeto]],tbl_PlanilhaB[Status],"Concluído") -> 1 | O149: =COUNTIFS(tbl_PlanilhaB[Projeto],Base_Projetos[[#This Row],[Projeto]],tbl_PlanilhaB[Status],"Em andamento") -> 0 | P149: =COUNTIFS(tbl_PlanilhaB[Projeto],Base_Projetos[[#This Row],[Projeto]],tbl_PlanilhaB[Status],"Atrasado") -> 0 | Q149: =COUNTIFS(tbl_PlanilhaB[Projeto],Base_Projetos[[#This Row],[Projeto]],tbl_PlanilhaB[Status],"Não iniciado") -> 0 | R149: =IF(Base_Projetos[[#This Row],[Total de tarefas]]=Base_Projetos[[#This Row],[Tarefas Concluídas]],"Concluído",IF(Base_Projetos[[#This Row],[Tarefas não iniciadas]]=Base_Projetos[[#This Row],[Total de tarefas]],"Não iniciado",IF(Base_Projetos[[#This Row],[Tarefas atrasadas]]>0,"Atrasado","Em andamento"))) -> Concluído | S149: =Base_Projetos[[#This Row],[Tarefas Concluídas]]/Base_Projetos[[#This Row],[Total de tarefas]] -> 1
A150: =A149+1 -> 146 | B150: simulação de carga de caixa de madeira | C150: simulação de carga de caixa de madeira com uma AGRIVAL 60L e mais caixa de itens de reposição. | D150: 3- Alta | E150: Fagner | F150: 1 | G150: =SUMIF(tbl_PlanilhaB[Projeto],Base_Projetos[[#This Row],[Projeto]],tbl_PlanilhaB[Valor previsto]) -> 0 | H150: =SUMIF(tbl_PlanilhaB[Projeto],Base_Projetos[[#This Row],[Projeto]],tbl_PlanilhaB[Valor gasto]) -> 0 | I150: =_xlfn.MINIFS(TAREFAS!E:E,TAREFAS!B:B,Base_Projetos[[#This Row],[Projeto]]) -> 45869 | J150: =_xlfn.MAXIFS(TAREFAS!G:G,TAREFAS!B:B,Base_Projetos[[#This Row],[Projeto]]) -> 45874 | K150: =IF(Base_Projetos[[#This Row],[Total de tarefas]]=Base_Projetos[[#This Row],[Tarefas não iniciadas]],"Não iniciado",_xlfn.MINIFS(TAREFAS!H:H,TAREFAS!B:B,Base_Projetos[[#This Row],[Projeto]])) -> 45869 | L150: =IF(Base_Projetos[[#This Row],[Total de tarefas]]=Base_Projetos[[#This Row],[Tarefas Concluídas]],_xlfn.MAXIFS(TAREFAS!H:H,TAREFAS!B:B,Base_Projetos[[#This Row],[Projeto]]),IF(Base_Projetos[[#This Row],[Total de tarefas]]=Base_Projetos[[#This Row],[Tarefas não iniciadas]],"Não iniciado","Em andamento")) -> 45869 | M150: =SUM(Base_Projetos[[#This Row],[Tarefas Concluídas]:[Tarefas não iniciadas]]) -> 1 | N150: =COUNTIFS(tbl_PlanilhaB[Projeto],Base_Projetos[[#This Row],[Projeto]],tbl_PlanilhaB[Status],"Concluído") -> 1 | O150: =COUNTIFS(tbl_PlanilhaB[Projeto],Base_Projetos[[#This Row],[Projeto]],tbl_PlanilhaB[Status],"Em andamento") -> 0 | P150: =COUNTIFS(tbl_PlanilhaB[Projeto],Base_Projetos[[#This Row],[Projeto]],tbl_PlanilhaB[Status],"Atrasado") -> 0 | Q150: =COUNTIFS(tbl_PlanilhaB[Projeto],Base_Projetos[[#This Row],[Projeto]],tbl_PlanilhaB[Status],"Não iniciado") -> 0 | R150: =IF(Base_Projetos[[#This Row],[Total de tarefas]]=Base_Projetos[[#This Row],[Tarefas Concluídas]],"Concluído",IF(Base_Projetos[[#This Row],[Tarefas não iniciadas]]=Base_Projetos[[#This Row],[Total de tarefas]],"Não iniciado",IF(Base_Projetos[[#This Row],[Tarefas atrasadas]]>0,"Atrasado","Em andamento"))) -> Concluído | S150: =Base_Projetos[[#This Row],[Tarefas Concluídas]]/Base_Projetos[[#This Row],[Total de tarefas]] -> 1
... A173: =A172+1 -> 169 | B173: Tabela para orçamento cilindros novos Oldra : CJ0285 CJ0415 CJ0134 CJ0129 CJ0761 CJ0121 CJ0142 | C173: Revisão das vedações | D173: 3- Alta | E173: William Rosa | F173: 1 | G173: =SUMIF(tbl_PlanilhaB[Projeto],Base_Projetos[[#This Row],[Projeto]],tbl_PlanilhaB[Valor previsto]) -> 0 | H173: =SUMIF(tbl_PlanilhaB[Projeto],Base_Projetos[[#This Row],[Projeto]],tbl_PlanilhaB[Valor gasto]) -> 0 | I173: =_xlfn.MINIFS(TAREFAS!E:E,TAREFAS!B:B,Base_Projetos[[#This Row],[Projeto]]) -> 45905 | J173: =_xlfn.MAXIFS(TAREFAS!G:G,TAREFAS!B:B,Base_Projetos[[#This Row],[Projeto]]) -> 45908 | K173: =IF(Base_Projetos[[#This Row],[Total de tarefas]]=Base_Projetos[[#This Row],[Tarefas não iniciadas]],"Não iniciado",_xlfn.MINIFS(TAREFAS!H:H,TAREFAS!B:B,Base_Projetos[[#This Row],[Projeto]])) -> 45905 | L173: =IF(Base_Projetos[[#This Row],[Total de tarefas]]=Base_Projetos[[#This Row],[Tarefas Concluídas]],_xlfn.MAXIFS(TAREFAS!H:H,TAREFAS!B:B,Base_Projetos[[#This Row],[Projeto]]),IF(Base_Projetos[[#This Row],[Total de tarefas]]=Base_Projetos[[#This Row],[Tarefas não iniciadas]],"Não iniciado","Em andamento")) -> 45905 | M173: =SUM(Base_Projetos[[#This Row],[Tarefas Concluídas]:[Tarefas não iniciadas]]) -> 1 | N173: =COUNTIFS(tbl_PlanilhaB[Projeto],Base_Projetos[[#This Row],[Projeto]],tbl_PlanilhaB[Status],"Concluído") -> 1 | O173: =COUNTIFS(tbl_PlanilhaB[Projeto],Base_Projetos[[#This Row],[Projeto]],tbl_PlanilhaB[Status],"Em andamento") -> 0 | P173: =COUNTIFS(tbl_PlanilhaB[Projeto],Base_Projetos[[#This Row],[Projeto]],tbl_PlanilhaB[Status],"Atrasado") -> 0 | Q173: =COUNTIFS(tbl_PlanilhaB[Projeto],Base_Projetos[[#This Row],[Projeto]],tbl_PlanilhaB[Status],"Não iniciado") -> 0 | R173: =IF(Base_Projetos[[#This Row],[Total de tarefas]]=Base_Projetos[[#This Row],[Tarefas Concluídas]],"Concluído",IF(Base_Projetos[[#This Row],[Tarefas não iniciadas]]=Base_Projetos[[#This Row],[Total de tarefas]],"Não iniciado",IF(Base_Projetos[[#This Row],[Tarefas atrasadas]]>0,"Atrasado","Em andamento"))) -> Concluído | S173: =Base_Projetos[[#This Row],[Tarefas Concluídas]]/Base_Projetos[[#This Row],[Total de tarefas]] -> 1
A174: 170 | B174: Seminário Powermig e Lincoln Electric | C174: Visita ao seminário de soldagem para análise de produtos e tecnologias atuais que podemos vir a adquirir e que oferecem vantagens competivivas. | D174: 3- Alta | E174: João Calheiros | F174: 1 | G174: =SUMIF(tbl_PlanilhaB[Projeto],Base_Projetos[[#This Row],[Projeto]],tbl_PlanilhaB[Valor previsto]) -> 0 | H174: =SUMIF(tbl_PlanilhaB[Projeto],Base_Projetos[[#This Row],[Projeto]],tbl_PlanilhaB[Valor gasto]) -> 0 | I174: =_xlfn.MINIFS(TAREFAS!E:E,TAREFAS!B:B,Base_Projetos[[#This Row],[Projeto]]) -> 45888 | J174: =_xlfn.MAXIFS(TAREFAS!G:G,TAREFAS!B:B,Base_Projetos[[#This Row],[Projeto]]) -> 45895 | K174: =IF(Base_Projetos[[#This Row],[Total de tarefas]]=Base_Projetos[[#This Row],[Tarefas não iniciadas]],"Não iniciado",_xlfn.MINIFS(TAREFAS!H:H,TAREFAS!B:B,Base_Projetos[[#This Row],[Projeto]])) -> 45888 | L174: =IF(Base_Projetos[[#This Row],[Total de tarefas]]=Base_Projetos[[#This Row],[Tarefas Concluídas]],_xlfn.MAXIFS(TAREFAS!H:H,TAREFAS!B:B,Base_Projetos[[#This Row],[Projeto]]),IF(Base_Projetos[[#This Row],[Total de tarefas]]=Base_Projetos[[#This Row],[Tarefas não iniciadas]],"Não iniciado","Em andamento")) -> 45891 | M174: =SUM(Base_Projetos[[#This Row],[Tarefas Concluídas]:[Tarefas não iniciadas]]) -> 3 | N174: =COUNTIFS(tbl_PlanilhaB[Projeto],Base_Projetos[[#This Row],[Projeto]],tbl_PlanilhaB[Status],"Concluído") -> 3 | O174: =COUNTIFS(tbl_PlanilhaB[Projeto],Base_Projetos[[#This Row],[Projeto]],tbl_PlanilhaB[Status],"Em andamento") -> 0 | P174: =COUNTIFS(tbl_PlanilhaB[Projeto],Base_Projetos[[#This Row],[Projeto]],tbl_PlanilhaB[Status],"Atrasado") -> 0 | Q174: =COUNTIFS(tbl_PlanilhaB[Projeto],Base_Projetos[[#This Row],[Projeto]],tbl_PlanilhaB[Status],"Não iniciado") -> 0 | R174: =IF(Base_Projetos[[#This Row],[Total de tarefas]]=Base_Projetos[[#This Row],[Tarefas Concluídas]],"Concluído",IF(Base_Projetos[[#This Row],[Tarefas não iniciadas]]=Base_Projetos[[#This Row],[Total de tarefas]],"Não iniciado",IF(Base_Projetos[[#This Row],[Tarefas atrasadas]]>0,"Atrasado","Em andamento"))) -> Concluído | S174: =Base_Projetos[[#This Row],[Tarefas Concluídas]]/Base_Projetos[[#This Row],[Total de tarefas]] -> 1
A175: 171 | B175: Aplicativo Registrador de Atividades | C175: Desenvolvimento de Aplicação para Controle de Atividades na Engenharia de Processos. | D175: 2- Média | E175: João Calheiros | F175: 1 | G175: =SUMIF(tbl_PlanilhaB[Projeto],Base_Projetos[[#This Row],[Projeto]],tbl_PlanilhaB[Valor previsto]) -> 0 | H175: =SUMIF(tbl_PlanilhaB[Projeto],Base_Projetos[[#This Row],[Projeto]],tbl_PlanilhaB[Valor gasto]) -> 0 | I175: =_xlfn.MINIFS(TAREFAS!E:E,TAREFAS!B:B,Base_Projetos[[#This Row],[Projeto]]) -> 45901 | J175: =_xlfn.MAXIFS(TAREFAS!G:G,TAREFAS!B:B,Base_Projetos[[#This Row],[Projeto]]) -> 45930 | K175: =IF(Base_Projetos[[#This Row],[Total de tarefas]]=Base_Projetos[[#This Row],[Tarefas não iniciadas]],"Não iniciado",_xlfn.MINIFS(TAREFAS!H:H,TAREFAS!B:B,Base_Projetos[[#This Row],[Projeto]])) -> 45901 | L175: =IF(Base_Projetos[[#This Row],[Total de tarefas]]=Base_Projetos[[#This Row],[Tarefas Concluídas]],_xlfn.MAXIFS(TAREFAS!H:H,TAREFAS!B:B,Base_Projetos[[#This Row],[Projeto]]),IF(Base_Projetos[[#This Row],[Total de tarefas]]=Base_Projetos[[#This Row],[Tarefas não iniciadas]],"Não iniciado","Em andamento")) -> 45929 | M175: =SUM(Base_Projetos[[#This Row],[Tarefas Concluídas]:[Tarefas não iniciadas]]) -> 3 | N175: =COUNTIFS(tbl_PlanilhaB[Projeto],Base_Projetos[[#This Row],[Projeto]],tbl_PlanilhaB[Status],"Concluído") -> 3 | O175: =COUNTIFS(tbl_PlanilhaB[Projeto],Base_Projetos[[#This Row],[Projeto]],tbl_PlanilhaB[Status],"Em andamento") -> 0 | P175: =COUNTIFS(tbl_PlanilhaB[Projeto],Base_Projetos[[#This Row],[Projeto]],tbl_PlanilhaB[Status],"Atrasado") -> 0 | Q175: =COUNTIFS(tbl_PlanilhaB[Projeto],Base_Projetos[[#This Row],[Projeto]],tbl_PlanilhaB[Status],"Não iniciado") -> 0 | R175: =IF(Base_Projetos[[#This Row],[Total de tarefas]]=Base_Projetos[[#This Row],[Tarefas Concluídas]],"Concluído",IF(Base_Projetos[[#This Row],[Tarefas não iniciadas]]=Base_Projetos[[#This Row],[Total de tarefas]],"Não iniciado",IF(Base_Projetos[[#This Row],[Tarefas atrasadas]]>0,"Atrasado","Em andamento"))) -> Concluído | S175: =Base_Projetos[[#This Row],[Tarefas Concluídas]]/Base_Projetos[[#This Row],[Total de tarefas]] -> 1
A176: 172 | B176: Qualificação Soldador Emerson | C176: Projeto piloto para Treinamento de Soldadores | D176: 3- Alta | E176: João Calheiros | F176: 1 | G176: =SUMIF(tbl_PlanilhaB[Projeto],Base_Projetos[[#This Row],[Projeto]],tbl_PlanilhaB[Valor previsto]) -> 0 | H176: =SUMIF(tbl_PlanilhaB[Projeto],Base_Projetos[[#This Row],[Projeto]],tbl_PlanilhaB[Valor gasto]) -> 0 | I176: =_xlfn.MINIFS(TAREFAS!E:E,TAREFAS!B:B,Base_Projetos[[#This Row],[Projeto]]) -> 45895 | J176: =_xlfn.MAXIFS(TAREFAS!G:G,TAREFAS!B:B,Base_Projetos[[#This Row],[Projeto]]) -> 45911 | K176: =IF(Base_Projetos[[#This Row],[Total de tarefas]]=Base_Projetos[[#This Row],[Tarefas não iniciadas]],"Não iniciado",_xlfn.MINIFS(TAREFAS!H:H,TAREFAS!B:B,Base_Projetos[[#This Row],[Projeto]])) -> 45895 | L176: =IF(Base_Projetos[[#This Row],[Total de tarefas]]=Base_Projetos[[#This Row],[Tarefas Concluídas]],_xlfn.MAXIFS(TAREFAS!H:H,TAREFAS!B:B,Base_Projetos[[#This Row],[Projeto]]),IF(Base_Projetos[[#This Row],[Total de tarefas]]=Base_Projetos[[#This Row],[Tarefas não iniciadas]],"Não iniciado","Em andamento")) -> 45909 | M176: =SUM(Base_Projetos[[#This Row],[Tarefas Concluídas]:[Tarefas não iniciadas]]) -> 6 | N176: =COUNTIFS(tbl_PlanilhaB[Projeto],Base_Projetos[[#This Row],[Projeto]],tbl_PlanilhaB[Status],"Concluído") -> 6 | O176: =COUNTIFS(tbl_PlanilhaB[Projeto],Base_Projetos[[#This Row],[Projeto]],tbl_PlanilhaB[Status],"Em andamento") -> 0 | P176: =COUNTIFS(tbl_PlanilhaB[Projeto],Base_Projetos[[#This Row],[Projeto]],tbl_PlanilhaB[Status],"Atrasado") -> 0 | Q176: =COUNTIFS(tbl_PlanilhaB[Projeto],Base_Projetos[[#This Row],[Projeto]],tbl_PlanilhaB[Status],"Não iniciado") -> 0 | R176: =IF(Base_Projetos[[#This Row],[Total de tarefas]]=Base_Projetos[[#This Row],[Tarefas Concluídas]],"Concluído",IF(Base_Projetos[[#This Row],[Tarefas não iniciadas]]=Base_Projetos[[#This Row],[Total de tarefas]],"Não iniciado",IF(Base_Projetos[[#This Row],[Tarefas atrasadas]]>0,"Atrasado","Em andamento"))) -> Concluído | S176: =Base_Projetos[[#This Row],[Tarefas Concluídas]]/Base_Projetos[[#This Row],[Total de tarefas]] -> 1
A177: =A176+1 -> 173 | B177: Revisão da tabela de orçamento para clientes SANIG e SCHMERKEL | C177: Revisado todas as vedações e componentes | D177: 3- Alta | E177: William Rosa | F177: 1 | G177: =SUMIF(tbl_PlanilhaB[Projeto],Base_Projetos[[#This Row],[Projeto]],tbl_PlanilhaB[Valor previsto]) -> 0 | H177: =SUMIF(tbl_PlanilhaB[Projeto],Base_Projetos[[#This Row],[Projeto]],tbl_PlanilhaB[Valor gasto]) -> 0 | I177: =_xlfn.MINIFS(TAREFAS!E:E,TAREFAS!B:B,Base_Projetos[[#This Row],[Projeto]]) -> 45910 | J177: =_xlfn.MAXIFS(TAREFAS!G:G,TAREFAS!B:B,Base_Projetos[[#This Row],[Projeto]]) -> 45911 | K177: =IF(Base_Projetos[[#This Row],[Total de tarefas]]=Base_Projetos[[#This Row],[Tarefas não iniciadas]],"Não iniciado",_xlfn.MINIFS(TAREFAS!H:H,TAREFAS!B:B,Base_Projetos[[#This Row],[Projeto]])) -> 45910 | L177: =IF(Base_Projetos[[#This Row],[Total de tarefas]]=Base_Projetos[[#This Row],[Tarefas Concluídas]],_xlfn.MAXIFS(TAREFAS!H:H,TAREFAS!B:B,Base_Projetos[[#This Row],[Projeto]]),IF(Base_Projetos[[#This Row],[Total de tarefas]]=Base_Projetos[[#This Row],[Tarefas não iniciadas]],"Não iniciado","Em andamento")) -> 45910 | M177: =SUM(Base_Projetos[[#This Row],[Tarefas Concluídas]:[Tarefas não iniciadas]]) -> 1 | N177: =COUNTIFS(tbl_PlanilhaB[Projeto],Base_Projetos[[#This Row],[Projeto]],tbl_PlanilhaB[Status],"Concluído") -> 1 | O177: =COUNTIFS(tbl_PlanilhaB[Projeto],Base_Projetos[[#This Row],[Projeto]],tbl_PlanilhaB[Status],"Em andamento") -> 0 | P177: =COUNTIFS(tbl_PlanilhaB[Projeto],Base_Projetos[[#This Row],[Projeto]],tbl_PlanilhaB[Status],"Atrasado") -> 0 | Q177: =COUNTIFS(tbl_PlanilhaB[Projeto],Base_Projetos[[#This Row],[Projeto]],tbl_PlanilhaB[Status],"Não iniciado") -> 0 | R177: =IF(Base_Projetos[[#This Row],[Total de tarefas]]=Base_Projetos[[#This Row],[Tarefas Concluídas]],"Concluído",IF(Base_Projetos[[#This Row],[Tarefas não iniciadas]]=Base_Projetos[[#This Row],[Total de tarefas]],"Não iniciado",IF(Base_Projetos[[#This Row],[Tarefas atrasadas]]>0,"Atrasado","Em andamento"))) -> Concluído | S177: =Base_Projetos[[#This Row],[Tarefas Concluídas]]/Base_Projetos[[#This Row],[Total de tarefas]] -> 1
A178: =A177+1 -> 174 | B178: Elaboração de instrução de trabalho. IT_PRO_XX_REGISTRO DE TEMPOS E EVENTOS -SOLDAGEM ROBOTIZADA | C178: Elaboração de instrução de trabalho para o registro de tempos e eventos no setor de Soldagem Robotizada. | D178: 3- Alta | E178: Jackson | F178: 1 | G178: =SUMIF(tbl_PlanilhaB[Projeto],Base_Projetos[[#This Row],[Projeto]],tbl_PlanilhaB[Valor previsto]) -> 0 | H178: =SUMIF(tbl_PlanilhaB[Projeto],Base_Projetos[[#This Row],[Projeto]],tbl_PlanilhaB[Valor gasto]) -> 0 | I178: =_xlfn.MINIFS(TAREFAS!E:E,TAREFAS!B:B,Base_Projetos[[#This Row],[Projeto]]) -> 45915 | J178: =_xlfn.MAXIFS(TAREFAS!G:G,TAREFAS!B:B,Base_Projetos[[#This Row],[Projeto]]) -> 45916 | K178: =IF(Base_Projetos[[#This Row],[Total de tarefas]]=Base_Projetos[[#This Row],[Tarefas não iniciadas]],"Não iniciado",_xlfn.MINIFS(TAREFAS!H:H,TAREFAS!B:B,Base_Projetos[[#This Row],[Projeto]])) -> 45915 | L178: =IF(Base_Projetos[[#This Row],[Total de tarefas]]=Base_Projetos[[#This Row],[Tarefas Concluídas]],_xlfn.MAXIFS(TAREFAS!H:H,TAREFAS!B:B,Base_Projetos[[#This Row],[Projeto]]),IF(Base_Projetos[[#This Row],[Total de tarefas]]=Base_Projetos[[#This Row],[Tarefas não iniciadas]],"Não iniciado","Em andamento")) -> 45915 | M178: =SUM(Base_Projetos[[#This Row],[Tarefas Concluídas]:[Tarefas não iniciadas]]) -> 1 | N178: =COUNTIFS(tbl_PlanilhaB[Projeto],Base_Projetos[[#This Row],[Projeto]],tbl_PlanilhaB[Status],"Concluído") -> 1 | O178: =COUNTIFS(tbl_PlanilhaB[Projeto],Base_Projetos[[#This Row],[Projeto]],tbl_PlanilhaB[Status],"Em andamento") -> 0 | P178: =COUNTIFS(tbl_PlanilhaB[Projeto],Base_Projetos[[#This Row],[Projeto]],tbl_PlanilhaB[Status],"Atrasado") -> 0 | Q178: =COUNTIFS(tbl_PlanilhaB[Projeto],Base_Projetos[[#This Row],[Projeto]],tbl_PlanilhaB[Status],"Não iniciado") -> 0 | R178: =IF(Base_Projetos[[#This Row],[Total de tarefas]]=Base_Projetos[[#This Row],[Tarefas Concluídas]],"Concluído",IF(Base_Projetos[[#This Row],[Tarefas não iniciadas]]=Base_Projetos[[#This Row],[Total de tarefas]],"Não iniciado",IF(Base_Projetos[[#This Row],[Tarefas atrasadas]]>0,"Atrasado","Em andamento"))) -> Concluído | S178: =Base_Projetos[[#This Row],[Tarefas Concluídas]]/Base_Projetos[[#This Row],[Total de tarefas]] -> 1
A179: =A178+1 -> 175 | B179: Elaboração de Instrução de trabalho. IT_PRO_XX_REGISTRO DE TEMPOS DE PARADA DE PRODUÇÃO - SOLDAGEM ROBOTIZADA. | C179: Elaboração de instrução de trabalho para o registro de tempos de parada de produção. | D179: 3- Alta | E179: Jackson | F179: 1 | G179: =SUMIF(tbl_PlanilhaB[Projeto],Base_Projetos[[#This Row],[Projeto]],tbl_PlanilhaB[Valor previsto]) -> 0 | H179: =SUMIF(tbl_PlanilhaB[Projeto],Base_Projetos[[#This Row],[Projeto]],tbl_PlanilhaB[Valor gasto]) -> 0 | I179: =_xlfn.MINIFS(TAREFAS!E:E,TAREFAS!B:B,Base_Projetos[[#This Row],[Projeto]]) -> 45922 | J179: =_xlfn.MAXIFS(TAREFAS!G:G,TAREFAS!B:B,Base_Projetos[[#This Row],[Projeto]]) -> 45923 | K179: =IF(Base_Projetos[[#This Row],[Total de tarefas]]=Base_Projetos[[#This Row],[Tarefas não iniciadas]],"Não iniciado",_xlfn.MINIFS(TAREFAS!H:H,TAREFAS!B:B,Base_Projetos[[#This Row],[Projeto]])) -> 45922 | L179: =IF(Base_Projetos[[#This Row],[Total de tarefas]]=Base_Projetos[[#This Row],[Tarefas Concluídas]],_xlfn.MAXIFS(TAREFAS!H:H,TAREFAS!B:B,Base_Projetos[[#This Row],[Projeto]]),IF(Base_Projetos[[#This Row],[Total de tarefas]]=Base_Projetos[[#This Row],[Tarefas não iniciadas]],"Não iniciado","Em andamento")) -> 45922 | M179: =SUM(Base_Projetos[[#This Row],[Tarefas Concluídas]:[Tarefas não iniciadas]]) -> 1 | N179: =COUNTIFS(tbl_PlanilhaB[Projeto],Base_Projetos[[#This Row],[Projeto]],tbl_PlanilhaB[Status],"Concluído") -> 1 | O179: =COUNTIFS(tbl_PlanilhaB[Projeto],Base_Projetos[[#This Row],[Projeto]],tbl_PlanilhaB[Status],"Em andamento") -> 0 | P179: =COUNTIFS(tbl_PlanilhaB[Projeto],Base_Projetos[[#This Row],[Projeto]],tbl_PlanilhaB[Status],"Atrasado") -> 0 | Q179: =COUNTIFS(tbl_PlanilhaB[Projeto],Base_Projetos[[#This Row],[Projeto]],tbl_PlanilhaB[Status],"Não iniciado") -> 0 | R179: =IF(Base_Projetos[[#This Row],[Total de tarefas]]=Base_Projetos[[#This Row],[Tarefas Concluídas]],"Concluído",IF(Base_Projetos[[#This Row],[Tarefas não iniciadas]]=Base_Projetos[[#This Row],[Total de tarefas]],"Não iniciado",IF(Base_Projetos[[#This Row],[Tarefas atrasadas]]>0,"Atrasado","Em andamento"))) -> Concluído | S179: =Base_Projetos[[#This Row],[Tarefas Concluídas]]/Base_Projetos[[#This Row],[Total de tarefas]] -> 1
A180: =A179+1 -> 176 | B180: Treinamento dos líderes sobre normatização de soldagem | C180: Conscientiar sobre a normatização, alinhar sobre os procedimentos e atribuições dos líderes, inpetores e soldadores no programa de soldagem. | D180: 3- Alta | E180: João Calheiros | F180: 1 | G180: =SUMIF(tbl_PlanilhaB[Projeto],Base_Projetos[[#This Row],[Projeto]],tbl_PlanilhaB[Valor previsto]) -> 0 | H180: =SUMIF(tbl_PlanilhaB[Projeto],Base_Projetos[[#This Row],[Projeto]],tbl_PlanilhaB[Valor gasto]) -> 0 | I180: =_xlfn.MINIFS(TAREFAS!E:E,TAREFAS!B:B,Base_Projetos[[#This Row],[Projeto]]) -> 45931 | J180: =_xlfn.MAXIFS(TAREFAS!G:G,TAREFAS!B:B,Base_Projetos[[#This Row],[Projeto]]) -> 45936 | K180: =IF(Base_Projetos[[#This Row],[Total de tarefas]]=Base_Projetos[[#This Row],[Tarefas não iniciadas]],"Não iniciado",_xlfn.MINIFS(TAREFAS!H:H,TAREFAS!B:B,Base_Projetos[[#This Row],[Projeto]])) -> 45931 | L180: =IF(Base_Projetos[[#This Row],[Total de tarefas]]=Base_Projetos[[#This Row],[Tarefas Concluídas]],_xlfn.MAXIFS(TAREFAS!H:H,TAREFAS!B:B,Base_Projetos[[#This Row],[Projeto]]),IF(Base_Projetos[[#This Row],[Total de tarefas]]=Base_Projetos[[#This Row],[Tarefas não iniciadas]],"Não iniciado","Em andamento")) -> 45933 | M180: =SUM(Base_Projetos[[#This Row],[Tarefas Concluídas]:[Tarefas não iniciadas]]) -> 3 | N180: =COUNTIFS(tbl_PlanilhaB[Projeto],Base_Projetos[[#This Row],[Projeto]],tbl_PlanilhaB[Status],"Concluído") -> 3 | O180: =COUNTIFS(tbl_PlanilhaB[Projeto],Base_Projetos[[#This Row],[Projeto]],tbl_PlanilhaB[Status],"Em andamento") -> 0 | P180: =COUNTIFS(tbl_PlanilhaB[Projeto],Base_Projetos[[#This Row],[Projeto]],tbl_PlanilhaB[Status],"Atrasado") -> 0 | Q180: =COUNTIFS(tbl_PlanilhaB[Projeto],Base_Projetos[[#This Row],[Projeto]],tbl_PlanilhaB[Status],"Não iniciado") -> 0 | R180: =IF(Base_Projetos[[#This Row],[Total de tarefas]]=Base_Projetos[[#This Row],[Tarefas Concluídas]],"Concluído",IF(Base_Projetos[[#This Row],[Tarefas não iniciadas]]=Base_Projetos[[#This Row],[Total de tarefas]],"Não iniciado",IF(Base_Projetos[[#This Row],[Tarefas atrasadas]]>0,"Atrasado","Em andamento"))) -> Concluído | S180: =Base_Projetos[[#This Row],[Tarefas Concluídas]]/Base_Projetos[[#This Row],[Total de tarefas]] -> 1
A181: =A180+1 -> 177 | B181: Reforma gabarito caçamba cata pedra | C181: atualização de gabarito | D181: 2- Média | E181: Fagner | F181: 1 | G181: =SUMIF(tbl_PlanilhaB[Projeto],Base_Projetos[[#This Row],[Projeto]],tbl_PlanilhaB[Valor previsto]) -> 0 | H181: =SUMIF(tbl_PlanilhaB[Projeto],Base_Projetos[[#This Row],[Projeto]],tbl_PlanilhaB[Valor gasto]) -> 0 | I181: =_xlfn.MINIFS(TAREFAS!E:E,TAREFAS!B:B,Base_Projetos[[#This Row],[Projeto]]) -> 45911 | J181: =_xlfn.MAXIFS(TAREFAS!G:G,TAREFAS!B:B,Base_Projetos[[#This Row],[Projeto]]) -> 45968 | K181: =IF(Base_Projetos[[#This Row],[Total de tarefas]]=Base_Projetos[[#This Row],[Tarefas não iniciadas]],"Não iniciado",_xlfn.MINIFS(TAREFAS!H:H,TAREFAS!B:B,Base_Projetos[[#This Row],[Projeto]])) -> 45911 | L181: =IF(Base_Projetos[[#This Row],[Total de tarefas]]=Base_Projetos[[#This Row],[Tarefas Concluídas]],_xlfn.MAXIFS(TAREFAS!H:H,TAREFAS!B:B,Base_Projetos[[#This Row],[Projeto]]),IF(Base_Projetos[[#This Row],[Total de tarefas]]=Base_Projetos[[#This Row],[Tarefas não iniciadas]],"Não iniciado","Em andamento")) -> Em andamento | M181: =SUM(Base_Projetos[[#This Row],[Tarefas Concluídas]:[Tarefas não iniciadas]]) -> 8 | N181: =COUNTIFS(tbl_PlanilhaB[Projeto],Base_Projetos[[#This Row],[Projeto]],tbl_PlanilhaB[Status],"Concluído") -> 7 | O181: =COUNTIFS(tbl_PlanilhaB[Projeto],Base_Projetos[[#This Row],[Projeto]],tbl_PlanilhaB[Status],"Em andamento") -> 0 | P181: =COUNTIFS(tbl_PlanilhaB[Projeto],Base_Projetos[[#This Row],[Projeto]],tbl_PlanilhaB[Status],"Atrasado") -> 1 | Q181: =COUNTIFS(tbl_PlanilhaB[Projeto],Base_Projetos[[#This Row],[Projeto]],tbl_PlanilhaB[Status],"Não iniciado") -> 0 | R181: =IF(Base_Projetos[[#This Row],[Total de tarefas]]=Base_Projetos[[#This Row],[Tarefas Concluídas]],"Concluído",IF(Base_Projetos[[#This Row],[Tarefas não iniciadas]]=Base_Projetos[[#This Row],[Total de tarefas]],"Não iniciado",IF(Base_Projetos[[#This Row],[Tarefas atrasadas]]>0,"Atrasado","Em andamento"))) -> Atrasado | S181: =Base_Projetos[[#This Row],[Tarefas Concluídas]]/Base_Projetos[[#This Row],[Total de tarefas]] -> 0.875
